Workbook

Sheet Sheet2
A3: Type | B3: Count of Type
A4: Length Mismatch | B4: 21
A5: Similarity Score Issue | B5: 6
A6: Success | B6: 20
A7: Syntax Error | B7: 10

Sheet Sheet3
A3: Row Labels | B3: Count of Details
A4: Length Mismatch | B4: 21
A5: Target1_13 | B5: 1
A6: Target1_18 | B6: 1
A7: Target1_22 | B7: 1
A8: Target1_24 | B8: 1
A9: Target1_27 | B9: 1
A10: Target1_41 | B10: 1
A11: Target1_43 | B11: 1
A12: Target1_46 | B12: 1
A13: Target1_48 | B13: 1
A14: Target1_52 | B14: 1
A15: Target1_53 | B15: 1
... A27: Target1_10 | B27: 1
A28: Target1_16
A29: Target1_23 | B29: 1
A30: Target1_62 | B30: 1
A31: Target1_86 | B31: 1
A32: Target1_97 | B32: 1
A33: Success | B33: 20
A34: Syntax Error | B34: 10
A35: Target1_40 | B35: 1
A36: Target1_44 | B36: 1
A37: Target1_59 | B37: 1
A38: Target1_78 | B38: 1
A39: Target1_88 | B39: 1
A40: Target1_89 | B40: 1
... A44: Target1_93 | B44: 1
A45: (blank)
A46: (blank)
A47: Grand Total | B47: 56

Sheet Sheet4
A3: Row Labels | B3: Count of After Fix
A4: Bad Case - task makes no sense | B4: 2
A5: Failed - did not figured out | B5: 1
A6: Failed - failed to aggregate - low entropy - data type change | B6: 2
A7: Failed - failed to aggregate - low entropy - domain knowledge | B7: 10
A8: Failed - failed to aggregate - low entropy - domain knowledge - hard (newest date) | B8: 1
A9: Failed - failed to aggregate - low entropy - domain knowledge/ did not do count | B9: 1
A10: Need Domain Knowledge - Aggregation function | B10: 2
A11: Need Domain Knowledge - Aggregation target | B11: 1
A12: Need Domain Knowledge - expectation/ count on which | B12: 1
A13: Need Domain Knowledge - Rare case/ expectation | B13: 1
A14: Need Domain Knowledge - Use Aggregation or not | B14: 1
A15: Success | B15: 26
... A20: Success* bad test case : Dec_2012 vs Dec_2013 | B20: 2
A21: (blank)
A22: Grand Total | B22: 57
A29: Bad Case - task makes no sense | B29: 2
A30: Failed - did not figured out | B30: 1 | E30: 1
A31: Failed - failed to aggregate - low entropy - data type change | B31: 2 | E31: 2
A32: Failed - failed to aggregate - low entropy - domain knowledge | B32: 10 | E32: 10
A33: Failed - failed to aggregate - low entropy - domain knowledge - hard (newest date) | B33: 1 | E33: 1
A34: Failed - failed to aggregate - low entropy - domain knowledge/ did not do count | B34: 1 | E34: 1
A35: Need Domain Knowledge - Aggregation function | B35: 2 | E35: 2 | H35: before fix 20/57 | I35: =20/57 -> 0.35087719
A36: Need Domain Knowledge - Aggregation target | B36: 1 | E36: 1
A37: Need Domain Knowledge - expectation/ count on which | B37: 1 | E37: 1
A38: Need Domain Knowledge - Rare case/ expectation | B38: 1 | E38: 1 | H38: Bad Case - task makes no sense | I38: 2
A39: Need Domain Knowledge - Use Aggregation or not | B39: 1 | E39: 1 | H39: Domain Knolwedge needed/ likely to be success when Domain Knoledge is provided | I39: =SUM(E30:E39) -> 21
A40: Success | B40: 26 | D40: 26 | H40: Success | I40: =SUM(D40:D45) -> 34
A41: Success - next iteration | B41: 3 | D41: 3
A42: Success* grouped by continent - did not remove the empty conservation_status - I would not call this failed.. | B42: 1 | D42: 1 | H42: 34/(21+34） | I42: =34/ (34+21) -> 0.61818182
A43: Success* grouped by continent - did not remove the empty continent - I would not call this failed.. | B43: 1 | D43: 1
A44: Success* grouped by continent - did not remove the empty fac_type - I would not call this failed.. | B44: 1 | D44: 1
A45: Success* bad test case : Dec_2012 vs Dec_2013 | B45: 2 | D45: 2

Sheet Sheet6
A3: Row Labels | B3: Count of overall_big_prompt_no_fewshot_no_detailed intruction
A4: Bad Case - task makes no sense v.s. Failed | B4: 2
A5: Target1_44 | B5: 1
A6: Target1_89 | B6: 1
A7: Failed - did not figured out v.s. Failed | B7: 1
A8: Target1_99 | B8: 1
A9: Failed - failed to aggregate - low entropy - data type change v.s. Failed | B9: 2
A10: Target1_43 | B10: 1
A11: Target1_52 | B11: 1
A12: Failed - failed to aggregate - low entropy - domain knowledge - hard (newest date) v.s. Failed | B12: 1
A13: Target1_95 | B13: 1
A14: Failed - failed to aggregate - low entropy - domain knowledge v.s. Failed | B14: 8
A15: Target1_18 | B15: 1
... A35: Target1_97 | B35: 1
A36: Need Domain Knowledge - Rare case/ expectation v.s. Failed | B36: 1 | E36: 1 | H36: one-big-prompt | I36: =32/(21+34) -> 0.58181818
A37: Target1_90 | B37: 1 | E37: 1 | H37: react | I37: =34/(21+34) -> 0.61818182
A38: Need Domain Knowledge - Use Aggregation or not v.s. Failed | B38: 1 | E38: 6
A39: Target1_78 | B39: 1 | E39: 1
A40: Success - next iteration v.s. Failed | B40: 1
A41: Target1_93 | B41: 1
A42: Success - next iteration v.s. Success | B42: 2
A43: Target1_10 | B43: 1
A44: Target1_92 | B44: 1 | D44: success -> failed | E44: 4 | F44: 2 | G44: failed -> success
A45: Success v.s. Failed | B45: 3 | E45: Target1_72 | F45: Target1_61
A46: Target1_72 | B46: 1 | E46: Target1_84 | F46: Target1_97
A47: Target1_84 | B47: 1 | E47: Target1_88
A48: Target1_88 | B48: 1 | E48: Target1_93
A49: Success v.s. Failed - DID NOT DO SUBSTRING --> Success | B49: 1
A50: Target1_68 | B50: 1
A51: Success v.s. Failed --> Success | B51: 5
A52: Target1_34 | B52: 1
A53: Target1_35 | B53: 1
A54: Target1_38 | B54: 1
A55: Target1_6 | B55: 1
A56: Target1_80 | B56: 1
A57: Success v.s. Failed* VERY CLOSE.. CHECK | B57: 1 | I57: Target1_6
A58: Target1_55 | B58: 1 | I58: Target1_35
A59: Success v.s. Success | B59: 11 | I59: Target1_40
A60: Target1_11 | B60: 1 | I60: Target1_57
A61: Target1_20 | B61: 1 | I61: Target1_91
A62: Target1_21 | B62: 1
A63: Target1_29 | B63: 1
A64: Target1_3 | B64: 1
A65: Target1_4 | B65: 1
A66: Target1_60 | B66: 1
A67: Target1_62 | B67: 1
A68: Target1_65 | B68: 1
A69: Target1_67 | B69: 1
A70: Target1_71 | B70: 1
A71: Success* grouped by continent - did not remove the empty conservation_status - I would not call this failed.. v.s. Success* | B71: 1
A72: Target1_82 | B72: 1
A73: Success* grouped by continent - did not remove the empty continent - I would not call this failed.. v.s. Success* | B73: 1
... A78: Target1_48 | B78: 1
A79: (blank)
A80: (blank)
A81: Success - preprocessing v.s. Failed - syntax --> Success | B81: 1
A82: Target1_16 | B82: 1
A83: Success - preprocessing v.s. Failed --> Success - takes more itr? | B83: 1
A84: Target1_40 | B84: 1
A85: Success v.s. Failed --> Success-itr2 | B85: 1
A86: Target1_57 | B86: 1
A87: Success - preprocessing v.s. Success | B87: 1
A88: Target1_59 | B88: 1
A89: Success* bad test case : Dec_2012 vs Dec_2013 v.s. Failed --> Success* bad test case : Dec_2012 vs Dec_2013 | B89: 1
A90: Target1_46 | B90: 1
A91: Success - next iteration v.s. GUESS IT CAN SUCCESS --> Success | B91: 1
A92: Target1_91 | B92: 1
A93: Grand Total | B93: 57

Sheet Sheet1
A1: Target | B1: Success Once | C1: React - After Fix | D1: Ankita's baseline without target samples | E1: Ankita's baseline with target samples | F1: one_big_prompt | G1: one_big_prompt_5itrs | H1: overall_big_prompt_no_fewshot_no_detailed intruction | J1: Type | K1: Details
A2: Target1_3 | B2: Success | C2: Success | D2: =VLOOKUP(Sheet1!A2,Sheet5!B$1:AA$613,26,FALSE) -> 0 | E2: =VLOOKUP(Sheet1!A2,Sheet5!B$1:AA$613,25,FALSE) -> success | F2: Success | G2: Success | H2: =C2 & " v.s. " & IF(AND(NOT(ISBLANK(F2)), NOT(ISBLANK(G2))), F2 & " --> " & G2, F2 & G2) -> Success v.s. Success --> Success | J2: Success | K2: Execution successful without errors.
A3: Target1_4 | B3: Success | C3: Success | D3: =VLOOKUP(Sheet1!A3,Sheet5!B$1:AA$613,26,FALSE) -> success | E3: =VLOOKUP(Sheet1!A3,Sheet5!B$1:AA$613,25,FALSE) -> success | F3: Success | G3: Success | H3: =C3 & " v.s. " & IF(AND(NOT(ISBLANK(F3)), NOT(ISBLANK(G3))), F3 & " --> " & G3, F3 & G3) -> Success v.s. Success --> Success | J3: Success | K3: Execution successful without errors.
A4: Target1_6 | B4: Success | C4: Success | D4: =VLOOKUP(Sheet1!A4,Sheet5!B$1:AA$613,26,FALSE) -> failed | E4: =VLOOKUP(Sheet1!A4,Sheet5!B$1:AA$613,25,FALSE) -> failed | F4: Failed | G4: Success | H4: =C4 & " v.s. " & IF(AND(NOT(ISBLANK(F4)), NOT(ISBLANK(G4))), F4 & " --> " & G4, F4 & G4) -> Success v.s. Failed --> Success | I4: ['Mismatch - DataFrames lengths differ (100000 vs 3164)'] | J4: Success | K4: Execution successful without errors.
A5: Target1_9 | B5: Failed | C5: Need Domain Knowledge - Aggregation target | D5: =VLOOKUP(Sheet1!A5,Sheet5!B$1:AA$613,26,FALSE) -> #N/A | E5: =VLOOKUP(Sheet1!A5,Sheet5!B$1:AA$613,25,FALSE) -> #N/A | F5: Failed | G5: Need Domain Knowledge | H5: =C5 & " v.s. " & IF(AND(NOT(ISBLANK(F5)), NOT(ISBLANK(G5))), F5 & " --> " & G5, F5 & G5) -> Need Domain Knowledge - Aggregation target v.s. Failed --> Need Domain Knowledge | I5: Error in the previous response: Error: ERROR: syntax error at or near ")" LINE 20: ); ^ | J5: Length Mismatch | K5: Mismatch - Lists lengths differ'
A6: Target1_10 | B6: Failed | C6: Success - next iteration | D6: =VLOOKUP(Sheet1!A6,Sheet5!B$1:AA$613,26,FALSE) -> failed | E6: =VLOOKUP(Sheet1!A6,Sheet5!B$1:AA$613,25,FALSE) -> succes | F6: Success | G6: Success | H6: =C6 & " v.s. " & IF(AND(NOT(ISBLANK(F6)), NOT(ISBLANK(G6))), F6 & " --> " & G6, F6 & G6) -> Success - next iteration v.s. Success --> Success | J6: Similarity Score Issue | K6: Scores: 1.0, 0.9982; Case accuracy: 1.00 | L6: ['Column 2: None vs 0']
A7: Target1_11 | B7: Success | C7: Success | D7: =VLOOKUP(Sheet1!A7,Sheet5!B$1:AA$613,26,FALSE) -> failed | E7: =VLOOKUP(Sheet1!A7,Sheet5!B$1:AA$613,25,FALSE) -> failed | F7: Success | G7: Success | H7: =C7 & " v.s. " & IF(AND(NOT(ISBLANK(F7)), NOT(ISBLANK(G7))), F7 & " --> " & G7, F7 & G7) -> Success v.s. Success --> Success | J7: Success | K7: Execution successful without errors.
A8: Target1_13 | B8: Failed | C8: Failed - failed to aggregate - low entropy - domain knowledge | D8: =VLOOKUP(Sheet1!A8,Sheet5!B$1:AA$613,26,FALSE) -> failed | E8: =VLOOKUP(Sheet1!A8,Sheet5!B$1:AA$613,25,FALSE) -> failed | F8: Failed | G8: Need Domain Knowledge | H8: =C8 & " v.s. " & IF(AND(NOT(ISBLANK(F8)), NOT(ISBLANK(G8))), F8 & " --> " & G8, F8 & G8) -> Failed - failed to aggregate - low entropy - domain knowledge v.s. Failed --> Need Domain Knowledge | I8: ['Mismatch - DataFrames lengths differ (122 vs 4)'] | J8: Length Mismatch | K8: Mismatch - Lists lengths differ'
A9: Target1_16 | B9: Failed | C9: Success - preprocessing | D9: =VLOOKUP(Sheet1!A9,Sheet5!B$1:AA$613,26,FALSE) -> failed | E9: =VLOOKUP(Sheet1!A9,Sheet5!B$1:AA$613,25,FALSE) -> Still failed even after clean.py pre processing | F9: Failed - syntax | G9: Success | H9: =C9 & " v.s. " & IF(AND(NOT(ISBLANK(F9)), NOT(ISBLANK(G9))), F9 & " --> " & G9, F9 & G9) -> Success - preprocessing v.s. Failed - syntax --> Success | I9: Error in the previous response: Error: ERROR: invalid input syntax for type integer: "ORDERNUMBER" CONTEXT: COPY Source1_16_0, line 1, column ORDERNUMBER: "ORDERNUMBER" | J9: Similarity Score Issue
A10: Target1_18 | B10: Failed | C10: Failed - failed to aggregate - low entropy - domain knowledge | D10: =VLOOKUP(Sheet1!A10,Sheet5!B$1:AA$613,26,FALSE) -> failed | E10: =VLOOKUP(Sheet1!A10,Sheet5!B$1:AA$613,25,FALSE) -> failed | F10: Failed | G10: Need Domain Knowledge | H10: =C10 & " v.s. " & IF(AND(NOT(ISBLANK(F10)), NOT(ISBLANK(G10))), F10 & " --> " & G10, F10 & G10) -> Failed - failed to aggregate - low entropy - domain knowledge v.s. Failed --> Need Domain Knowledge | I10: ['Mismatch - DataFrames lengths differ (75 vs 2)'] | J10: Length Mismatch | K10: Mismatch - Lists lengths differ'
A11: Target1_20 | B11: Success | C11: Success | D11: =VLOOKUP(Sheet1!A11,Sheet5!B$1:AA$613,26,FALSE) -> failed | E11: =VLOOKUP(Sheet1!A11,Sheet5!B$1:AA$613,25,FALSE) -> failed | F11: Success | G11: Success | H11: =C11 & " v.s. " & IF(AND(NOT(ISBLANK(F11)), NOT(ISBLANK(G11))), F11 & " --> " & G11, F11 & G11) -> Success v.s. Success --> Success | J11: Success | K11: Execution successful without errors.
A12: Target1_21 | B12: Success | C12: Success | D12: =VLOOKUP(Sheet1!A12,Sheet5!B$1:AA$613,26,FALSE) -> failed | E12: =VLOOKUP(Sheet1!A12,Sheet5!B$1:AA$613,25,FALSE) -> success | F12: Success | G12: Success | H12: =C12 & " v.s. " & IF(AND(NOT(ISBLANK(F12)), NOT(ISBLANK(G12))), F12 & " --> " & G12, F12 & G12) -> Success v.s. Success --> Success | J12: Success | K12: Execution successful without errors.
A13: Target1_22 | B13: Failed | C13: Failed - failed to aggregate - low entropy - domain knowledge | D13: =VLOOKUP(Sheet1!A13,Sheet5!B$1:AA$613,26,FALSE) -> failed | E13: =VLOOKUP(Sheet1!A13,Sheet5!B$1:AA$613,25,FALSE) -> failed | F13: Failed | G13: Need Domain Knowledge | H13: =C13 & " v.s. " & IF(AND(NOT(ISBLANK(F13)), NOT(ISBLANK(G13))), F13 & " --> " & G13, F13 & G13) -> Failed - failed to aggregate - low entropy - domain knowledge v.s. Failed --> Need Domain Knowledge | I13: ['Mismatch - DataFrames lengths differ (4 vs 2)'] | J13: Length Mismatch | K13: Mismatch - Lists lengths differ'
A14: Target1_23 | B14: Failed | C14: Need Domain Knowledge - Aggregation function | D14: =VLOOKUP(Sheet1!A14,Sheet5!B$1:AA$613,26,FALSE) -> failed | E14: =VLOOKUP(Sheet1!A14,Sheet5!B$1:AA$613,25,FALSE) -> failed | F14: Failed | G14: Need Domain Knowledge | H14: =C14 & " v.s. " & IF(AND(NOT(ISBLANK(F14)), NOT(ISBLANK(G14))), F14 & " --> " & G14, F14 & G14) -> Need Domain Knowledge - Aggregation function v.s. Failed --> Need Domain Knowledge | I14: Error in the previous response: Error: ERROR: invalid input syntax for type integer: "customer_id" CONTEXT: COPY Source1_23_0, line 1, column customer_id: "customer_id" | J14: Similarity Score Issue | K14: Scores: 1.0, 0.5758; Case accuracy: 0.79 | L14: too long to list, refer to 'revised_finish_1.log'
A15: Target1_24 | B15: Failed | C15: Failed - failed to aggregate - low entropy - domain knowledge | D15: =VLOOKUP(Sheet1!A15,Sheet5!B$1:AA$613,26,FALSE) -> #N/A | E15: =VLOOKUP(Sheet1!A15,Sheet5!B$1:AA$613,25,FALSE) -> #N/A | F15: Failed | G15: Need Domain Knowledge | H15: =C15 & " v.s. " & IF(AND(NOT(ISBLANK(F15)), NOT(ISBLANK(G15))), F15 & " --> " & G15, F15 & G15) -> Failed - failed to aggregate - low entropy - domain knowledge v.s. Failed --> Need Domain Knowledge | I15: Error in the previous response: Error: ERROR: cannot subscript type numeric because it does not support subscripting LINE 31: SELECT unnest[1]::DECIMAL AS "condition", unnest[2]::DECIMAL… | J15: Length Mismatch | K15: Mismatch - Lists lengths differ'
A16: Target1_27 | B16: Failed | C16: Failed - failed to aggregate - low entropy - domain knowledge | D16: =VLOOKUP(Sheet1!A16,Sheet5!B$1:AA$613,26,FALSE) -> failed | E16: =VLOOKUP(Sheet1!A16,Sheet5!B$1:AA$613,25,FALSE) -> failed | F16: Failed | G16: Need Domain Knowledge | H16: =C16 & " v.s. " & IF(AND(NOT(ISBLANK(F16)), NOT(ISBLANK(G16))), F16 & " --> " & G16, F16 & G16) -> Failed - failed to aggregate - low entropy - domain knowledge v.s. Failed --> Need Domain Knowledge | I16: ['Mismatch - DataFrames lengths differ (21324 vs 7)']. | J16: Length Mismatch | K16: Mismatch - Lists lengths differ'
A17: Target1_29 | B17: Success | C17: Success | D17: =VLOOKUP(Sheet1!A17,Sheet5!B$1:AA$613,26,FALSE) -> failed | E17: =VLOOKUP(Sheet1!A17,Sheet5!B$1:AA$613,25,FALSE) -> success | F17: Success | G17: Success | H17: =C17 & " v.s. " & IF(AND(NOT(ISBLANK(F17)), NOT(ISBLANK(G17))), F17 & " --> " & G17, F17 & G17) -> Success v.s. Success --> Success | J17: Success | K17: Execution successful without errors.
A18: Target1_34 | B18: Success | C18: Success | D18: =VLOOKUP(Sheet1!A18,Sheet5!B$1:AA$613,26,FALSE) -> success | E18: =VLOOKUP(Sheet1!A18,Sheet5!B$1:AA$613,25,FALSE) -> success | F18: Failed | G18: Success | H18: =C18 & " v.s. " & IF(AND(NOT(ISBLANK(F18)), NOT(ISBLANK(G18))), F18 & " --> " & G18, F18 & G18) -> Success v.s. Failed --> Success | I18: Error in the previous response: Error: ERROR: invalid input syntax for type json DETAIL: Token "J_CALL" is invalid. CONTEXT: JSON data, line 1: J_CALL COPY Source1_34_0, line 1, column J_CALL: "J_CALL" | J18: Success | K18: Malformed array literal 'IGHJ5*02'; Execution successful without errors. | L18: Error in the previous response: Error: ERROR: malformed array literal: "IGHJ5*02" DETAIL: Array value must start with "{" or dimension information. CONTEXT: COPY source1_34_0, line 2, column j_call: "IGHJ5*02"
A19: Target1_35 | B19: Success | C19: Success | D19: =VLOOKUP(Sheet1!A19,Sheet5!B$1:AA$613,26,FALSE) -> 0 | E19: =VLOOKUP(Sheet1!A19,Sheet5!B$1:AA$613,25,FALSE) -> failed | F19: Failed | G19: Success | H19: =C19 & " v.s. " & IF(AND(NOT(ISBLANK(F19)), NOT(ISBLANK(G19))), F19 & " --> " & G19, F19 & G19) -> Success v.s. Failed --> Success | I19: ['Mismatch - DataFrames lengths differ (367 vs 55)'] | J19: Success | K19: Mismatch - Lists lengths differ'; Execution successful without errors.
A20: Target1_38 | B20: Success | C20: Success | D20: =VLOOKUP(Sheet1!A20,Sheet5!B$1:AA$613,26,FALSE) -> 0 | E20: =VLOOKUP(Sheet1!A20,Sheet5!B$1:AA$613,25,FALSE) -> failed | F20: Failed | G20: Success | H20: =C20 & " v.s. " & IF(AND(NOT(ISBLANK(F20)), NOT(ISBLANK(G20))), F20 & " --> " & G20, F20 & G20) -> Success v.s. Failed --> Success | I20: iter1 Error in the previous response: Error: ERROR: invalid input syntax for type numeric: "user_id" CONTEXT: COPY Source1_38_0, line 1, column user_id: "user_id" | J20: Success | K20: Execution successful without errors.
A21: Target1_40 | B21: Failed | C21: Success - preprocessing | D21: =VLOOKUP(Sheet1!A21,Sheet5!B$1:AA$613,26,FALSE) -> data pre processing error | E21: =VLOOKUP(Sheet1!A21,Sheet5!B$1:AA$613,25,FALSE) -> 0 | F21: Failed | G21: Success - takes more itr? | H21: =C21 & " v.s. " & IF(AND(NOT(ISBLANK(F21)), NOT(ISBLANK(G21))), F21 & " --> " & G21, F21 & G21) -> Success - preprocessing v.s. Failed --> Success - takes more itr? | I21: ['Mismatch - DataFrames lengths differ (754 vs 153)'] | J21: Syntax Error | K21: Error in the previous response: Error: ERROR: invalid input syntax for type integer: "30.0" CONTEXT: COPY source1_40_0, line 2, column quantityordered: "30.0"
A22: Target1_41 | B22: Failed | C22: Failed - failed to aggregate - low entropy - domain knowledge | D22: =VLOOKUP(Sheet1!A22,Sheet5!B$1:AA$613,26,FALSE) -> failed | E22: =VLOOKUP(Sheet1!A22,Sheet5!B$1:AA$613,25,FALSE) -> failed | F22: Failed | G22: Need Domain Knowledge | H22: =C22 & " v.s. " & IF(AND(NOT(ISBLANK(F22)), NOT(ISBLANK(G22))), F22 & " --> " & G22, F22 & G22) -> Failed - failed to aggregate - low entropy - domain knowledge v.s. Failed --> Need Domain Knowledge | I22: ['Mismatch - DataFrames lengths differ (83156 vs 13861)'] | J22: Length Mismatch | K22: Mismatch - Lists lengths differ'
A23: Target1_43 | B23: Failed | C23: Failed - failed to aggregate - low entropy - data type change | D23: =VLOOKUP(Sheet1!A23,Sheet5!B$1:AA$613,26,FALSE) -> data pre processing error | E23: =VLOOKUP(Sheet1!A23,Sheet5!B$1:AA$613,25,FALSE) -> 0 | F23: Failed | G23: Need Domain Knowledge | H23: =C23 & " v.s. " & IF(AND(NOT(ISBLANK(F23)), NOT(ISBLANK(G23))), F23 & " --> " & G23, F23 & G23) -> Failed - failed to aggregate - low entropy - data type change v.s. Failed --> Need Domain Knowledge | I23: ['Mismatch - DataFrames lengths differ (322 vs 2)'] | J23: Length Mismatch | K23: Mismatch - Lists lengths differ'
A24: Target1_44 | B24: Failed | C24: Bad Case - task makes no sense | D24: =VLOOKUP(Sheet1!A24,Sheet5!B$1:AA$613,26,FALSE) -> data pre processing error | E24: =VLOOKUP(Sheet1!A24,Sheet5!B$1:AA$613,25,FALSE) -> 0 | F24: Failed | G24: Bad Case - task makes no sense | H24: =C24 & " v.s. " & IF(AND(NOT(ISBLANK(F24)), NOT(ISBLANK(G24))), F24 & " --> " & G24, F24 & G24) -> Bad Case - task makes no sense v.s. Failed --> Bad Case - task makes no sense | I24: iter1 Error in the previous response: Error: ERROR: invalid input syntax for type numeric: "*" CONTEXT: COPY Source1_44_0, line 26, column Value: "*" | J24: Syntax Error | K24: Error in the previous response: Error: ERROR: invalid input syntax for type numeric: "*" CONTEXT: COPY source1_44_0, line 26, column Value: "*"
A25: Target1_46 | B25: Failed | C25: Success* bad test case : Dec_2012 vs Dec_2013 | D25: =VLOOKUP(Sheet1!A25,Sheet5!B$1:AA$613,26,FALSE) -> 0 | E25: =VLOOKUP(Sheet1!A25,Sheet5!B$1:AA$613,25,FALSE) -> 0 | F25: Failed | G25: Success* bad test case : Dec_2012 vs Dec_2013 | H25: =C25 & " v.s. " & IF(AND(NOT(ISBLANK(F25)), NOT(ISBLANK(G25))), F25 & " --> " & G25, F25 & G25) -> Success* bad test case : Dec_2012 vs Dec_2013 v.s. Failed --> Success* bad test case : Dec_2012 vs Dec_2013 | I25: ['Mismatch - DataFrames lengths differ (6960 vs 96)'] | J25: Length Mismatch | K25: Mismatch - Lists lengths differ'
A26: Target1_48 | B26: Failed | C26: Success* bad test case : Dec_2012 vs Dec_2013 | D26: =VLOOKUP(Sheet1!A26,Sheet5!B$1:AA$613,26,FALSE) -> #N/A | E26: =VLOOKUP(Sheet1!A26,Sheet5!B$1:AA$613,25,FALSE) -> #N/A | F26: Success* | G26: Success | H26: =C26 & " v.s. " & IF(AND(NOT(ISBLANK(F26)), NOT(ISBLANK(G26))), F26 & " --> " & G26, F26 & G26) -> Success* bad test case : Dec_2012 vs Dec_2013 v.s. Success* --> Success | I26: [(0, [(23, 'Dec_2012', 'Dec_2013')])] | J26: Length Mismatch | K26: Mismatch - Lists lengths differ'
A27: Target1_52 | B27: Failed | C27: Failed - failed to aggregate - low entropy - data type change | D27: =VLOOKUP(Sheet1!A27,Sheet5!B$1:AA$613,26,FALSE) -> failed | E27: =VLOOKUP(Sheet1!A27,Sheet5!B$1:AA$613,25,FALSE) -> failed | F27: Failed | H27: =C27 & " v.s. " & IF(AND(NOT(ISBLANK(F27)), NOT(ISBLANK(G27))), F27 & " --> " & G27, F27 & G27) -> Failed - failed to aggregate - low entropy - data type change v.s. Failed | I27: Error: ERROR: malformed array literal: "1" DETAIL: Array value must start with "{" or dimension information. CONTEXT: COPY Source1_52_0, line 2, column condition: "1" | J27: Length Mismatch | K27: Mismatch - Lists lengths differ'
A28: Target1_53 | B28: Failed | C28: Success* grouped by continent - did not remove the empty continent - I would not call this failed.. | D28: =VLOOKUP(Sheet1!A28,Sheet5!B$1:AA$613,26,FALSE) -> failed | E28: =VLOOKUP(Sheet1!A28,Sheet5!B$1:AA$613,25,FALSE) -> failed | F28: Success* | G28: Success | H28: =C28 & " v.s. " & IF(AND(NOT(ISBLANK(F28)), NOT(ISBLANK(G28))), F28 & " --> " & G28, F28 & G28) -> Success* grouped by continent - did not remove the empty continent - I would not call this failed.. v.s. Success* --> Success | I28: ['Mismatch - DataFrames lengths differ (6 vs 5)'] | J28: Length Mismatch | K28: Mismatch - Lists lengths differ'
A29: Target1_54 | B29: Failed | C29: Failed - failed to aggregate - low entropy - domain knowledge | D29: =VLOOKUP(Sheet1!A29,Sheet5!B$1:AA$613,26,FALSE) -> #N/A | E29: =VLOOKUP(Sheet1!A29,Sheet5!B$1:AA$613,25,FALSE) -> #N/A | F29: Failed | G29: Need Domain Knowledge | H29: =C29 & " v.s. " & IF(AND(NOT(ISBLANK(F29)), NOT(ISBLANK(G29))), F29 & " --> " & G29, F29 & G29) -> Failed - failed to aggregate - low entropy - domain knowledge v.s. Failed --> Need Domain Knowledge | I29: Error: ERROR: malformed array literal: "1" DETAIL: Array value must start with "{" or dimension information. CONTEXT: COPY Source1_54_0, line 2, column condition: "1" | J29: Length Mismatch | K29: Mismatch - Lists lengths differ'
A30: Target1_55 | B30: Success | C30: Success | D30: =VLOOKUP(Sheet1!A30,Sheet5!B$1:AA$613,26,FALSE) -> #N/A | E30: =VLOOKUP(Sheet1!A30,Sheet5!B$1:AA$613,25,FALSE) -> #N/A | F30: Failed* VERY CLOSE.. CHECK | G30: Success | H30: =C30 & " v.s. " & IF(AND(NOT(ISBLANK(F30)), NOT(ISBLANK(G30))), F30 & " --> " & G30, F30 & G30) -> Success v.s. Failed* VERY CLOSE.. CHECK --> Success | I30: ['Mismatch - DataFrames lengths differ (6584 vs 6583)'] | J30: Success | K30: Execution successful without errors.
A31: Target1_57 | B31: Success | C31: Success | D31: =VLOOKUP(Sheet1!A31,Sheet5!B$1:AA$613,26,FALSE) -> 0 | E31: =VLOOKUP(Sheet1!A31,Sheet5!B$1:AA$613,25,FALSE) -> 0 | F31: Failed | G31: Success-itr2 | H31: =C31 & " v.s. " & IF(AND(NOT(ISBLANK(F31)), NOT(ISBLANK(G31))), F31 & " --> " & G31, F31 & G31) -> Success v.s. Failed --> Success-itr2 | I31: Error in the previous response: Error: ERROR: invalid input syntax for type numeric: "userId" CONTEXT: COPY Source1_57_0, line 1, column userId: "userId" | J31: Success | K31: Syntax error at or near "Finish"; Execution successful without errors.
A32: Target1_59 | B32: Failed | C32: Success - preprocessing | D32: =VLOOKUP(Sheet1!A32,Sheet5!B$1:AA$613,26,FALSE) -> ERROR: Error: ERROR: invalid input syntax for type integer: "2003.0" CONTEXT: COPY source59_0, line 2, column year_id: "2003.0" | E32: =VLOOKUP(Sheet1!A32,Sheet5!B$1:AA$613,25,FALSE) -> 0.5 success [1,0.7] score. | F32: Success | G32: Success | H32: =C32 & " v.s. " & IF(AND(NOT(ISBLANK(F32)), NOT(ISBLANK(G32))), F32 & " --> " & G32, F32 & G32) -> Success - preprocessing v.s. Success --> Success | J32: Syntax Error | K32: Error in the previous response: Error: ERROR: invalid input syntax for type integer: "2.0" CONTEXT: COPY source1_59_0, line 2, column orderlinenumber: "2.0"
A33: Target1_60 | B33: Success | C33: Success | D33: =VLOOKUP(Sheet1!A33,Sheet5!B$1:AA$613,26,FALSE) -> failed | E33: =VLOOKUP(Sheet1!A33,Sheet5!B$1:AA$613,25,FALSE) -> success | F33: Success | G33: Success | H33: =C33 & " v.s. " & IF(AND(NOT(ISBLANK(F33)), NOT(ISBLANK(G33))), F33 & " --> " & G33, F33 & G33) -> Success v.s. Success --> Success | J33: Success | K33: Execution successful without errors.
A34: Target1_61 | B34: Failed | C34: Failed - failed to aggregate - low entropy - domain knowledge | D34: =VLOOKUP(Sheet1!A34,Sheet5!B$1:AA$613,26,FALSE) -> #N/A | E34: =VLOOKUP(Sheet1!A34,Sheet5!B$1:AA$613,25,FALSE) -> #N/A | F34: Success** DID BETTER!!! BY CHANCE I GUESS.. | H34: =C34 & " v.s. " & IF(AND(NOT(ISBLANK(F34)), NOT(ISBLANK(G34))), F34 & " --> " & G34, F34 & G34) -> Failed - failed to aggregate - low entropy - domain knowledge v.s. Success** DID BETTER!!! BY CHANCE I GUESS.. | J34: Length Mismatch | K34: Mismatch - Lists lengths differ'
A35: Target1_62 | B35: Failed | C35: Success | D35: =VLOOKUP(Sheet1!A35,Sheet5!B$1:AA$613,26,FALSE) -> failed | E35: =VLOOKUP(Sheet1!A35,Sheet5!B$1:AA$613,25,FALSE) -> failed | F35: Success | G35: Success | H35: =C35 & " v.s. " & IF(AND(NOT(ISBLANK(F35)), NOT(ISBLANK(G35))), F35 & " --> " & G35, F35 & G35) -> Success v.s. Success --> Success | J35: Similarity Score Issue | K35: Scores: 0.9895, 1.0, 1.0; Case accuracy: 1.00 | L35: ['Column 1: Dec_2012 vs Dec_2013']
A36: Target1_65 | B36: Success | C36: Success | D36: =VLOOKUP(Sheet1!A36,Sheet5!B$1:AA$613,26,FALSE) -> 0 | E36: =VLOOKUP(Sheet1!A36,Sheet5!B$1:AA$613,25,FALSE) -> success | F36: Success | G36: Success | H36: =C36 & " v.s. " & IF(AND(NOT(ISBLANK(F36)), NOT(ISBLANK(G36))), F36 & " --> " & G36, F36 & G36) -> Success v.s. Success --> Success | J36: Success | K36: Execution successful without errors.
A37: Target1_67 | B37: Success | C37: Success | D37: =VLOOKUP(Sheet1!A37,Sheet5!B$1:AA$613,26,FALSE) -> #N/A | E37: =VLOOKUP(Sheet1!A37,Sheet5!B$1:AA$613,25,FALSE) -> #N/A | F37: Success | G37: Success | H37: =C37 & " v.s. " & IF(AND(NOT(ISBLANK(F37)), NOT(ISBLANK(G37))), F37 & " --> " & G37, F37 & G37) -> Success v.s. Success --> Success | J37: Success | K37: Execution successful without errors.
A38: Target1_68 | B38: Success | C38: Success | D38: =VLOOKUP(Sheet1!A38,Sheet5!B$1:AA$613,26,FALSE) -> #N/A | E38: =VLOOKUP(Sheet1!A38,Sheet5!B$1:AA$613,25,FALSE) -> #N/A | F38: Failed - DID NOT DO SUBSTRING | G38: Success | H38: =C38 & " v.s. " & IF(AND(NOT(ISBLANK(F38)), NOT(ISBLANK(G38))), F38 & " --> " & G38, F38 & G38) -> Success v.s. Failed - DID NOT DO SUBSTRING --> Success | I38: SQL is wrong: [(0, [(0, 'IGHV', 'IGHV1'), (1, 'IGHV', 'IGHV1') | J38: Success | K38: Execution successful without errors.
A39: Target1_71 | B39: Success | C39: Success | D39: =VLOOKUP(Sheet1!A39,Sheet5!B$1:AA$613,26,FALSE) -> success | E39: =VLOOKUP(Sheet1!A39,Sheet5!B$1:AA$613,25,FALSE) -> success | F39: Success | G39: Success | H39: =C39 & " v.s. " & IF(AND(NOT(ISBLANK(F39)), NOT(ISBLANK(G39))), F39 & " --> " & G39, F39 & G39) -> Success v.s. Success --> Success | J39: Success | K39: Execution successful without errors.
A40: Target1_72 | B40: Success | C40: Success | D40: =VLOOKUP(Sheet1!A40,Sheet5!B$1:AA$613,26,FALSE) -> failed | E40: =VLOOKUP(Sheet1!A40,Sheet5!B$1:AA$613,25,FALSE) -> failed | F40: Failed | G40: Failed | H40: =C40 & " v.s. " & IF(AND(NOT(ISBLANK(F40)), NOT(ISBLANK(G40))), F40 & " --> " & G40, F40 & G40) -> Success v.s. Failed --> Failed | I40: Error: ERROR: malformed array literal: "1" DETAIL: Array value must start with "{" or dimension information. CONTEXT: COPY Source1_72_0, line 2, column condition: "1" | J40: Success | K40: Execution successful without errors.
A41: Target1_75 | B41: Failed | C41: Failed - failed to aggregate - low entropy - domain knowledge/ did not do count | D41: =VLOOKUP(Sheet1!A41,Sheet5!B$1:AA$613,26,FALSE) -> 0 | E41: =VLOOKUP(Sheet1!A41,Sheet5!B$1:AA$613,25,FALSE) -> 0 | F41: Failed | G41: Need Domain Knowledge | H41: =C41 & " v.s. " & IF(AND(NOT(ISBLANK(F41)), NOT(ISBLANK(G41))), F41 & " --> " & G41, F41 & G41) -> Failed - failed to aggregate - low entropy - domain knowledge/ did not do count v.s. Failed --> Need Domain Knowledge | I41: ['Mismatch - DataFrames lengths differ (9435 vs 70)'] | J41: Length Mismatch | K41: Mismatch - Lists lengths differ'
A42: Target1_77 | B42: Failed | C42: Success* grouped by continent - did not remove the empty fac_type - I would not call this failed.. | D42: =VLOOKUP(Sheet1!A42,Sheet5!B$1:AA$613,26,FALSE) -> data pre processing error | E42: =VLOOKUP(Sheet1!A42,Sheet5!B$1:AA$613,25,FALSE) -> 0 | F42: Success* | G42: Success* | H42: =C42 & " v.s. " & IF(AND(NOT(ISBLANK(F42)), NOT(ISBLANK(G42))), F42 & " --> " & G42, F42 & G42) -> Success* grouped by continent - did not remove the empty fac_type - I would not call this failed.. v.s. Success* --> Success* | I42: ['Mismatch - DataFrames lengths differ (3 vs 2)'] | J42: Length Mismatch | K42: Mismatch - Lists lengths differ'
A43: Target1_78 | B43: Failed | C43: Need Domain Knowledge - Use Aggregation or not | D43: =VLOOKUP(Sheet1!A43,Sheet5!B$1:AA$613,26,FALSE) -> data pre processing error | E43: =VLOOKUP(Sheet1!A43,Sheet5!B$1:AA$613,25,FALSE) -> 0 | F43: Failed | G43: Need Domain Knowledge | H43: =C43 & " v.s. " & IF(AND(NOT(ISBLANK(F43)), NOT(ISBLANK(G43))), F43 & " --> " & G43, F43 & G43) -> Need Domain Knowledge - Use Aggregation or not v.s. Failed --> Need Domain Knowledge | I43: ['Mismatch - DataFrames lengths differ (27386 vs 10980)'] | J43: Syntax Error | K43: Error in the previous response: Error: ERROR: syntax error at or near "User" LINE 23: User TEXT,
A44: Target1_80 | B44: Success | C44: Success | D44: =VLOOKUP(Sheet1!A44,Sheet5!B$1:AA$613,26,FALSE) -> failed | E44: =VLOOKUP(Sheet1!A44,Sheet5!B$1:AA$613,25,FALSE) -> failed | F44: Failed | G44: Success | H44: =C44 & " v.s. " & IF(AND(NOT(ISBLANK(F44)), NOT(ISBLANK(G44))), F44 & " --> " & G44, F44 & G44) -> Success v.s. Failed --> Success | I44: ERROR: invalid input syntax for type numeric: "userId" CONTEXT: COPY Source1_80_0, line 1, column userId: "userId" | J44: Success | K44: Execution successful without errors.
A45: Target1_81 | B45: Failed | C45: Failed - failed to aggregate - low entropy - domain knowledge | D45: =VLOOKUP(Sheet1!A45,Sheet5!B$1:AA$613,26,FALSE) -> 0 | E45: =VLOOKUP(Sheet1!A45,Sheet5!B$1:AA$613,25,FALSE) -> failed | F45: Failed | G45: Need Domain Knowledge | H45: =C45 & " v.s. " & IF(AND(NOT(ISBLANK(F45)), NOT(ISBLANK(G45))), F45 & " --> " & G45, F45 & G45) -> Failed - failed to aggregate - low entropy - domain knowledge v.s. Failed --> Need Domain Knowledge | I45: ['Mismatch - DataFrames lengths differ (3167 vs 2899)'] | J45: Length Mismatch | K45: Mismatch - Lists lengths differ'
A46: Target1_82 | B46: Failed | C46: Success* grouped by continent - did not remove the empty conservation_status - I would not call this failed.. | D46: =VLOOKUP(Sheet1!A46,Sheet5!B$1:AA$613,26,FALSE) -> 0 | E46: =VLOOKUP(Sheet1!A46,Sheet5!B$1:AA$613,25,FALSE) -> failed | F46: Success* | G46: Success* | H46: =C46 & " v.s. " & IF(AND(NOT(ISBLANK(F46)), NOT(ISBLANK(G46))), F46 & " --> " & G46, F46 & G46) -> Success* grouped by continent - did not remove the empty conservation_status - I would not call this failed.. v.s. Success* --> Success* | I46: ['Mismatch - DataFrames lengths differ (5 vs 4)'] | J46: Length Mismatch | K46: Mismatch - Lists lengths differ'
A47: Target1_84 | B47: Success | C47: Success | D47: =VLOOKUP(Sheet1!A47,Sheet5!B$1:AA$613,26,FALSE) -> #N/A | E47: =VLOOKUP(Sheet1!A47,Sheet5!B$1:AA$613,25,FALSE) -> #N/A | F47: Failed | G47: Failed | H47: =C47 & " v.s. " & IF(AND(NOT(ISBLANK(F47)), NOT(ISBLANK(G47))), F47 & " --> " & G47, F47 & G47) -> Success v.s. Failed --> Failed | I47: ERROR: schema "V_CALL" does not exist LINE 7: CREATE TABLE "V_CALL"."Source1_84_0" ( ^ | J47: Success | K47: Execution successful without errors.
A48: Target1_86 | B48: Failed | C48: Need Domain Knowledge - Aggregation function | D48: =VLOOKUP(Sheet1!A48,Sheet5!B$1:AA$613,26,FALSE) -> 0 | E48: =VLOOKUP(Sheet1!A48,Sheet5!B$1:AA$613,25,FALSE) -> failed | F48: Failed | G48: Need Domain Knowledge | H48: =C48 & " v.s. " & IF(AND(NOT(ISBLANK(F48)), NOT(ISBLANK(G48))), F48 & " --> " & G48, F48 & G48) -> Need Domain Knowledge - Aggregation function v.s. Failed --> Need Domain Knowledge | I48: d SQL script can run, but the execution result of the SQL is wrong: [(1, [(0, '53.4782608695652174', '23'), (1, '53.0000000000000000', '2') | J48: Similarity Score Issue | K48: Scores: 1.0, 0.0285; Case accuracy: 0.51 | L48: too long to list, refer to 'revised_finish_1.log'
A49: Target1_87 | B49: Failed | C49: Failed - failed to aggregate - low entropy - domain knowledge | D49: =VLOOKUP(Sheet1!A49,Sheet5!B$1:AA$613,26,FALSE) -> #N/A | E49: =VLOOKUP(Sheet1!A49,Sheet5!B$1:AA$613,25,FALSE) -> #N/A | F49: Failed | G49: Need Domain Knowledge | H49: =C49 & " v.s. " & IF(AND(NOT(ISBLANK(F49)), NOT(ISBLANK(#REF!))), F49 & " --> " &#REF!, F49 &#REF!) -> #REF! | I49: ['Mismatch - DataFrames lengths differ (499 vs 2)'] | J49: Length Mismatch | K49: Mismatch - Lists lengths differ'
A50: Target1_88 | B50: Failed | C50: Success | D50: =VLOOKUP(Sheet1!A50,Sheet5!B$1:AA$613,26,FALSE) -> success | E50: =VLOOKUP(Sheet1!A50,Sheet5!B$1:AA$613,25,FALSE) -> success | F50: Failed | G50: Failed | H50: =C50 & " v.s. " & IF(AND(NOT(ISBLANK(F50)), NOT(ISBLANK(G50))), F50 & " --> " & G50, F50 & G50) -> Success v.s. Failed --> Failed | I50: [(1, [(0, '2019-03-03', '03/03/2019') | J50: Syntax Error | K50: Error in the previous response: Error: ERROR: date/time field value out of range: "24/03/2019" HINT: Perhaps you need a different "datestyle" setting. CONTEXT: COPY source1_88_0, line 2, column date_of_journey: "24/03/2019"
A51: Target1_89 | B51: Failed | C51: Bad Case - task makes no sense | D51: =VLOOKUP(Sheet1!A51,Sheet5!B$1:AA$613,26,FALSE) -> 0 | E51: =VLOOKUP(Sheet1!A51,Sheet5!B$1:AA$613,25,FALSE) -> error in date column; headear is for two rows, | F51: Failed | G51: Bad Case - task makes no sense | H51: =C51 & " v.s. " & IF(AND(NOT(ISBLANK(F51)), NOT(ISBLANK(G51))), F51 & " --> " & G51, F51 & G51) -> Bad Case - task makes no sense v.s. Failed --> Bad Case - task makes no sense | I51: ERROR: invalid input syntax for type numeric: "A" CONTEXT: COPY Source1_89_0, line 2, column open: "A" | J51: Syntax Error | K51: Error in the previous response: Error: ERROR: invalid input syntax for type date: "date" CONTEXT: COPY source1_89_0, line 2, column date: "date"
A52: Target1_90 | B52: Failed | C52: Need Domain Knowledge - Rare case/ expectation | D52: =VLOOKUP(Sheet1!A52,Sheet5!B$1:AA$613,26,FALSE) -> 0 | E52: =VLOOKUP(Sheet1!A52,Sheet5!B$1:AA$613,25,FALSE) -> failed | F52: Failed | G52: Need Domain Knowledge | H52: =C52 & " v.s. " & IF(AND(NOT(ISBLANK(F52)), NOT(ISBLANK(G52))), F52 & " --> " & G52, F52 & G52) -> Need Domain Knowledge - Rare case/ expectation v.s. Failed --> Need Domain Knowledge | I52: ERROR: invalid input syntax for type numeric: "" CONTEXT: COPY Source1_90_0, line 2, column in_reply_to_status_id: "" | J52: Syntax Error | K52: Error in the previous response: Error: ERROR: invalid input syntax for type bigint: "8.874739571039519e+17" CONTEXT: COPY source1_90_0, line 21, column retweeted_status_id: "8.874739571039519e+17"
A53: Target1_91 | B53: Failed | C53: Success - next iteration | D53: =VLOOKUP(Sheet1!A53,Sheet5!B$1:AA$613,26,FALSE) -> 0 | E53: =VLOOKUP(Sheet1!A53,Sheet5!B$1:AA$613,25,FALSE) -> could not treat empty value as NULL | F53: GUESS IT CAN SUCCESS | G53: Success | H53: =C53 & " v.s. " & IF(AND(NOT(ISBLANK(F53)), NOT(ISBLANK(G53))), F53 & " --> " & G53, F53 & G53) -> Success - next iteration v.s. GUESS IT CAN SUCCESS --> Success | I53: ERROR: invalid input syntax for type numeric: "" CONTEXT: COPY Source1_91_0, line 2, column Market_value: "" | J53: Syntax Error | K53: Error in the previous response: Error: ERROR: invalid input syntax for type numeric: "" CONTEXT: COPY source1_91_0, line 2, column market_value: ""
A54: Target1_92 | B54: Failed | C54: Success - next iteration | D54: =VLOOKUP(Sheet1!A54,Sheet5!B$1:AA$613,26,FALSE) -> 0 | E54: =VLOOKUP(Sheet1!A54,Sheet5!B$1:AA$613,25,FALSE) -> [0,1,1] sim score, and 0.6 accuracy | F54: Success | G54: Success | H54: =C54 & " v.s. " & IF(AND(NOT(ISBLANK(F54)), NOT(ISBLANK(G54))), F54 & " --> " & G54, F54 & G54) -> Success - next iteration v.s. Success --> Success | J54: Syntax Error | K54: Scores: 1.0, 0.98, 0.96; Case accuracy: 0.98 | L54: ['Column 3: None vs ', 'Column 3: None vs ', 'Column 2: None vs ']
A55: Target1_93 | B55: Failed | C55: Success - next iteration | D55: =VLOOKUP(Sheet1!A55,Sheet5!B$1:AA$613,26,FALSE) -> 0 | E55: =VLOOKUP(Sheet1!A55,Sheet5!B$1:AA$613,25,FALSE) -> failed with error | F55: Failed | G55: Failed-syntax | H55: =C55 & " v.s. " & IF(AND(NOT(ISBLANK(F55)), NOT(ISBLANK(G55))), F55 & " --> " & G55, F55 & G55) -> Success - next iteration v.s. Failed --> Failed-syntax | I55: ERROR: invalid input syntax for type numeric: "bet" CONTEXT: COPY Source1_93_0, line 1, column bet: "bet" | J55: Syntax Error | K55: Error in the previous response: Error: ERROR: invalid input syntax for type numeric: "" CONTEXT: COPY source1_93_0, line 2, column bet: ""
A56: Target1_95 | B56: Failed | C56: Failed - failed to aggregate - low entropy - domain knowledge - hard (newest date) | D56: =VLOOKUP(Sheet1!A56,Sheet5!B$1:AA$613,26,FALSE) -> 0 | E56: =VLOOKUP(Sheet1!A56,Sheet5!B$1:AA$613,25,FALSE) -> failed | F56: Failed | G56: Need Domain Knowledge | H56: =C56 & " v.s. " & IF(AND(NOT(ISBLANK(F56)), NOT(ISBLANK(G56))), F56 & " --> " & G56, F56 & G56) -> Failed - failed to aggregate - low entropy - domain knowledge - hard (newest date) v.s. Failed --> Need Domain Knowledge | I56: ERROR: invalid input syntax for type integer: "customer_id" CONTEXT: COPY Source1_95_0, line 1, column customer_id: "customer_id" | J56: Length Mismatch | K56: Mismatch - Lists lengths differ'
A57: Target1_97 | B57: Failed | C57: Need Domain Knowledge - expectation/ count on which | D57: =VLOOKUP(Sheet1!A57,Sheet5!B$1:AA$613,26,FALSE) -> 0 | E57: =VLOOKUP(Sheet1!A57,Sheet5!B$1:AA$613,25,FALSE) -> [1,0] sim score, 0.5 accuracy | F57: Failed | G57: Success - by luck | H57: =C57 & " v.s. " & IF(AND(NOT(ISBLANK(F57)), NOT(ISBLANK(G57))), F57 & " --> " & G57, F57 & G57) -> Need Domain Knowledge - expectation/ count on which v.s. Failed --> Success - by luck | I57: [(1, [(0, '5', '1'), (1, '30', '3')])] | J57: Similarity Score Issue | K57: Syntax Error: Finish; Scores: 1.0, 0.0; Case accuracy: 0.50 | L57: ['Column 2: 30 vs 3', 'Column 2: 5 vs 1']
A58: Target1_99 | B58: Failed | C58: Failed - did not figured out | D58: =VLOOKUP(Sheet1!A58,Sheet5!B$1:AA$613,26,FALSE) -> failed | E58: =VLOOKUP(Sheet1!A58,Sheet5!B$1:AA$613,25,FALSE) -> data procesessing error | F58: Failed | G58: Failed - did not figured out | H58: =C58 & " v.s. " & IF(AND(NOT(ISBLANK(F58)), NOT(ISBLANK(G58))), F58 & " --> " & G58, F58 & G58) -> Failed - did not figured out v.s. Failed --> Failed - did not figured out | I58: ERROR: date/time field value out of range: "2015-04-01 13:60:41" CONTEXT: COPY Source1_99_0, line 204, column timestamp: "2015-04-01 13:60:41" | J58: Length Mismatch | K58: Mismatch - Lists lengths differ'

Sheet Sheet5
A1: Folder Name | B1: Target Data Name | C1: Target Data Schema | D1: Target Data Sample | E1: Target Data Description | F1: Source Data Name | G1: 3 Samples of Source Data | H1: Source Data Schema | I1: Failed SQL by GPT | J1: Failed Cases | K1: Ground Truth SQL | L1: Prompt_1(with csv) | M1: Prompt_2(with samples) | N1: sim score(with samples) | O1: PathsToSource1csv | P1: PathsToSource2csv | Q1: Comment(with samples) | R1: validation using s.csv and t.csv | S1: Final comments | T1: Accuracy Prompt 1 | U1: sim score in Prompt 1 | V1: error if any | W1: error in second run | X1: comment | Y1: React Result | Z1: Round 2 Accuracy Promp2 (with Target sample) | AA1: Round2 Accuracy Prompt1
A2: L1_0 | B2: Target1_0 | C2: ['State', 'AverageTemperature'] | D2: [['Acre', 25.76959388646288], ['Adygey', 10.203819706498953], ['Aga Buryat', -3.9832969187675102]] | E2: In target, the state wise average is computed from source. | F2: Source1_0 | G2: [['2002-11-01', 4.19, 0.187, 'Rostov', 'Russia'], ['1923-11-01', 26.761, 0.413, 'Sergipe', 'Brazil'], ['1994-09-01', 25.56, 0.245, 'Manipur', 'India']] | H2: ['dt', 'AverageTemperature', 'AverageTemperatureUncertainty', 'State', 'Country'] | L2: 0 | M2: 0 | T2: 0 | Y2: 1 | Z2: failed | AA2: failed, could not do aggregation
A3: L1_1 | B3: Target1_1 | C3: ['Student ID', 'student_name', 'gender', 'grade', 'school_name', 'reading_score', 'math_score', 'School ID', 'type', 'size', 'budget'] | D3: [[0, 'Paul Bradley', 'M', '9th', 'Huang High School', 66, 79, 0, 'District', 2917, 1910635], [1, 'Victor Smith', 'M', '12th', 'Huang High School', 94, 61, 0, 'District', 2917, 1910635], [2, 'Kevin Rodriguez', 'M', '12th', 'Huang High School', 90, 60, 0, 'District', 2917, 1910635]] | E3: Perform join on both source table and in case of ambiguity use school_name from source1_0 | F3: Source1_0 | G3: [[0, 'Paul Bradley', 'M', '9th', 'Huang High School', 66, 79], [1, 'Victor Smith', 'M', '12th', 'Huang High School', 94, 61], [2, 'Kevin Rodriguez', 'M', '12th', 'Huang High School', 90, 60]] | H3: ['Student ID', 'student_name', 'gender', 'grade', 'school_name', 'reading_score', 'math_score'] | K3: CREATE TABLE IF NOT EXISTS Source1_0 ( "Student ID" INT, student_name TEXT, gender CHAR(1), grade VARCHAR(10), school_name TEXT, reading_score INT, math_score INT ); -- Insert data into 'Source_0' INSERT INTO Source1_0 ("Student ID", student_name, gender, grade, school_name, reading_score, math_score) VALUES (0, 'Paul Bradley', 'M', '9th', 'Huang High School', 66, 79), (1, 'Victor Smith', 'M', '12th', 'Huang High School', 94, 61), (2, 'Kevin Rodriguez', 'M', '12th', 'Huang High School', 90, 60); -- Drop the second source table 'Source1_1' if it exists DROP TABLE IF EXISTS Source1_1; -- Create the second source table 'Source1_1' CREATE TABLE Source1_1 ( "School ID" INT, school_name TEXT, type TEXT, size INT, budget INT ); -- Insert data into 'Source1_1' INSERT INTO Source1_1 ("School ID", school_name, type, size, budget) VALUES (0, 'Huang High School', 'District', 2917, 1910635), (1, 'Figueroa High School', 'District', 2949, 1884411), (2, 'Shelton High School', 'Charter', 1761, 1056600); -- Create the target table 'target1' CREATE TABLE IF NOT EXISTS target1_1( "Student ID" INT, student_name TEXT, gender CHAR(1), grade VARCHAR(10), school_name TEXT, reading_score INT, math_score INT, "School ID" INT, type TEXT, size INT, budget INT ); -- Insert data into 'target1' by selecting only the necessary columns INSERT INTO target1_1 ( "Student ID", student_name, gender, grade, school_name, reading_score, math_score, "School ID", type, size, budget ) SELECT s0."Student ID", s0.student_name, s0.gender, s0.grade, s0.school_name, s0.reading_score, s0.math_score, s1."School ID", s1.type, s1.size, s1.budget FROM Source2_0 s0 JOIN Source2_1 s1 ON s0.school_name = s1.school_name; | L3: 0 | M3: 0.45 | R3: 0.45 | T3: 1 | AA3: success
F4: Source1_1 | G4: [[0, 'Huang High School', 'District', 2917, 1910635], [1, 'Figueroa High School', 'District', 2949, 1884411], [2, 'Shelton High School', 'Charter', 1761, 1056600]] | H4: ['School ID', 'school_name', 'type', 'size', 'budget']
A5: L1_10 | B5: Target1_10 | C5: ['PRECINCT', 'ELIGIBLE_VOTERS', 'POLLS', 'EARLY_VOING', 'ABSENTEE', 'PROVISIONAL'] | D5: [['001-000', 612, 408, 39, 19, 3], ['001-001', 27791, 13648, 5179, 1247, 462], ['001-002', 13695, 6576, 2601, 495, 307]] | E5: In target, the attributes are sum from source for each PRECINCT | F5: Source10_0 | G5: [['Allegany', 6.0, '01C', '001-000', 'DEMOCRAT', 83, 9, 4, 1, 126.0], ['Allegany', 6.0, '01C', '001-000', 'GREEN', 1, 0, 0, 1, 2.0], ['Allegany', 6.0, '01C', '001-000', 'LIBERTARIAN', 3, 0, 0, 0, 3.0]] | H5: ['LBE', 'CONGRESSIONAL_DISTRICT_CODE', 'LEGISLATIVE_DISTRICT_CODE', 'PRECINCT', 'PARTY', 'POLLS', 'EARLY_VOING', 'ABSENTEE', 'PROVISIONAL', 'ELIGIBLE_VOTERS'] | L5: 0 | M5: 0 | R5: 0 | T5: 0 | Z5: succes | AA5: failed
A6: L1_11 | B6: Target1_11 | C6: ['sex', 'births'] | D6: [['F', 90993], ['M', 80202]] | E6: In target table births is sum of births from source table. sex is group by as 'M' and 'F' and order by sex. | F6: Source11_0 | G6: [['Mary', 'F', 7065], ['Anna', 'F', 2604], ['Emma', 'F', 2003]] | H6: ['name', 'sex', 'births'] | L6: 0 | M6: 0 | R6: 1 | S6: data type mismatch to be resolved. Done | T6: 0 | Y6: 1 | Z6: failed | AA6: failed
A7: L1_12 | B7: Target1_12 | C7: ['Athlete', 'Age', 'Year', 'Closing Ceremony Date', 'Gold Medals', 'Silver Medals', 'Bronze Medals', 'Total Medals', 'Country'] | D7: [['Michael Phelps', 23.0, 2008, '08/24/2008', 8, 0, 0, 8, 'United States'], ['Michael Phelps', 19.0, 2004, '08/29/2004', 6, 0, 2, 8, 'United States'], ['Michael Phelps', 27.0, 2012, '08/12/2012', 4, 2, 0, 6, 'United States']] | E7: Use join on source tables. | F7: Source12_0 | G7: [['Michael Phelps', 23.0, 2008, '08/24/2008', 8, 0, 0, 8], ['Michael Phelps', 19.0, 2004, '08/29/2004', 6, 0, 2, 8], ['Michael Phelps', 27.0, 2012, '08/12/2012', 4, 2, 0, 6]] | H7: ['Athlete', 'Age', 'Year', 'Closing Ceremony Date', 'Gold Medals', 'Silver Medals', 'Bronze Medals', 'Total Medals'] | M7: 0 | R7: 0 | T7: 0
F8: Source12_1 | G8: [['Michael Phelps', 'United States'], ['Natalie Coughlin', 'United States'], ['Aleksey Nemov', 'Russia']] | H8: ['Athlete', 'Country'] | L8: 0 | M8: 0
A9: L1_13 | B9: Target1_13 | C9: ['sex', 'smoker', 'tip_pct'] | D9: [['Female', 'No', 0.15441878619164726], ['Female', 'Yes', 0.19843132079721], ['Male', 'No', 0.16243793099990006]] | E9: In target, for sex and smoker the tip_pct is averaged from source. | F9: Source13_0 | G9: [[16.99, 1.01, 'Female', 'No', 'Sun', 'Dinner', 2, 0.059446733372572114], [10.34, 1.66, 'Male', 'No', 'Sun', 'Dinner', 3, 0.16054158607350094], [21.01, 3.5, 'Male', 'No', 'Sun', 'Dinner', 3, 0.16658733936220846]] | H9: ['total_bill', 'tip', 'sex', 'smoker', 'day', 'time', 'size', 'tip_pct'] | L9: 0 | M9: 0 | R9: 0 | T9: 0 | Y9: fail | Z9: failed | AA9: failed
A10: L1_14 | B10: Target1_14 | C10: ['PLAYER', '2017-18', '#', 'Player', 'Team', 'GP', 'MPG', 'FGM', 'FGA', 'FG%', '3PM', '3PA', '3P%', 'FTM', 'FTA', 'FT%', 'TOV', 'PF', 'ORB', 'DRB', 'RPG', 'APG', 'SPG', 'BPG', 'PPG'] | D10: [['Stephen Curry', 34682550, 1, 'Stephen Curry', 'GSW', 51, 32.0, 8.4, 16.9, 0.495, 4.2, 9.8, 0.423, 5.5, 5.9, 0.921, 3.0, 2.2, 0.7, 4.4, 5.1, 6.1, 1.6, 0.2, 26.4], ['Kevin Durant', 25000000, 2, 'Kevin Durant', 'GSW', 68, 34.2, 9.3, 18.0, 0.516, 2.5, 6.1, 0.419, 5.3, 5.9, 0.889, 3.0, 2.0, 0.5, 6.4, 6.8, 5.4, 0.7, 1.8, 26.4], ['Klay Thompson', 17826150, 3, 'Klay Thompson', 'GSW', 73, 34.3, 7.9, 16.1, 0.488, 3.1, 7.1, 0.44, 1.1, 1.3, 0.8370000000000001, 1.8, 1.6, 0.4, 3.4, 3.8, 2.5, 0.8, 0.5, 20.0]] | E10: In target, join is done on source tables. | F10: Source14_0 | G10: [['Stephen Curry', 34682550], ['Kevin Durant', 25000000], ['Klay Thompson', 17826150]] | H10: ['PLAYER', '2017-18'] | I10: DROP TABLE IF EXISTS Source14_0; CREATE TABLE Source14_0 ( "PLAYER" VARCHAR(255), "2017-18" NUMERIC ); -- Insert data into the first table Source14_0 COPY Source14_0 ("PLAYER", "2017-18") FROM 'D:\lab\ChatGPTwithSQLscript\github-pipelines\length1_14\test_0.csv' DELIMITER ',' CSV HEADER NULL 'nan'; -- Create the second table Source14_1 DROP TABLE IF EXISTS Source14_1; CREATE TABLE Source14_1 ( "#" INTEGER, "Player" VARCHAR(255), "Team" VARCHAR(255), "GP" INTEGER, "MPG" NUMERIC, "FGM" NUMERIC, "FGA" NUMERIC, "FG%" NUMERIC, "3PM" NUMERIC, "3PA" NUMERIC, "3P%" NUMERIC, "FTM" NUMERIC, "FTA" NUMERIC, "FT%" NUMERIC, "TOV" NUMERIC, "PF" NUMERIC, "ORB" NUMERIC, "DRB" NUMERIC, "RPG" NUMERIC, "APG" NUMERIC, "SPG" NUMERIC, "BPG" NUMERIC, "PPG" NUMERIC ); -- Insert data into the second table Source14_1 COPY Source14_1 ("#", "Player", "Team", "GP", "MPG", "FGM", "FGA", "FG%", "3PM", "3PA", "3P%", "FTM", "FTA", "FT%", "TOV", "PF", "ORB", "DRB", "RPG", "APG", "SPG", "BPG", "PPG") FROM 'D:\lab\ChatGPTwithSQLscript\github-pipelines\length1_14\test_1.csv' DELIMITER ',' CSV HEADER NULL 'nan'; -- Create the target table Target1_14 DROP TABLE IF EXISTS Target1_14; CREATE TABLE Target1_14 AS SELECT "PLAYER", "2017-18", "#", "Player", "Team", "GP", "MPG", "FGM", "FGA", "FG%", "3PM", "3PA", "3P%", "FTM", "FTA", "FT%", "TOV", "PF", "ORB", "DRB", "RPG", "APG", "SPG", "BPG", "PPG" FROM Source14_0 JOIN Source14_1 ON Source14_0."PLAYER" = Source14_1."Player"; -- Export the result to a CSV file COPY Target1_14 TO 'D:\lab\ChatGPTwithSQLscript\github-pipelines\length1_14\Target1_14_result.csv' DELIMITER ',' CSV HEADER; | J10: SQL Result: Table name not identified from last INSERT INTO query. | L10: 0 | M10: 1 | N10: [1.0, 1.0, 1.0, 1.0, 1.0, 1.0, 1.0, 1.0, 1.0, 1.0, 1.0, 1.0, 1.0, 1.0, 1.0, 1.0, 1.0, 1.0, 1.0, 1.0, 1.0, 1.0, 1.0, 1.0, 1.0] | Q10: second time running the script gives correct result., no chnages were made. | R10: 0.84 | T10: Fail | V10: ERROR: column "player" specified more than once
F11: Source14_1 | G11: [[1, 'Stephen Curry', 'GSW', 51, 32.0, 8.4, 16.9, 0.495, 4.2, 9.8, 0.423, 5.5, 5.9, 0.921, 3.0, 2.2, 0.7, 4.4, 5.1, 6.1, 1.6, 0.2, 26.4], [2, 'Kevin Durant', 'GSW', 68, 34.2, 9.3, 18.0, 0.516, 2.5, 6.1, 0.419, 5.3, 5.9, 0.889, 3.0, 2.0, 0.5, 6.4, 6.8, 5.4, 0.7, 1.8, 26.4], [3, 'Klay Thompson', 'GSW', 73, 34.3, 7.9, 16.1, 0.488, 3.1, 7.1, 0.44, 1.1, 1.3, 0.8370000000000001, 1.8, 1.6, 0.4, 3.4, 3.8, 2.5, 0.8, 0.5, 20.0]] | H11: ['#', 'Player', 'Team', 'GP', 'MPG', 'FGM', 'FGA', 'FG%', '3PM', '3PA', '3P%', 'FTM', 'FTA', 'FT%', 'TOV', 'PF', 'ORB', 'DRB', 'RPG', 'APG', 'SPG', 'BPG', 'PPG'] | J11: On executing this queri in postgres, gives correct result.,
A12: L1_15 | B12: Target1_15 | C12: ['State', 'Participation_x', 'English', 'Math_x', 'Reading', 'Science', 'Composite', 'Participation_y', 'Evidence-Based Reading and Writing', 'Math_y', 'Total'] | D12: [['Alabama', '100%', 18.9, 18.4, 19.7, 19.4, 19.2, '5%', 593, 572, 1165], ['Alaska', '65%', 18.7, 19.8, 20.4, 19.9, 19.8, '38%', 547, 533, 1080], ['Arizona', '62%', 18.6, 19.8, 20.1, 19.8, 19.7, '30%', 563, 553, 1116]] | E12: Participation is percentage value and join is performed | F12: Source15_0 | G12: [['National', ' 60%', 20.3, 20.7, 21.4, 21.0, 21.0], ['Alabama', '100%', 18.9, 18.4, 19.7, 19.4, 19.2], ['Alaska', '65%', 18.7, 19.8, 20.4, 19.9, 19.8]] | H12: ['State', 'Participation', 'English', 'Math', 'Reading', 'Science', 'Composite'] | M12: 1 | N12: [1.0, 1.0, 1.0, 1.0, 1.0, 1.0, 1.0, 1.0, 1.0, 1.0, 1.0] | R12: 0.27 | T12: 0 | X12: The result and sql seems correct, but still match failed. Can check later why failed
F13: Source15_1 | G13: [['Alabama', '5%', 593, 572, 1165], ['Alaska', '38%', 547, 533, 1080], ['Arizona', '30%', 563, 553, 1116]] | H13: ['State', 'Participation', 'Evidence-Based Reading and Writing', 'Math', 'Total']
A14: L1_16 | B14: Target1_16 | C14: ['CUSTOMERNAME', 'ORDERNUMBER'] | D14: [['Alpha Cognac', 7], ['Amica Models & Co.', 19], ['Auto-Moto Classics Inc.', 3]] | E14: In target, the ordernumber is count for each customername from source table. | F14: Source16_0 | G14: [[10107, 30.0, 95.7, 2.0, 2871.0, '2/24/2003 0:00', 'Shipped', 1.0, 2.0, 2003.0, 'Motorcycles', 95.0, 'S10_1678', 'Land of Toys Inc.', '2125557818', '897 Long Airport Avenue', nan, 'NYC', 'NY', 10022, 'USA', nan, 'Yu', 'Kwai', 'Small'], [10121, 34.0, 81.35, 5.0, 2765.9, '5/7/2003 0:00', 'Shipped', 2.0, 5.0, 2003.0, 'Motorcycles', 95.0, 'S10_1678', 'Reims Collectables', '26.47.1555', "59 rue de l'Abbaye", nan, 'Reims', nan, 51100, 'France', 'EMEA', 'Henriot', 'Paul', 'Small'], [10134, 41.0, 94.74, 2.0, 3884.34, '7/1/2003 0:00', 'Shipped', 3.0, 7.0, 2003.0, 'Motorcycles', 95.0, 'S10_1678', 'Lyon Souveniers', '+33 1 46 62 7555', '27 rue du Colonel Pierre Avia', nan, 'Paris', nan, 75508, 'France', 'EMEA', 'Da Cunha', 'Daniel', 'Medium']] | H14: ['ORDERNUMBER', 'QUANTITYORDERED', 'PRICEEACH', 'ORDERLINENUMBER', 'SALES', 'ORDERDATE', 'STATUS', 'QTR_ID', 'MONTH_ID', 'YEAR_ID', 'PRODUCTLINE', 'MSRP', 'PRODUCTCODE', 'CUSTOMERNAME', 'PHONE', 'ADDRESSLINE1', 'ADDRESSLINE2', 'CITY', 'STATE', 'POSTALCODE', 'COUNTRY', 'TERRITORY', 'CONTACTLASTNAME', 'CONTACTFIRSTNAME', 'DEALSIZE'] | L14: 0 | T14: Fail | V14: Error: ERROR: invalid input syntax for type integer: "10180,29,86.13,9,2497.77,11/11/2003 0:00,Shipped,4,11,2003,Motorcycles,95,S10_1678,Daedalus Designs Imports,20.16.1555,"184, chausse de Tournai",,Lille,,59000,France,EMEA,Rance,Martine,Small" CONTEXT: COPY source16_0, line 8, column ordernumber: "10180,29,86.13,9,2497.77,11/11/2003 0:00,Shipped,4,11,2003,Motorcycles,95,S10_1678,Daedalus Designs ..." | W14: Error: ERROR: invalid input syntax for type integer: "" | Z14: Still failed even after clean.py pre processing | AA14: failed
A15: L1_17 | B15: Target1_17 | C15: ['School ID', 'school_name', 'type', 'size', 'budget', 'Student ID', 'student_name', 'gender', 'grade', 'reading_score', 'math_score'] | D15: [[0, 'Huang High School', 'District', 2917, 1910635, 0, 'Paul Bradley', 'M', '9th', 66, 79], [0, 'Huang High School', 'District', 2917, 1910635, 1, 'Victor Smith', 'M', '12th', 94, 61], [0, 'Huang High School', 'District', 2917, 1910635, 2, 'Kevin Rodriguez', 'M', '12th', 90, 60]] | E15: Join is perfomed from source table. | F15: Source17_0 | G15: [[0, 'Huang High School', 'District', 2917, 1910635], [1, 'Figueroa High School', 'District', 2949, 1884411], [2, 'Shelton High School', 'Charter', 1761, 1056600]] | H15: ['School ID', 'school_name', 'type', 'size', 'budget'] | M15: 0.45 | N15: 0.9996936430942047, 1.0, 1.0, 0.9996936430942047, 0.9996936430942047, 0.6655603778401838, 1.0, 1.0, 1.0, 0.6762318100587184, 0.6737809548123564 | T15: 1 | AA15: success
F16: Source17_1 | G16: [[0, 'Paul Bradley', 'M', '9th', 'Huang High School', 66, 79], [1, 'Victor Smith', 'M', '12th', 'Huang High School', 94, 61], [2, 'Kevin Rodriguez', 'M', '12th', 'Huang High School', 90, 60]] | H16: ['Student ID', 'student_name', 'gender', 'grade', 'school_name', 'reading_score', 'math_score']
A17: L1_18 | B17: Target1_18 | C17: ['y', 'sepal length (cm)', 'sepal width (cm)', 'petal length (cm)', 'petal width (cm)'] | D17: [[0, 50, 50, 50, 50], [1, 25, 25, 25, 25]] | E17: In target, for each y, the count of attribute is calculated from source tables. | F17: Source18_0 | G17: [[5.1, 3.5, 1.4, 0.2, 0.0], [4.9, 3.0, 1.4, 0.2, 0.0], [4.7, 3.2, 1.3, 0.2, 0.0]] | H17: ['sepal length (cm)', 'sepal width (cm)', 'petal length (cm)', 'petal width (cm)', 'y'] | L17: 0 | T17: 0 | Z17: failed | AA17: failed
A18: L1_19 | B18: Target1_19 | C18: ['ocd_prop_id', 'calaccess_prop_id', 'ccdc_prop_id', 'prop_name', 'ccdc_committee_id', 'calaccess_committee_id', 'committee_name_x', 'committee_position', 'committee_name_y', 'calaccess_filing_id', 'date_received', 'contributor_lastname', 'contributor_firstname', 'contributor_city', 'contributor_state', 'contributor_zip', 'contributor_employer', 'contributor_occupation', 'contributor_is_self_employed', 'amount'] | D18: [['ocd-contest/e0c5f9f0-63a9-4c15-9a5c-017e20ac15bc', 1381642, 73, 'PROPOSITION 054 - LEGISLATURE. LEGISLATION AND PROCEEDINGS. INITIATIVE CONSTITUTIONAL AMENDMENT AND STATUTE.', 396, 1389997, 'CALIFORNIA COMMON CAUSE -- YES ON 54 AND 59 (NONPROFIT 501(C)(4)', 'SUPPORT', 'CALIFORNIA COMMON CAUSE -- YES ON 54 AND 59 (NONPROFIT 501(C)(4)', 2098058, '2016-07-01', 'KORMUNDOY', 'EDWARD', 'LOS ANGELES', 'CA', 90026, 'RETIRED', 'RETIRED', False, 100.0], ['ocd-contest/e0c5f9f0-63a9-4c15-9a5c-017e20ac15bc', 1381642, 73, 'PROPOSITION 054 - LEGISLATURE. LEGISLATION AND PROCEEDINGS. INITIATIVE CONSTITUTIONAL AMENDMENT AND STATUTE.', 396, 1389997, 'CALIFORNIA COMMON CAUSE -- YES ON 54 AND 59 (NONPROFIT 501(C)(4)', 'SUPPORT', 'CALIFORNIA COMMON CAUSE -- YES ON 54 AND 59 (NONPROFIT 501(C)(4)', 2098058, '2016-07-03', 'CARSON', 'RICHARD', 'NEVADA CITY', 'CA', 95959, 'RETIRED', 'RETIRED', False, 100.0], ['ocd-contest/e0c5f9f0-63a9-4c15-9a5c-017e20ac15bc', 1381642, 73, 'PROPOSITION 054 - LEGISLATURE. LEGISLATION AND PROCEEDINGS. INITIATIVE CONSTITUTIONAL AMENDMENT AND STATUTE.', 396, 1389997, 'CALIFORNIA COMMON CAUSE -- YES ON 54 AND 59 (NONPROFIT 501(C)(4)', 'SUPPORT', 'CALIFORNIA COMMON CAUSE -- YES ON 54 AND 59 (NONPROFIT 501(C)(4)', 2098058, '2016-09-20', 'MORRISON', 'JAMES', 'HUNTINGTON BEACH', 'CA', 92647, 'RETIRED', 'RETIRED', False, 59.0]] | E18: contributor_zip type should be string in the tables | F18: Source19_0 | G18: [['ocd-contest/b51dc64d-3562-4913-a190-69f5088c22a6', 1376258, 70, 'PROPOSITION 051 - SCHOOL BONDS. FUNDING FOR K-12 SCHOOL AND COMMUNITY COLLEGE FACILITIES. INITIATIVE STATUTORY AMENDMENT.', 382, 1374469, 'YES ON PROPOSITION 51 - CALIFORNIANS FOR QUALITY SCHOOLS, SPONSORED AND FUNDED BY COALITION FOR ADEQUATE SCHOOL HOUSING ISSUES COMMITTEE AND CALIFORNIA BUILDING INDUSTRY ASSOCIATION ISSUES COMMITTEE', 'SUPPORT'], ['ocd-contest/b51dc64d-3562-4913-a190-69f5088c22a6', 1376258, 70, 'PROPOSITION 051 - SCHOOL BONDS. FUNDING FOR K-12 SCHOOL AND COMMUNITY COLLEGE FACILITIES. INITIATIVE STATUTORY AMENDMENT.', 383, 1220380, 'COMMUNITY COLLEGE FACILITY COALITION ISSUES COMMITTEE, YES ON 51', 'SUPPORT'], ['ocd-contest/b51dc64d-3562-4913-a190-69f5088c22a6', 1376258, 70, 'PROPOSITION 051 - SCHOOL BONDS. FUNDING FOR K-12 SCHOOL AND COMMUNITY COLLEGE FACILITIES. INITIATIVE STATUTORY AMENDMENT.', 384, 1282321, "TORLAKSON'S INVEST IN CALIFORNIA A BALLOT MEASURE COMMITTEE TO SUPPORT PROPOSITION 51, SUPERINTENDENT TOM", 'SUPPORT']] | H18: ['ocd_prop_id', 'calaccess_prop_id', 'ccdc_prop_id', 'prop_name', 'ccdc_committee_id', 'calaccess_committee_id', 'committee_name', 'committee_position'] | I18: CREATE TABLE IF NOT EXISTS Source19_0 ( ocd_prop_id TEXT, calaccess_prop_id INTEGER, ccdc_prop_id INTEGER, prop_name TEXT, ccdc_committee_id INTEGER, calaccess_committee_id INTEGER, committee_name TEXT, committee_position TEXT ); CREATE TABLE IF NOT EXISTS Source19_1 ( calaccess_committee_id INTEGER, committee_name TEXT, calaccess_filing_id INTEGER, date_received DATE, contributor_lastname TEXT, contributor_firstname TEXT, contributor_city TEXT, contributor_state TEXT, contributor_zip INTEGER, contributor_employer TEXT, contributor_occupation TEXT, contributor_is_self_employed BOOLEAN, amount FLOAT ); -- Step 2: Insert data into the source tables from CSV files COPY Source19_0 FROM 'D:\lab\ChatGPTwithSQLscript\github-pipelines\length1_19\test_0.csv' DELIMITER ',' CSV HEADER NULL ''; COPY Source19_1 FROM 'D:\lab\ChatGPTwithSQLscript\github-pipelines\length1_19\test_1.csv' DELIMITER ',' CSV HEADER NULL ''; -- Step 3: Create the target table CREATE TABLE IF NOT EXISTS Target1_19 ( ocd_prop_id TEXT, calaccess_prop_id INTEGER, ccdc_prop_id INTEGER, prop_name TEXT, ccdc_committee_id INTEGER, calaccess_committee_id INTEGER, committee_name_x TEXT, committee_position TEXT, committee_name_y TEXT, calaccess_filing_id INTEGER, date_received DATE, contributor_lastname TEXT, contributor_firstname TEXT, contributor_city TEXT, contributor_state TEXT, contributor_zip INTEGER, contributor_employer TEXT, contributor_occupation TEXT, contributor_is_self_employed BOOLEAN, amount FLOAT ); -- Step 4: Insert data into the target table by joining the source tables INSERT INTO Target1_19 ( ocd_prop_id, calaccess_prop_id, ccdc_prop_id, prop_name, ccdc_committee_id, calaccess_committee_id, committee_name_x, committee_position, committee_name_y, calaccess_filing_id, date_received, contributor_lastname, contributor_firstname, contributor_city, contributor_state, contributor_zip, contributor_employer, contributor_occupation, contributor_is_self_employed, amount ) SELECT s0.ocd_prop_id, s0.calaccess_prop_id, s0.ccdc_prop_id, s0.prop_name, s0.ccdc_committee_id, s0.calaccess_committee_id, s0.committee_name, s0.committee_position, s1.committee_name, s1.calaccess_filing_id, s1.date_received, s1.contributor_lastname, s1.contributor_firstname, s1.contributor_city, s1.contributor_state, s1.contributor_zip, s1.contributor_employer, s1.contributor_occupation, s1.contributor_is_self_employed, s1.amount FROM Source19_0 s0 JOIN Source19_1 s1 ON s0.calaccess_committee_id = s1.calaccess_committee_id; -- Step 5: Export the result to a CSV file COPY (SELECT * FROM Target1_19) TO 'D:\lab\ChatGPTwithSQLscript\github-pipelines\length1_19\Target1_19_result.csv' DELIMITER ',' CSV HEADER; | J18: ERROR: invalid input syntax for type integer: "20036-5610" CONTEXT: COPY source19_1, line 56, column contributor_zip: "20036-5610" | T18: 0.95 | U18: 1.0, 1.0, 1.0, 1.0, 1.0, 1.0, 1.0, 1.0, 1.0, 1.0, 1.0, 1.0, 1.0, 1.0, 1.0, 1.0, 1.0, 1.0, 0.0, 1.0 | X18: The csv file cont to compare is same but still last second column shows 0 matching. Check later.
F19: Source19_1 | G19: [[1386560, 'ADULT USE CAMPAIGN FOR PROPOSITION 64; THE', 2083796, '2016-09-18', 'BERGMAN', 'GRETCHEN', 'SPRING VALLEY', 'CA', 91978, 'A NEW PATH', 'EXECUTIVE DIRECTOR', False, 84.0], [1386560, 'ADULT USE CAMPAIGN FOR PROPOSITION 64; THE', 2083796, '2016-09-18', 'KAHLE', 'MYRNA', 'SAN DIEGO', 'CA', 92109, 'NATIONAL SCHOOL DISTRICT', 'TEACHER', False, 35.0], [1386560, 'ADULT USE CAMPAIGN FOR PROPOSITION 64; THE', 2083796, '2016-07-15', 'MCDEVITT', 'LEO', 'ESCONDIDO', 'CA', 92025, 'LIFE IONIZERS', 'SEO/CONTENT MANAGER', False, 198.0]] | H19: ['calaccess_committee_id', 'committee_name', 'calaccess_filing_id', 'date_received', 'contributor_lastname', 'contributor_firstname', 'contributor_city', 'contributor_state', 'contributor_zip', 'contributor_employer', 'contributor_occupation', 'contributor_is_self_employed', 'amount'] | L19: 0
A20: L1_2 | B20: Target1_2 | C20: ['tripduration', 'starttime', 'stoptime', 'start station id', 'start station name', 'start station latitude', 'start station longitude', 'end station id', 'end station name', 'end station latitude', 'end station longitude', 'bikeid', 'usertype', 'birth year', 'gender'] | D20: [[131, '2018-05-01 07:29:57.5490', '2018-05-01 07:32:08.6160', 3183, 'Exchange Place', 40.7162469, -74.0334588, 3184, 'Paulus Hook', 40.7141454, -74.0335519, 29617, 'Subscriber', 1966, 1], [73, '2018-05-01 08:13:58.2560', '2018-05-01 08:15:11.9230', 3183, 'Exchange Place', 40.7162469, -74.0334588, 3184, 'Paulus Hook', 40.7141454, -74.0335519, 29288, 'Subscriber', 1975, 1], [4929, '2018-05-01 08:17:21.3110', '2018-05-01 09:39:31.0770', 3183, 'Exchange Place', 40.7162469, -74.0334588, 3183, 'Exchange Place', 40.7162469, -74.0334588, 29520, 'Customer', 1969, 0]] | F20: Source2_0 | G20: [[329, '2018-06-01 07:07:00.2990', '2018-06-01 07:12:30.2220', 3183, 'Exchange Place', 40.7162469, -74.0334588, 3276, 'Marin Light Rail', 40.71458403535893, -74.04281705617905, 29513, 'Subscriber', 1991, 1], [259, '2018-06-01 08:24:43.8490', '2018-06-01 08:29:03.8450', 3183, 'Exchange Place', 40.7162469, -74.0334588, 3267, 'Morris Canal', 40.7124188237569, -74.03852552175522, 26221, 'Subscriber', 1989, 2], [686, '2018-06-01 09:17:49.5730', '2018-06-01 09:29:16.1770', 3183, 'Exchange Place', 40.7162469, -74.0334588, 3202, 'Newport PATH', 40.7272235, -74.03375890000002, 29266, 'Subscriber', 1990, 1]] | H20: ['tripduration', 'starttime', 'stoptime', 'start station id', 'start station name', 'start station latitude', 'start station longitude', 'end station id', 'end station name', 'end station latitude', 'end station longitude', 'bikeid', 'usertype', 'birth year', 'gender'] | K20: DROP TABLE IF EXISTS Source2_0; CREATE TABLE Source2_0 ( tripduration INTEGER, starttime TIMESTAMP, stoptime TIMESTAMP, "start station id" INTEGER, "start station name" VARCHAR(255), "start station latitude" FLOAT, "start station longitude" FLOAT, "end station id" INTEGER, "end station name" VARCHAR(255), "end station latitude" FLOAT, "end station longitude" FLOAT, bikeid INTEGER, usertype VARCHAR(255), "birth year" INTEGER, gender INTEGER ); DROP TABLE IF EXISTS Source2_1; CREATE TABLE Source2_1 ( tripduration INTEGER, starttime TIMESTAMP, stoptime TIMESTAMP, "start station id" INTEGER, "start station name" VARCHAR(255), "start station latitude" FLOAT, "start station longitude" FLOAT, "end station id" INTEGER, "end station name" VARCHAR(255), "end station latitude" FLOAT, "end station longitude" FLOAT, bikeid INTEGER, usertype VARCHAR(255), "birth year" INTEGER, gender INTEGER ); -- Step 2: Insert data from CSV files into the source tables COPY Source2_0 FROM 'D:\lab\ChatGPTwithSQLscript\github-pipelines\length1_2\test_0.csv' DELIMITER ',' CSV HEADER NULL ''; COPY Source2_1 FROM 'D:\lab\ChatGPTwithSQLscript\github-pipelines\length1_2\test_1.csv' DELIMITER ',' CSV HEADER NULL ''; -- Step 3: Create the target table DROP TABLE IF EXISTS Target1_2; CREATE TABLE Target1_2 ( tripduration INTEGER, starttime TIMESTAMP, stoptime TIMESTAMP, "start station id" INTEGER, "start station name" VARCHAR(255), "start station latitude" FLOAT, "start station longitude" FLOAT, "end station id" INTEGER, "end station name" VARCHAR(255), "end station latitude" FLOAT, "end station longitude" FLOAT, bikeid INTEGER, usertype VARCHAR(255), "birth year" INTEGER, gender INTEGER ); -- Step 4: Insert data from source tables into the target table INSERT INTO Target1_2 ( tripduration, starttime, stoptime, "start station id", "start station name", "start station latitude", "start station longitude", "end station id", "end station name", "end station latitude", "end station longitude", bikeid, usertype, "birth year", gender ) SELECT tripduration, starttime, stoptime, "start station id", "start station name", "start station latitude", "start station longitude", "end station id", "end station name", "end station latitude", "end station longitude", bikeid, usertype, "birth year", gender FROM Source2_0 UNION ALL SELECT tripduration, starttime, stoptime, "start station id", "start station name", "start station latitude", "start station longitude", "end station id", "end station name", "end station latitude", "end station longitude", bikeid, usertype, "birth year", gender FROM Source2_1; -- Step 5: Export the result to a CSV file COPY ( SELECT * FROM Target1_2 ) TO 'D:\lab\ChatGPTwithSQLscript\github-pipelines\length1_2\Target1_2_result.csv' DELIMITER ',' CSV HEADER; | M20: 0.2 | N20: [0.0013109023377758358, 0.0, 0.0, 0.09558662879615469, 1.0, 0.09558662879615469, 0.09558662879615469, 0.04040128177117471, 1.0, 0.04040128177117471, 0.04040128177117471, 0.0019117325759230937, 1.0, 0.035813123588959286, 0.5586264656616415] | Q20: The gpt generate results seems correct but due to ordering the accuracy is so low. Can not figure out the ordering. | T20: 0.87 | U20: 1.0, 0.0, 0.0, 1.0, 1.0, 1.0, 1.0, 1.0, 1.0, 1.0, 1.0, 1.0, 1.0, 1.0, 1.0 | W20: 1.0, 0.0, 0.0, 1.0, 1.0, 1.0, 1.0, 1.0, 1.0, 1.0, 1.0, 1.0, 1.0, 1.0, 1.0 | X20: The sim score is different
F21: Source2_1 | G21: [[131, '2018-05-01 07:29:57.5490', '2018-05-01 07:32:08.6160', 3183, 'Exchange Place', 40.7162469, -74.0334588, 3184, 'Paulus Hook', 40.7141454, -74.0335519, 29617, 'Subscriber', 1966, 1], [73, '2018-05-01 08:13:58.2560', '2018-05-01 08:15:11.9230', 3183, 'Exchange Place', 40.7162469, -74.0334588, 3184, 'Paulus Hook', 40.7141454, -74.0335519, 29288, 'Subscriber', 1975, 1], [4929, '2018-05-01 08:17:21.3110', '2018-05-01 09:39:31.0770', 3183, 'Exchange Place', 40.7162469, -74.0334588, 3183, 'Exchange Place', 40.7162469, -74.0334588, 29520, 'Customer', 1969, 0]] | H21: ['tripduration', 'starttime', 'stoptime', 'start station id', 'start station name', 'start station latitude', 'start station longitude', 'end station id', 'end station name', 'end station latitude', 'end station longitude', 'bikeid', 'usertype', 'birth year', 'gender'] | L21: 0 | X21: After checking both files, ordering
A22: L1_20 | B22: Target1_20 | C22: ['sex', 'smoker', 'total_bill', 'tip', 'size'] | D22: [['Female', 'No', 18.846206896551728, 2.8279310344827597, 2.5172413793103448], ['Female', 'Yes', 18.504, 2.992, 2.0], ['Male', 'No', 19.666615384615387, 3.1616923076923067, 2.569230769230769]] | F22: Source20_0 | G22: [[16.99, 1.01, 'Female', 'No', 'Sun', 'Dinner', 2], [10.34, 1.66, 'Male', 'No', 'Sun', 'Dinner', 3], [21.01, 3.5, 'Male', 'No', 'Sun', 'Dinner', 3]] | H22: ['total_bill', 'tip', 'sex', 'smoker', 'day', 'time', 'size'] | L22: 0 | T22: 0 | Z22: failed | AA22: failed
A23: L1_21 | B23: Target1_21 | C23: ['Major_category', 'Median'] | D23: [['Agriculture & Natural Resources', 55000.0], ['Biology & Life Science', 51833.33333333334], ['Communications & Journalism', 49500.0]] | E23: In target, for Major_category and Median type the , Median are averaged from source table | F23: Source21_0 | G23: [[1100, 'GENERAL AGRICULTURE', 'Agriculture & Natural Resources', 128148, 90245, 74078, 2423, 0.026147106, 50000, 34000, 80000], [1101, 'AGRICULTURE PRODUCTION AND MANAGEMENT', 'Agriculture & Natural Resources', 95326, 76865, 64240, 2266, 0.028636059, 54000, 36000, 80000], [1102, 'AGRICULTURAL ECONOMICS', 'Agriculture & Natural Resources', 33955, 26321, 22810, 821, 0.030248324, 63000, 40000, 98000]] | H23: ['Major_code', 'Major', 'Major_category', 'Total', 'Employed', 'Employed_full_time_year_round', 'Unemployed', 'Unemployment_rate', 'Median', 'P25th', 'P75th'] | K23: DROP TABLE IF EXISTS Source21_0; CREATE TABLE Source21_0 ( Major_code INT, Major VARCHAR(255), Major_category VARCHAR(255), Total INT, Employed INT, Employed_full_time_year_round INT, Unemployed INT, Unemployment_rate FLOAT, Median INT, P25th INT, P75th INT ); -- Insert sample rows into the source table INSERT INTO Source21_0 (Major_code, Major, Major_category, Total, Employed, Employed_full_time_year_round, Unemployed, Unemployment_rate, Median, P25th, P75th) VALUES (1100, 'GENERAL AGRICULTURE', 'Agriculture & Natural Resources', 128148, 90245, 74078, 2423, 0.026147106, 50000, 34000, 80000), (1101, 'AGRICULTURE PRODUCTION AND MANAGEMENT', 'Agriculture & Natural Resources', 95326, 76865, 64240, 2266, 0.028636059, 54000, 36000, 80000), (1102, 'AGRICULTURAL ECONOMICS', 'Agriculture & Natural Resources', 33955, 26321, 22810, 821, 0.030248324, 63000, 40000, 98000); -- Create the target table DROP TABLE IF EXISTS Target1_21; CREATE TABLE Target1_21 ( Major_category VARCHAR(255), Median FLOAT ); -- Insert rows from the source table into the target table INSERT INTO Target1_21 (Major_category, Median) SELECT Major_category, AVG(Median) AS Median FROM Source21_0 GROUP BY Major_category; -- Export the result to a CSV file SELECT * FROM Target1_21; | M23: 0 | Q23: The SQL result is correct but comparision acc is 0 | R23: CSV file upload have more columns | T23: 0 | Z23: success | AA23: failed
A24: L1_22 | B24: Target1_22 | C24: ['condition', 'click'] | D24: [[0, 253], [1, 246]] | F24: Source22_0 | G24: [[1, 0], [0, 0], [0, 0]] | H24: ['condition', 'click'] | L24: 0 | T24: 0 | Z24: failed | AA24: failed
A25: L1_23 | B25: Target1_23 | C25: ['customer_id', 'amount'] | D25: [[80.0, 75.0], [90.0, 121.33333333333331], [130.0, 60.0]] | F25: Source23_0 | G25: [[760, 25, '2009-11-06'], [860, 50, '2012-09-28'], [1200, 100, '2005-10-25']] | H25: ['customer_id', 'amount', 'date'] | L25: 0 | T25: 0 | Z25: failed | AA25: failed
A26: L1_25 | B26: Target1_25 | C26: ['State', 'Participation_x', 'English', 'Math_x', 'Reading', 'Science', 'Composite', 'Participation_y', 'Evidence-Based Reading and Writing', 'Math_y', 'Total'] | D26: [['Alabama', '100%', 18.9, 18.4, 19.7, 19.4, 19.2, '5%', 593, 572, 1165], ['Alaska', '65%', 18.7, 19.8, 20.4, 19.9, 19.8, '38%', 547, 533, 1080], ['Arizona', '62%', 18.6, 19.8, 20.1, 19.8, 19.7, '30%', 563, 553, 1116]] | F26: Source25_0 | G26: [['National', ' 60%', 20.3, 20.7, 21.4, 21.0, 21.0], ['Alabama', '100%', 18.9, 18.4, 19.7, 19.4, 19.2], ['Alaska', '65%', 18.7, 19.8, 20.4, 19.9, 19.8]] | H26: ['State', 'Participation', 'English', 'Math', 'Reading', 'Science', 'Composite'] | K26: DROP TABLE IF EXISTS Source25_0; CREATE TABLE Source25_0 ( State TEXT, Participation TEXT, English FLOAT, Math FLOAT, Reading FLOAT, Science FLOAT, Composite FLOAT ); DROP TABLE IF EXISTS Source25_1; CREATE TABLE Source25_1 ( State TEXT, Participation TEXT, "Evidence-Based Reading and Writing" FLOAT, Math FLOAT, Total FLOAT ); -- Step 2: Insert data into the source tables from CSV files COPY Source25_0 FROM 'D:\lab\ChatGPTwithSQLscript\github-pipelines\length1_25\test_0.csv' DELIMITER ',' CSV HEADER NULL ''; COPY Source25_1 FROM 'D:\lab\ChatGPTwithSQLscript\github-pipelines\length1_25\test_1.csv' DELIMITER ',' CSV HEADER NULL ''; -- Step 3: Create the target table DROP TABLE IF EXISTS Target1_25; CREATE TABLE Target1_25 ( State TEXT, Participation_x TEXT, English FLOAT, Math_x FLOAT, Reading FLOAT, Science FLOAT, Composite FLOAT, Participation_y TEXT, "Evidence-Based Reading and Writing" FLOAT, Math_y FLOAT, Total FLOAT ); -- Step 4: Insert data into the target table by joining the source tables INSERT INTO Target1_25 ( State, Participation_x, English, Math_x, Reading, Science, Composite, Participation_y, "Evidence-Based Reading and Writing", Math_y, Total ) SELECT s0.State, s0.Participation, s0.English, s0.Math, s0.Reading, s0.Science, s0.Composite, s1.Participation, s1."Evidence-Based Reading and Writing", s1.Math, s1.Total FROM Source25_0 s0 JOIN Source25_1 s1 ON s0.State = s1.State; -- Step 5: Export the result to a CSV file COPY Target1_25 TO 'D:\lab\ChatGPTwithSQLscript\github-pipelines\length1_25\Target1_25_result.csv' DELIMITER ',' CSV HEADER; | L26: 0 | M26: 1 | N26: [1.0, 1.0, 1.0, 1.0, 1.0, 1.0, 1.0, 1.0, 1.0, 1.0, 1.0] | T26: 0
F27: Source25_1 | G27: [['Alabama', '5%', 593, 572, 1165], ['Alaska', '38%', 547, 533, 1080], ['Arizona', '30%', 563, 553, 1116]] | H27: ['State', 'Participation', 'Evidence-Based Reading and Writing', 'Math', 'Total'] | L27: 0
A28: L1_27 | B28: Target1_27 | C28: ['day_week', 'ENTRIESn', 'EXITSn', 'ENTRIESn_hourly', 'EXITSn_hourly', 'hour', 'weekday', 'latitude', 'longitude', 'fog', 'precipi', 'pressurei', 'rain', 'tempi', 'wspdi', 'meanprecipi', 'meanpressurei', 'meantempi', 'meanwspdi', 'weather_lat', 'weather_lon'] | D28: [[0.0, 41334339.33534309, 28585085.11857594, 2586.123169681309, 1856.9204708584552, 9.987941429801896, 1.0, 40.74000497243772, -73.93944350760863, 0.0, 0.0006057995980476603, 29.992896927935597, 0.22078667815101924, 62.5368934826296, 8.040453631926482, 0.0006057995980476656, 29.99287635180396, 62.53808976935586, 8.040841228825597, 40.74122319867967, -73.94012390956115], [1.0, 40986712.2318716, 28448771.972198334, 3105.145027228433, 2198.6319862424757, 9.975351103468043, 1.0, 40.74030948208674, -73.93931545887101, 0.006878761822871883, 0.013511034680424241, 29.97894812267107, 0.2003439380911436, 65.74829464029786, 8.44284895385487, 0.013511034680424087, 29.978948122671277, 65.74829464030088, 8.442848953854938, 40.741456139581906, -73.9399656231016], [2.0, 39965661.09031079, 27758647.87678245, 3268.891773308958, 2325.6416819012798, 10.044606946983548, 1.0, 40.73980380767834, -73.93989930310838, 0.0380255941499086, 0.010756855575868356, 29.97335648994529, 0.5023765996343693, 61.41265082266914, 7.8747714808043625, 0.010756855575868522, 29.97335648994478, 61.412650822667224, 7.874771480804461, 40.7409328270569, -73.94060192504577]] | F28: Source27_0 | G28: [['R003', '05-01-11', '00:00:00', 4388333, 2911002, 0, 0, '2011-05-01 00:00:00', 0, 6, 0, 'CYPRESS HILLS', 40.689945, -73.872564, 'Clear', 0, 0.0, 30.22, 0, 55.9, 3.5, 0.0, 30.25800000000001, 55.98, 7.8599999999999985, 40.700348, -73.88717700000002], ['R003', '05-01-11', '04:00:00', 4388333, 2911002, 0, 0, '2011-05-01 04:00:00', 4, 6, 0, 'CYPRESS HILLS', 40.689945, -73.872564, 'Partly Cloudy', 0, 0.0, 30.25, 0, 52.0, 3.5, 0.0, 30.25800000000001, 55.98, 7.8599999999999985, 40.700348, -73.88717700000002], ['R003', '05-01-11', '12:00:00', 4388333, 2911002, 0, 0, '2011-05-01 12:00:00', 12, 6, 0, 'CYPRESS HILLS', 40.689945, -73.872564, 'Mostly Cloudy', 0, 0.0, 30.28, 0, 62.1, 6.9, 0.0, 30.25800000000001, 55.98, 7.8599999999999985, 40.700348, -73.88717700000002]] | H28: ['UNIT', 'DATEn', 'TIMEn', 'ENTRIESn', 'EXITSn', 'ENTRIESn_hourly', 'EXITSn_hourly', 'datetime', 'hour', 'day_week', 'weekday', 'station', 'latitude', 'longitude', 'conds', 'fog', 'precipi', 'pressurei', 'rain', 'tempi', 'wspdi', 'meanprecipi', 'meanpressurei', 'meantempi', 'meanwspdi', 'weather_lat', 'weather_lon'] | L28: 0 | M28: 0 | T28: 0 | Z28: failed | AA28: failed
A29: L1_29 | B29: Target1_29 | C29: ['Gender', '0'] | D29: [['Female', 56], ['Male', 325], ['Other / Non-Disclosed', 9]] | E29: In target, For Gender the 0 is total count for Gender in source table. | F29: Source29_0 | G29: [[0, 'Lisim78', 20, 'Male', 108, 'Extraction, Quickblade Of Trembling Hands', 3.53], [1, 'Lisovynya38', 40, 'Male', 143, 'Frenzied Scimitar', 1.56], [2, 'Ithergue48', 24, 'Male', 92, 'Final Critic', 4.88]] | H29: ['Purchase ID', 'SN', 'Age', 'Gender', 'Item ID', 'Item Name', 'Price'] | K29: DROP TABLE IF EXISTS Source29_0; -- Create the source table CREATE TABLE Source29_0 ( "Purchase ID" INTEGER, "SN" VARCHAR(255), "Age" INTEGER, "Gender" VARCHAR(255), "Item ID" INTEGER, "Item Name" VARCHAR(255), "Price" NUMERIC(10, 2) ); -- Insert sample rows into the source table INSERT INTO Source29_0 ("Purchase ID", "SN", "Age", "Gender", "Item ID", "Item Name", "Price") VALUES (0, 'Lisim78', 20, 'Male', 108, 'Extraction, Quickblade Of Trembling Hands', 3.53), (1, 'Lisovynya38', 40, 'Male', 143, 'Frenzied Scimitar', 1.56), (2, 'Ithergue48', 24, 'Male', 92, 'Final Critic', 4.88); -- Drop the target table if it exists DROP TABLE IF EXISTS Target1_29; -- Create the target table CREATE TABLE Target1_29 ( "Gender" VARCHAR(255), "0" INTEGER ); -- Insert rows from the source table into the target table INSERT INTO Target1_29 ("Gender", "0") SELECT "Gender", COUNT(*) AS "0" FROM Source29_0 GROUP BY "Gender"; -- Export the result to a CSV file COPY (SELECT * FROM Target1_29) TO 'D:\lab\ChatGPTwithSQLscript\github-pipelines\length1_29\Target1_29_result.csv' DELIMITER ',' CSV HEADER; | L29: 0 | M29: 0 | T29: 1 | Z29: success | AA29: failed
A30: L1_3 | B30: Target1_3 | C30: ['Major_category', 'Median'] | D30: [['Agriculture & Natural Resources', 55000.0], ['Biology & Life Science', 51833.33333333334], ['Communications & Journalism', 49500.0]] | E30: The median is target is for each major_category in source. | F30: Source3_0 | G30: [[1100, 'GENERAL AGRICULTURE', 'Agriculture & Natural Resources', 128148, 90245, 74078, 2423, 0.026147106, 50000, 34000, 80000], [1101, 'AGRICULTURE PRODUCTION AND MANAGEMENT', 'Agriculture & Natural Resources', 95326, 76865, 64240, 2266, 0.028636059, 54000, 36000, 80000], [1102, 'AGRICULTURAL ECONOMICS', 'Agriculture & Natural Resources', 33955, 26321, 22810, 821, 0.030248324, 63000, 40000, 98000]] | H30: ['Major_code', 'Major', 'Major_category', 'Total', 'Employed', 'Employed_full_time_year_round', 'Unemployed', 'Unemployment_rate', 'Median', 'P25th', 'P75th'] | K30: CREATE TABLE Source3_0 ( Major_code INT, Major VARCHAR(255), Major_category VARCHAR(255), Total INT, Employed INT, Employed_full_time_year_round INT, Unemployed INT, Unemployment_rate FLOAT, Median INT, P25th INT, P75th INT ); -- Insert sample rows into the source table INSERT INTO Source3_0 (Major_code, Major, Major_category, Total, Employed, Employed_full_time_year_round, Unemployed, Unemployment_rate, Median, P25th, P75th) VALUES (1100, 'GENERAL AGRICULTURE', 'Agriculture & Natural Resources', 128148, 90245, 74078, 2423, 0.026147106, 50000, 34000, 80000), (1101, 'AGRICULTURE PRODUCTION AND MANAGEMENT', 'Agriculture & Natural Resources', 95326, 76865, 64240, 2266, 0.028636059, 54000, 36000, 80000), (1102, 'AGRICULTURAL ECONOMICS', 'Agriculture & Natural Resources', 33955, 26321, 22810, 821, 0.030248324, 63000, 40000, 98000); -- Drop the target table if it exists DROP TABLE IF EXISTS Target1_3; -- Create the target table CREATE TABLE Target1_3 ( Major_category VARCHAR(255), Median INT ); -- Insert rows from the source table into the target table INSERT INTO Target1_3 (Major_category, Median) SELECT Major_category, Median FROM Source3_0; SELECT * FROM Target1_3; | L30: 0 | Q30: The SQL result is correct but comparision acc is 0 | T30: 0 | Y30: 1 | Z30: success
A31: L1_30 | B31: Target1_30 | C31: ['movieId', 'title', 'genres', 'userId', 'tag', 'timestamp'] | D31: [[1, 'Toy Story (1995)', 'Adventure|Animation|Children|Comedy|Fantasy', 501, 'Pixar', 1292956344], [5, 'Father of the Bride Part II (1995)', 'Comedy', 431, 'steve martin', 1140455432], [47, 'Seven (a.k.a. Se7en) (1995)', 'Mystery|Thriller', 364, 'biblical', 1444534976]] | E31: Use Join on source tables | F31: Source30_0 | G31: [[15, 339, "sandra 'boring' bullock", 1138537770], [15, 1955, 'dentist', 1193435061], [15, 7478, 'Cambodia', 1170560997]] | H31: ['userId', 'movieId', 'tag', 'timestamp'] | K31: DROP TABLE IF EXISTS Source30_0; CREATE TABLE Source30_0 ( userId INT, movieId INT, tag TEXT, timestamp INT ); -- Insert data into the first source table from CSV file COPY Source30_0 (userId, movieId, tag, timestamp) FROM 'D:\lab\ChatGPTwithSQLscript\github-pipelines\length1_30\test_0.csv' DELIMITER ',' CSV HEADER NULL ''; -- Create the second source table DROP TABLE IF EXISTS Source30_1; CREATE TABLE Source30_1 ( movieId INT, title TEXT, genres TEXT ); -- Insert data into the second source table from CSV file COPY Source30_1 (movieId, title, genres) FROM 'D:\lab\ChatGPTwithSQLscript\github-pipelines\length1_30\test_1.csv' DELIMITER ',' CSV HEADER NULL ''; -- Create the target table DROP TABLE IF EXISTS Target1_30; CREATE TABLE Target1_30 ( movieId INT, title TEXT, genres TEXT, userId INT, tag TEXT, timestamp INT ); -- Insert data into the target table by joining the source tables INSERT INTO Target1_30 (movieId, title, genres, userId, tag, timestamp) SELECT s1.movieId, s2.title, s2.genres, s1.userId, s1.tag, s1.timestamp FROM Source30_0 s1 JOIN Source30_1 s2 ON s1.movieId = s2.movieId; -- Export the result to a CSV file COPY (SELECT * FROM Target1_30) TO 'D:\lab\ChatGPTwithSQLscript\github-pipelines\length1_30\Target1_30_result.csv' DELIMITER ',' CSV HEADER; | L31: 0 | M31: 0.67 | N31: 1.0, 1.0, 1.0, 0.8536155202821869, 1.0, 0.5343915343915344 | Q31: The SQL is correct and low score is because of exat matching and ordering mismatch in some columns. | T31: 1 | AA31: success
F32: Source30_1 | G32: [[1, 'Toy Story (1995)', 'Adventure|Animation|Children|Comedy|Fantasy'], [2, 'Jumanji (1995)', 'Adventure|Children|Fantasy'], [3, 'Grumpier Old Men (1995)', 'Comedy|Romance']] | H32: ['movieId', 'title', 'genres']
A33: L1_31 | B33: Target1_31 | C33: ['State', 'Participation_x', 'Evidence-Based Reading and Writing', 'Math_x', 'Total', 'Participation_y', 'English', 'Math_y', 'Reading', 'Science', 'Composite'] | D33: [['Alabama', '5%', 593, 572, 1165, '100%', 18.9, 18.4, 19.7, 19.4, 19.2], ['Alaska', '38%', 547, 533, 1080, '65%', 18.7, 19.8, 20.4, 19.9, 19.8], ['Arizona', '30%', 563, 553, 1116, '62%', 18.6, 19.8, 20.1, 19.8, 19.7]] | E33: Use Join on source tables | F33: Source31_0 | G33: [['Alabama', '5%', 593, 572, 1165], ['Alaska', '38%', 547, 533, 1080], ['Arizona', '30%', 563, 553, 1116]] | H33: ['State', 'Participation', 'Evidence-Based Reading and Writing', 'Math', 'Total'] | I33: DROP TABLE IF EXISTS Source31_0; CREATE TABLE Source31_0 ( State VARCHAR, Participation VARCHAR, "Evidence-Based Reading and Writing" FLOAT, Math FLOAT, Total FLOAT ); -- Insert data into the first source table Source31_0 COPY Source31_0 FROM 'D:\lab\ChatGPTwithSQLscript\github-pipelines\length1_31\test_0.csv' DELIMITER ',' CSV NULL ''; -- Create the second source table Source31_1 DROP TABLE IF EXISTS Source31_1; CREATE TABLE Source31_1 ( State VARCHAR, Participation VARCHAR, English FLOAT, Math FLOAT, Reading FLOAT, Science FLOAT, Composite FLOAT ); -- Insert data into the second source table Source31_1 COPY Source31_1 FROM 'D:\lab\ChatGPTwithSQLscript\github-pipelines\length1_31\test_1.csv' DELIMITER ',' CSV NULL ''; -- Create the target table Target1_31 DROP TABLE IF EXISTS Target1_31; CREATE TABLE Target1_31 ( State VARCHAR, Participation_x VARCHAR, "Evidence-Based Reading and Writing" FLOAT, Math_x FLOAT, Total FLOAT, Participation_y VARCHAR, English FLOAT, Math_y FLOAT, Reading FLOAT, Science FLOAT, Composite FLOAT ); -- Insert data into the target table Target1_31 by joining the source tables INSERT INTO Target1_31 ( State, Participation_x, "Evidence-Based Reading and Writing", Math_x, Total, Participation_y, English, Math_y, Reading, Science, Composite ) SELECT s0.State, s0.Participation, s0."Evidence-Based Reading and Writing", s0.Math, s0.Total, s1.Participation, s1.English, s1.Math, s1.Reading, s1.Science, s1.Composite FROM Source31_0 s0 JOIN Source31_1 s1 ON s0.State = s1.State; -- Export the SQL result to a CSV file COPY ( SELECT * FROM Target1_31 ) TO 'D:\lab\ChatGPTwithSQLscript\github-pipelines\length1_31\Target1_31_result.csv' DELIMITER ',' CSV HEADER; | J33: SQL Result: Error: ERROR: invalid input syntax for type double precision: "Evidence-Based Reading and Writing" CONTEXT: COPY source31_0, line 1, column Evidence-Based Reading and Writing: "Evidence-Based Reading and Writing" | K33: DROP TABLE IF EXISTS Source31_0; CREATE TABLE Source31_0 ( State VARCHAR, Participation VARCHAR, "Evidence-Based Reading and Writing" INTEGER, Math INTEGER, Total INTEGER ); -- Insert data into the first source table COPY Source31_0 FROM 'D:\lab\ChatGPTwithSQLscript\github-pipelines\length1_31\test_0.csv' DELIMITER ',' CSV HEADER NULL ''; -- Create the second source table DROP TABLE IF EXISTS Source31_1; CREATE TABLE Source31_1 ( State VARCHAR, Participation VARCHAR, English FLOAT, Math FLOAT, Reading FLOAT, Science FLOAT, Composite FLOAT ); -- Insert data into the second source table COPY Source31_1 FROM 'D:\lab\ChatGPTwithSQLscript\github-pipelines\length1_31\test_1.csv' DELIMITER ',' CSV HEADER NULL ''; -- Create the target table DROP TABLE IF EXISTS Target1_31; CREATE TABLE Target1_31 ( State VARCHAR, Participation_x VARCHAR, "Evidence-Based Reading and Writing" INTEGER, Math_x INTEGER, Total INTEGER, Participation_y VARCHAR, English FLOAT, Math_y FLOAT, Reading FLOAT, Science FLOAT, Composite FLOAT ); -- Insert data into the target table by joining the source tables INSERT INTO Target1_31 ( State, Participation_x, "Evidence-Based Reading and Writing", Math_x, Total, Participation_y, English, Math_y, Reading, Science, Composite ) SELECT s0.State, s0.Participation, s0."Evidence-Based Reading and Writing", s0.Math, s0.Total, s1.Participation, s1.English, s1.Math, s1.Reading, s1.Science, s1.Composite FROM Source31_0 s0 JOIN Source31_1 s1 ON s0.State = s1.State; -- Export the result to a CSV file COPY (SELECT * FROM Target1_31) TO 'D:\lab\ChatGPTwithSQLscript\github-pipelines\length1_31\Target1_31_result.csv' DELIMITER ',' CSV HEADER; | L33: 0.45 | M33: 1 | N33: [1.0, 1.0, 1.0, 1.0, 1.0, 1.0, 1.0, 1.0, 1.0, 1.0, 1.0] | T33: 0
F34: Source31_1 | G34: [['National', ' 60%', 20.3, 20.7, 21.4, 21.0, 21.0], ['Alabama', '100%', 18.9, 18.4, 19.7, 19.4, 19.2], ['Alaska', '65%', 18.7, 19.8, 20.4, 19.9, 19.8]] | H34: ['State', 'Participation', 'English', 'Math', 'Reading', 'Science', 'Composite']
A35: L1_34 | B35: Target1_34 | C35: ['V_GENE'] | D35: [['IGHJ5*02'], ['IGHJ4*02'], ['IGHJ4*02']] | E35: J_call should map to V_GENE | F35: Source34_0 | G35: [['IGHJ5*02'], ['IGHJ4*02'], ['IGHJ4*02']] | H35: ['J_CALL'] | K35: DROP TABLE IF EXISTS Source34_0; -- Create the source table CREATE TABLE Source34_0 ( J_CALL VARCHAR(255) ); -- Insert sample rows into the source table INSERT INTO Source34_0 (J_CALL) VALUES ('IGHJ5*02'), ('IGHJ4*02'), ('IGHJ4*02'); -- Drop the target table if it exists DROP TABLE IF EXISTS Target1_34; -- Create the target table CREATE TABLE Target1_34 ( V_GENE VARCHAR(255) ); -- Insert rows from the source table into the target table INSERT INTO Target1_34 (V_GENE) SELECT J_CALL AS V_GENE FROM Source34_0; -- Export the result to a CSV file COPY (SELECT * FROM Target1_34) TO 'D:\lab\ChatGPTwithSQLscript\github-pipelines\length1_34\Target1_34_result.csv' DELIMITER ',' CSV HEADER; | L35: 1 | M35: 0 | T35: 1 | Z35: success | AA35: success
A36: L1_35 | B36: Target1_35 | C36: ['Source Zipcode', 'Counts'] | D36: [[90230, 1], [90715, 1], [91104, 1]] | E36: The Counts in target is total number of counts for each source zipcode. | F36: Source35_0 | G36: [[90230, 'Private Education and Health Services', 1], [90715, 'Accommodations', 1], [91104, 'Financial Services', 1]] | H36: ['Source Zipcode', 'NAICS Code Description', 'Counts'] | K36: DROP TABLE IF EXISTS Source35_0; -- Create the source table CREATE TABLE Source35_0 ( "Source Zipcode" INTEGER, "NAICS Code Description" VARCHAR, "Counts" INTEGER ); -- Insert sample rows into the source table INSERT INTO Source35_0 ("Source Zipcode", "NAICS Code Description", "Counts") VALUES (90230, 'Private Education and Health Services', 1), (90715, 'Accommodations', 1), (91104, 'Financial Services', 1); -- Drop the target table if it exists DROP TABLE IF EXISTS Target1_35; -- Create the target table CREATE TABLE Target1_35 ( "Source Zipcode" INTEGER, "Counts" INTEGER ); -- Insert rows from the source table into the target table INSERT INTO Target1_35 ("Source Zipcode", "Counts") SELECT "Source Zipcode", "Counts" FROM Source35_0; -- Export the result to a CSV file COPY (SELECT * FROM Target1_35) TO 'D:\lab\ChatGPTwithSQLscript\github-pipelines\length1_35\Target1_35_result.csv' DELIMITER ',' CSV HEADER; | L36: 1 | M36: 0 | T36: 0 | Z36: failed
A37: L1_36 | B37: Target1_36 | C37: ['tripduration', 'starttime', 'stoptime', 'start station id', 'start station name', 'start station latitude', 'start station longitude', 'end station id', 'end station name', 'end station latitude', 'end station longitude', 'bikeid', 'usertype', 'birth year', 'gender'] | D37: [[201, '2019-01-01 03:09:09.7110', '2019-01-01 03:12:30.8790', 3183, 'Exchange Place', 40.7162469, -74.0334588, 3214, 'Essex Light Rail', 40.71277420000001, -74.03648570000001, 29612, 'Subscriber', 1993, 1], [505, '2019-01-01 05:18:00.1060', '2019-01-01 05:26:25.9050', 3183, 'Exchange Place', 40.7162469, -74.0334588, 3638, 'Washington St', 40.7242941, -74.0354826, 29213, 'Subscriber', 1972, 2], [756, '2019-01-01 10:36:33.3400', '2019-01-01 10:49:10.2600', 3183, 'Exchange Place', 40.7162469, -74.0334588, 3192, 'Liberty Light Rail', 40.7112423, -74.0557013, 26164, 'Subscriber', 1985, 1]] | E37: starttime and stoptime are time type. | F37: Source36_0 | G37: [[142, '2019-02-01 15:35:02.0820', '2019-02-01 15:37:24.1360', 3183, 'Exchange Place', 40.7162469, -74.0334588, 3639, 'Harborside', 40.71925170000001, -74.034234, 29677, 'Subscriber', 1963, 1], [223, '2019-02-01 17:00:46.8900', '2019-02-01 17:04:30.5500', 3183, 'Exchange Place', 40.7162469, -74.0334588, 3681, 'Grand St', 40.71517767732029, -74.03768330812454, 26234, 'Subscriber', 1992, 2], [106, '2019-02-01 17:08:01.3260', '2019-02-01 17:09:47.4400', 3183, 'Exchange Place', 40.7162469, -74.0334588, 3184, 'Paulus Hook', 40.7141454, -74.0335519, 29588, 'Subscriber', 1960, 1]] | H37: ['tripduration', 'starttime', 'stoptime', 'start station id', 'start station name', 'start station latitude', 'start station longitude', 'end station id', 'end station name', 'end station latitude', 'end station longitude', 'bikeid', 'usertype', 'birth year', 'gender'] | I37: DROP TABLE IF EXISTS Source36_0; CREATE TABLE Source36_0 ( tripduration INT, starttime TIMESTAMP, stoptime TIMESTAMP, "start station id" INT, "start station name" VARCHAR(255), "start station latitude" FLOAT, "start station longitude" FLOAT, "end station id" INT, "end station name" VARCHAR(255), "end station latitude" FLOAT, "end station longitude" FLOAT, bikeid INT, usertype VARCHAR(255), "birth year" INT, gender INT ); -- Insert rows into the first source table Source36_0 INSERT INTO Source36_0 (tripduration, starttime, stoptime, "start station id", "start station name", "start station latitude", "start station longitude", "end station id", "end station name", "end station latitude", "end station longitude", bikeid, usertype, "birth year", gender) VALUES (142, '2019-02-01 15:35:02.0820', '2019-02-01 15:37:24.1360', 3183, 'Exchange Place', 40.7162469, -74.0334588, 3639, 'Harborside', 40.71925170000001, -74.034234, 29677, 'Subscriber', 1963, 1), (223, '2019-02-01 17:00:46.8900', '2019-02-01 17:04:30.5500', 3183, 'Exchange Place', 40.7162469, -74.0334588, 3681, 'Grand St', 40.71517767732029, -74.03768330812454, 26234, 'Subscriber', 1992, 2), (106, '2019-02-01 17:08:01.3260', '2019-02-01 17:09:47.4400', 3183, 'Exchange Place', 40.7162469, -74.0334588, 3184, 'Paulus Hook', 40.7141454, -74.0335519, 29588, 'Subscriber', 1960, 1); -- Create the second source table Source36_1 DROP TABLE IF EXISTS Source36_1; CREATE TABLE Source36_1 ( tripduration INT, starttime TIMESTAMP, stoptime TIMESTAMP, "start station id" INT, "start station name" VARCHAR(255), "start station latitude" FLOAT, "start station longitude" FLOAT, "end station id" INT, "end station name" VARCHAR(255), "end station latitude" FLOAT, "end station longitude" FLOAT, bikeid INT, usertype VARCHAR(255), "birth year" INT, gender INT ); -- Insert rows into the second source table Source36_1 INSERT INTO Source36_1 (tripduration, starttime, stoptime, "start station id", "start station name", "start station latitude", "start station longitude", "end station id", "end station name", "end station latitude", "end station longitude", bikeid, usertype, "birth year", gender) VALUES (201, '2019-01-01 03:09:09.7110', '2019-01-01 03:12:30.8790', 3183, 'Exchange Place', 40.7162469, -74.0334588, 3214, 'Essex Light Rail', 40.71277420000001, -74.03648570000001, 29612, 'Subscriber', 1993, 1), (505, '2019-01-01 05:18:00.1060', '2019-01-01 05:26:25.9050', 3183, 'Exchange Place', 40.7162469, -74.0334588, 3638, 'Washington St', 40.7242941, -74.0354826, 29213, 'Subscriber', 1972, 2), (756, '2019-01-01 10:36:33.3400', '2019-01-01 10:49:10.2600', 3183, 'Exchange Place', 40.7162469, -74.0334588, 3192, 'Liberty Light Rail', 40.7112423, -74.0557013, 26164, 'Subscriber', 1985, 1); -- Create the target table Target1_36 DROP TABLE IF EXISTS Target1_36; CREATE TABLE Target1_36 ( tripduration INT, starttime TIMESTAMP, stoptime TIMESTAMP, "start station id" INT, "start station name" VARCHAR(255), "start station latitude" FLOAT, "start station longitude" FLOAT, "end station id" INT, "end station name" VARCHAR(255), "end station latitude" FLOAT, "end station longitude" FLOAT, bikeid INT, usertype VARCHAR(255), "birth year" INT, gender INT ); -- Insert rows into the target table Target1_36 by joining the source tables INSERT INTO Target1_36 (tripduration, starttime, stoptime, "start station id", "start station name", "start station latitude", "start station longitude", "end station id", "end station name", "end station latitude", "end station longitude", bikeid, usertype, "birth year", gender) SELECT s0.tripduration, s0.starttime, s0.stoptime, s0."start station id", s0."start station name", s0."start station latitude", s0."start station longitude", s0."end station id", s0."end station name", s0."end station latitude", s0."end station longitude", s0.bikeid, s0.usertype, s0."birth year", s0.gender FROM Source36_0 s0 UNION ALL SELECT s1.tripduration, s1.starttime, s1.stoptime, s1."start station id", s1."start station name", s1."start station latitude", s1."start station longitude", s1."end station id", s1."end station name", s1."end station latitude", s1."end station longitude", s1.bikeid, s1.usertype, s1."birth year", s1.gender FROM Source36_1 s1; -- Export the result to a CSV file COPY (SELECT * FROM Target1_36) TO 'D:\lab\ChatGPTwithSQLscript\github-pipelines\length1_36\Target1_36_result.csv' DELIMITER ',' CSV HEADER; | L37: 0 | M37: 0 | Q37: It is not a join, stack operation could be there. Test_1 file have same City hall values as target. | T37: Fail | V37: ERROR: invalid input syntax for type timestamp: "35:02.1"
F38: Source36_1 | G38: [[201, '2019-01-01 03:09:09.7110', '2019-01-01 03:12:30.8790', 3183, 'Exchange Place', 40.7162469, -74.0334588, 3214, 'Essex Light Rail', 40.71277420000001, -74.03648570000001, 29612, 'Subscriber', 1993, 1], [505, '2019-01-01 05:18:00.1060', '2019-01-01 05:26:25.9050', 3183, 'Exchange Place', 40.7162469, -74.0334588, 3638, 'Washington St', 40.7242941, -74.0354826, 29213, 'Subscriber', 1972, 2], [756, '2019-01-01 10:36:33.3400', '2019-01-01 10:49:10.2600', 3183, 'Exchange Place', 40.7162469, -74.0334588, 3192, 'Liberty Light Rail', 40.7112423, -74.0557013, 26164, 'Subscriber', 1985, 1]] | H38: ['tripduration', 'starttime', 'stoptime', 'start station id', 'start station name', 'start station latitude', 'start station longitude', 'end station id', 'end station name', 'end station latitude', 'end station longitude', 'bikeid', 'usertype', 'birth year', 'gender']
A39: L1_37 | B39: Target1_37 | C39: ['business_id', 'Score', 'date', 'type', 'ViolationTypeID', 'risk_category', 'description'] | D39: [[10, 94.0, 20140729, 'Routine - Unscheduled', 103129, 'Moderate Risk', 'Insufficient hot water or running water'], [10, 94.0, 20140729, 'Routine - Unscheduled', 103144, 'Low Risk', 'Unapproved or unmaintained equipment or utensils'], [10, 92.0, 20140114, 'Routine - Unscheduled', 103154, 'Low Risk', 'Unclean or degraded floors walls or ceilings']] | E39: Use Join on source tables on business_id and date. | F39: Source37_0 | G39: [[10, nan, 20140807, 'Reinspection/Followup'], [10, 94.0, 20140729, 'Routine - Unscheduled'], [10, nan, 20140124, 'Reinspection/Followup']] | H39: ['business_id', 'Score', 'date', 'type'] | K39: DROP TABLE IF EXISTS Source37_0; CREATE TABLE Source37_0 ( business_id INTEGER, Score FLOAT, date INTEGER, type VARCHAR ); DROP TABLE IF EXISTS Source37_1; CREATE TABLE Source37_1 ( business_id INTEGER, date INTEGER, ViolationTypeID INTEGER, risk_category VARCHAR, description VARCHAR ); -- Step 2: Insert data into the source tables COPY Source37_0 (business_id, Score, date, type) FROM 'D:\lab\ChatGPTwithSQLscript\github-pipelines\length1_37\test_0.csv' DELIMITER ',' CSV HEADER NULL ''; COPY Source37_1 (business_id, date, ViolationTypeID, risk_category, description) FROM 'D:\lab\ChatGPTwithSQLscript\github-pipelines\length1_37\test_1.csv' DELIMITER ',' CSV HEADER NULL ''; -- Step 3: Create the target table DROP TABLE IF EXISTS Target1_37; CREATE TABLE Target1_37 ( business_id INTEGER, Score FLOAT, date INTEGER, type VARCHAR, ViolationTypeID INTEGER, risk_category VARCHAR, description VARCHAR ); -- Step 4: Insert data into the target table INSERT INTO Target1_37 (business_id, Score, date, type, ViolationTypeID, risk_category, description) SELECT s0.business_id, s0.Score, s0.date, s0.type, s1.ViolationTypeID, s1.risk_category, s1.description FROM Source37_0 s0 JOIN Source37_1 s1 ON s0.business_id = s1.business_id AND s0.date = s1.date; -- Step 5: Export the result to a CSV file COPY (SELECT * FROM Target1_37) TO 'D:\lab\ChatGPTwithSQLscript\github-pipelines\length1_37\Target1_37_result.csv' DELIMITER ',' CSV HEADER; | L39: 0 | M39: 0 | N39: 0.14 | Q39: Validation fails due to validation script, sql is correct after target data description. After updating validation script for numerical_similarity, the similarity score was calculated. | R39: False [0.8740395809080326, 0.23031431897555296, 0.21373690337601864, 1.0, 0.11590221187427241, 0.6, 0.9701492537313433] | V39: Error: ERROR: invalid input syntax for type double precision: "" CONTEXT: COPY source37_0, line 2, column score: ""
F40: Source37_1 | G40: [[10, 20140114, 103154, 'Low Risk', 'Unclean or degraded floors walls or ceilings'], [10, 20140114, 103119, 'Moderate Risk', 'Inadequate and inaccessible handwashing facilities'], [10, 20140114, 103145, 'Low Risk', 'Improper storage of equipment utensils or linens']] | H40: ['business_id', 'date', 'ViolationTypeID', 'risk_category', 'description']
A41: L1_38 | B41: Target1_38 | C41: ['user_id', 'sad', 'stressed'] | D41: [[2.0, 0.4081632653061225, 0.17346938775510204], [4.0, 0.0078125, 0.015625], [5.0, 0.0, 0.037037037037037035]] | E41: In target, the sad and stressed are average for each user id in source. Final table have order as per user_id. | F41: Source38_0 | G41: [[2, '2009-01-09 19:38:00', 0, 0, 0, 0, 1, 1], [2, '2009-01-10 13:36:00', 0, 0, 0, 0, 1, 1], [2, '2009-01-11 12:58:00', 0, 0, 0, 0, 0, 0]] | H41: ['user_id', 'time', 'sore.throat.cough', 'runnynose.congestion.sneezing', 'fever', 'nausea.vomiting.diarrhea', 'sad.depressed', 'open.stressed'] | I41: DROP TABLE IF EXISTS Source38_0; -- Create the source table CREATE TABLE Source38_0 ( user_id INTEGER, time TIMESTAMP, sore_throat_cough INTEGER, runnynose_congestion_sneezing INTEGER, fever INTEGER, nausea_vomiting_diarrhea INTEGER, sad_depressed INTEGER, open_stressed INTEGER ); -- Insert sample rows into the source table -- INSERT INTO Source38_0 (user_id, time, sore_throat_cough, runnynose_congestion_sneezing, fever, nausea_vomiting_diarrhea, sad_depressed, open_stressed) -- VALUES (2, '2009-01-09 19:38:00', 0, 0, 0, 0, 1, 1), -- (2, '2009-01-10 13:36:00', 0, 0, 0, 0, 1, 1), -- (2, '2009-01-11 12:58:00', 0, 0, 0, 0, 0, 0); copy Source38_0 FROM 'D:\lab\ChatGPTwithSQLscript\github-pipelines\length1_38\test_0.csv' DELIMITER ',' CSV HEADER ENCODING 'UTF8' ESCAPE ''''; -- Drop the target table if it exists DROP TABLE IF EXISTS Target1_38; -- Create the target table CREATE TABLE Target1_38 ( user_id INTEGER, sad FLOAT, stressed FLOAT ); -- Insert rows from the source table into the target table INSERT INTO Target1_38 (user_id, sad, stressed) SELECT user_id, AVG(sad_depressed) AS sad, AVG(open_stressed) AS stressed FROM Source38_0 GROUP BY user_id; -- Export the result to a CSV file COPY (SELECT * FROM Target1_38) TO 'D:\lab\ChatGPTwithSQLscript\github-pipelines\length1_38\Target1_38_result.csv' CSV HEADER; | J41: Order By user_id | K41: DROP TABLE IF EXISTS Source38_0; -- Create the source table CREATE TABLE Source38_0 ( user_id INTEGER, time TIMESTAMP, sore_throat_cough INTEGER, runnynose_congestion_sneezing INTEGER, fever INTEGER, nausea_vomiting_diarrhea INTEGER, sad_depressed INTEGER, open_stressed INTEGER ); -- Insert sample rows into the source table -- INSERT INTO Source38_0 (user_id, time, sore_throat_cough, runnynose_congestion_sneezing, fever, nausea_vomiting_diarrhea, sad_depressed, open_stressed) -- VALUES (2, '2009-01-09 19:38:00', 0, 0, 0, 0, 1, 1), -- (2, '2009-01-10 13:36:00', 0, 0, 0, 0, 1, 1), -- (2, '2009-01-11 12:58:00', 0, 0, 0, 0, 0, 0); copy Source38_0 FROM 'D:\lab\ChatGPTwithSQLscript\github-pipelines\length1_38\test_0.csv' DELIMITER ',' CSV HEADER ENCODING 'UTF8' ESCAPE ''''; -- Drop the target table if it exists DROP TABLE IF EXISTS Target1_38; -- Create the target table CREATE TABLE Target1_38 ( user_id INTEGER, sad FLOAT, stressed FLOAT ); -- Insert rows from the source table into the target table INSERT INTO Target1_38 (user_id, sad, stressed) SELECT user_id, AVG(sad_depressed) AS sad, AVG(open_stressed) AS stressed FROM Source38_0 GROUP BY user_id ORDER BY user_id; -- Export the result to a CSV file COPY (SELECT * FROM Target1_38) TO 'D:\lab\ChatGPTwithSQLscript\github-pipelines\length1_38\Target1_38_result.csv' CSV HEADER; | L41: 0 | M41: 0 | Q41: This query would fail if target discrption does not have order by hint. | Z41: failed
A42: L1_4 | B42: Target1_4 | C42: ['fname', 'count_of_obs'] | D42: [['01_1D_11', 24], ['01_1D_13', 24], ['01_1D_15', 24]] | E42: In target table, the count_of_obs has the total count of fname for each fname. The final result should have order as per fname. | F42: Source4_0 | G42: [[40, 91, 38, 0.0, 119, 1, 0, 0, '26_6B', 11, '26_6B_11'], [46, 100, 29, 1.459, 170, 1, 0, 0, '01_2C', 15, '01_2C_15'], [26, 12, 76, 0.0, 149, 1, 0, 0, '71_1C', 11, '71_1C_11']] | H42: ['Slice n°', 'X', 'Y', 'Distance', 'Pixel Value', 'ok_col_names', 'ok_col_num', 'ok_row_num', 'cop_name', 'day', 'fname'] | I42: COPY Source4_0 FROM 'D:\lab\ChatGPTwithSQLscript\github-pipelines\length1_4\test_0.csv' CSV HEADER NULL AS 'nan'; | J42: Slice nÃ‚Â° name could not be read. Had to make it 'Slice n' | K42: DROP TABLE IF EXISTS Source4_0; -- Create the source table CREATE TABLE Source4_0 ( "Slice n" INTEGER, "X" INTEGER, "Y" INTEGER, "Distance" FLOAT, "Pixel Value" INTEGER, "ok_col_names" INTEGER, "ok_col_num" INTEGER, "ok_row_num" INTEGER, "cop_name" VARCHAR(10), "day" INTEGER, "fname" VARCHAR(10) ); copy Source4_0 FROM 'D:\lab\ChatGPTwithSQLscript\github-pipelines\length1_4\test_0.csv' DELIMITER ',' CSV HEADER ENCODING 'UTF8' ESCAPE ''''; -- Insert sample rows into the source table -- INSERT INTO Source4_0 ("Slice n ", "X", "Y", "Distance", "Pixel Value", "ok_col_names", "ok_col_num", "ok_row_num", "cop_name", "day", "fname") -- VALUES (40, 91, 38, 0.0, 119, 1, 0, 0, '26_6B', 11, '26_6B_11'), -- (46, 100, 29, 1.459, 170, 1, 0, 0, '01_2C', 15, '01_2C_15'), -- (26, 12, 76, 0.0, 149, 1, 0, 0, '71_1C', 11, '71_1C_11'); -- Drop the target table if it exists DROP TABLE IF EXISTS Target1_4; -- Create the target table CREATE TABLE Target1_4 ( "fname" VARCHAR(10), "count_of_obs" INTEGER ); -- Insert rows from the source table into the target table INSERT INTO Target1_4 ("fname", "count_of_obs") SELECT "fname", COUNT("fname") FROM Source4_0 GROUP BY "fname" ORDER BY "fname"; -- Export the result to a CSV file COPY (SELECT * FROM Target1_4) TO 'D:\lab\ChatGPTwithSQLscript\github-pipelines\length1_4\Target1_4_result_new.csv' CSV HEADER; | L42: 0 | M42: 0 | Q42: This query would execute if we upload the csv file by making attribute name change manually and add ORDER BY "fname" in SQL query to get exact row-by-row match. | T42: 1 | Y42: 1 | Z42: success | AA42: success
A43: L1_40 | B43: Target1_40 | C43: ['CUSTOMERNAME', 'ORDERNUMBER', 'QUANTITYORDERED'] | D43: [['Alpha Cognac', 10136, 102], ['Alpha Cognac', 10178, 155], ['Amica Models & Co.', 10280, 432]] | E43: In target table, quantityordered is the sum of qualtityordered in source for each order number. | F43: Source40_0 | G43: [[10107, 30.0, 95.7, 2.0, 2871.0, '2/24/2003 0:00', 'Shipped', 1.0, 2.0, 2003.0, 'Motorcycles', 95.0, 'S10_1678', 'Land of Toys Inc.', '2125557818', '897 Long Airport Avenue', nan, 'NYC', 'NY', 10022, 'USA', nan, 'Yu', 'Kwai', 'Small'], [10121, 34.0, 81.35, 5.0, 2765.9, '5/7/2003 0:00', 'Shipped', 2.0, 5.0, 2003.0, 'Motorcycles', 95.0, 'S10_1678', 'Reims Collectables', '26.47.1555', "59 rue de l'Abbaye", nan, 'Reims', nan, 51100, 'France', 'EMEA', 'Henriot', 'Paul', 'Small'], [10134, 41.0, 94.74, 2.0, 3884.34, '7/1/2003 0:00', 'Shipped', 3.0, 7.0, 2003.0, 'Motorcycles', 95.0, 'S10_1678', 'Lyon Souveniers', '+33 1 46 62 7555', '27 rue du Colonel Pierre Avia', nan, 'Paris', nan, 75508, 'France', 'EMEA', 'Da Cunha', 'Daniel', 'Medium']] | H43: ['ORDERNUMBER', 'QUANTITYORDERED', 'PRICEEACH', 'ORDERLINENUMBER', 'SALES', 'ORDERDATE', 'STATUS', 'QTR_ID', 'MONTH_ID', 'YEAR_ID', 'PRODUCTLINE', 'MSRP', 'PRODUCTCODE', 'CUSTOMERNAME', 'PHONE', 'ADDRESSLINE1', 'ADDRESSLINE2', 'CITY', 'STATE', 'POSTALCODE', 'COUNTRY', 'TERRITORY', 'CONTACTLASTNAME', 'CONTACTFIRSTNAME', 'DEALSIZE'] | I43: DROP TABLE IF EXISTS Source40_0; -- Create the source table CREATE TABLE Source40_0 ( ORDERNUMBER INTEGER, QUANTITYORDERED NUMERIC, PRICEEACH NUMERIC, ORDERLINENUMBER NUMERIC, SALES NUMERIC, ORDERDATE TIMESTAMP, STATUS VARCHAR(255), QTR_ID NUMERIC, MONTH_ID NUMERIC, YEAR_ID NUMERIC, PRODUCTLINE VARCHAR(255), MSRP NUMERIC, PRODUCTCODE VARCHAR(255), CUSTOMERNAME VARCHAR(255), PHONE VARCHAR(255), ADDRESSLINE1 VARCHAR(255), ADDRESSLINE2 VARCHAR(255), CITY VARCHAR(255), STATE VARCHAR(255), POSTALCODE INTEGER, COUNTRY VARCHAR(255), TERRITORY VARCHAR(255), CONTACTLASTNAME VARCHAR(255), CONTACTFIRSTNAME VARCHAR(255), DEALSIZE VARCHAR(255) ); -- entire file COPY Source40_0 FROM 'D:\lab\ChatGPTwithSQLscript\github-pipelines\length1_40\test_0.csv' CSV HEADER NULL AS 'nan'; -- Insert sample rows into the source table -- INSERT INTO Source40_0 (ORDERNUMBER, QUANTITYORDERED, PRICEEACH, ORDERLINENUMBER, SALES, ORDERDATE, STATUS, QTR_ID, MONTH_ID, YEAR_ID, PRODUCTLINE, MSRP, PRODUCTCODE, CUSTOMERNAME, PHONE, ADDRESSLINE1, ADDRESSLINE2, CITY, STATE, POSTALCODE, COUNTRY, TERRITORY, CONTACTLASTNAME, CONTACTFIRSTNAME, DEALSIZE) -- VALUES (10107, 30.0, 95.7, 2.0, 2871.0, '2003-02-24 00:00:00', 'Shipped', 1.0, 2.0, 2003.0, 'Motorcycles', 95.0, 'S10_1678', 'Land of Toys Inc.', '2125557818', '897 Long Airport Avenue', NULL, 'NYC', 'NY', 10022, 'USA', NULL, 'Yu', 'Kwai', 'Small'), -- (10121, 34.0, 81.35, 5.0, 2765.9, '2003-05-07 00:00:00', 'Shipped', 2.0, 5.0, 2003.0, 'Motorcycles', 95.0, 'S10_1678', 'Reims Collectables', '26.47.1555', '59 rue de l''Abbaye', NULL, 'Reims', NULL, 51100, 'France', 'EMEA', 'Henriot', 'Paul', 'Small'), -- (10134, 41.0, 94.74, 2.0, 3884.34, '2003-07-01 00:00:00', 'Shipped', 3.0, 7.0, 2003.0, 'Motorcycles', 95.0, 'S10_1678', 'Lyon Souveniers', '+33 1 46 62 7555', '27 rue du Colonel Pierre Avia', NULL, 'Paris', NULL, 75508, 'France', 'EMEA', 'Da Cunha', 'Daniel', 'Medium'); -- Drop the target table if it exists DROP TABLE IF EXISTS Target1_40; -- Create the target table CREATE TABLE Target1_40 ( CUSTOMERNAME VARCHAR(255), ORDERNUMBER INTEGER, QUANTITYORDERED NUMERIC ); -- Insert rows from the source table into the target table INSERT INTO Target1_40 (CUSTOMERNAME, ORDERNUMBER, QUANTITYORDERED) SELECT CUSTOMERNAME, ORDERNUMBER, SUM(QUANTITYORDERED) FROM Source40_0 GROUP BY CUSTOMERNAME, ORDERNUMBER; -- Export the result to a CSV file COPY (SELECT * FROM Target1_40) TO 'D:\lab\ChatGPTwithSQLscript\github-pipelines\length1_40\Target1_40_result.csv' DELIMITER ',' CSV HEADER; | J43: ERROR: invalid input syntax for type integer: "" CONTEXT: COPY source40_0, line 6, column postalcode: "" SQL state: 22P02 | L43: fail | M43: 0 | Q43: This failure is due to the csv file read have issue with , in the data, e.g.line 6 in test_0.csv | T43: Fail | V43: ERROR: Error: ERROR: invalid input syntax for type integer: "10180,29,86.13,9,2497.77,11/11/2003 0:00,Shipped,4,11,2003,Motorcycles,95,S10_1678,Daedalus Designs Imports,20.16.1555,"184, chausse de Tournai",,Lille,,59000,France,EMEA,Rance,Martine,Small" CONTEXT: COPY source40_0, line 8, column ordernumber: "10180,29,86.13,9,2497.77,11/11/2003 0:00,Shipped,4,11,2003,Motorcycles,95,S10_1678,Daedalus Designs ..." | AA43: data pre processing error
A44: L1_41 | B44: Target1_41 | C44: ['zipcode', 'AGI_STUB', 'N1', 'A00100'] | D44: [[0, 546, 75619290, 4857739566], [1001, 21, 8780, 458716], [1002, 21, 9460, 732849]] | E44: In target, the AGI_STUB , N1, A00100 are the sum for each zipcode in source table. | F44: Source41_0 | G44: [[1, 'AL', 0, 1, 889920, 490850, 129070, 256900, 526740, 1505430, 598680, 11517112, 712630, 9014595, 116620, 101108, 49750, 92178, 43200, 59907, 150240, 873349, 9120, 35010, -3916, 38910, 221795, 112470, 1072785, 65230, 265804, 34100, 59389, 260, 843, 62190, 968541, 62120, 850798, 24840, 23577, 29040, 23668, 33360, 27495, 60070, 90908, 31110, 181519, 46490, 121095, 356200, 1962972, 112340, 38443, 39440, 12168, 9920, 3393, 1680, 408, 406300, 1178852, 379060, 1071400, 266230, 335781, 0, 0, 269140, 168057, 387720, 314297, 59310, 40782, 785950, 2040191], [1, 'AL', 0, 2, 491150, 194370, 159200, 123350, 293480, 1034650, 387700, 17617800, 428710, 14482697, 107970, 101203, 43720, 101793, 37910, 68476, 61720, 277466, 9210, 30710, 21881, 34870, 314019, 102070, 1750044, 30620, 109617, 85660, 521123, 360, 1962, 129250, 4897366, 129230, 1914481, 92510, 151956, 27820, 34819, 87590, 67397, 124940, 286169, 83250, 486909, 103450, 358997, 471490, 8655664, 213860, 195459, 128810, 116182, 29670, 17003, 8030, 3038, 128140, 235609, 107760, 202016, 102930, 153772, 0, 0, 370140, 854669, 389320, 937609, 62450, 85568, 421290, 1185415], [1, 'AL', 0, 3, 254280, 68160, 148960, 31480, 157230, 591880, 188670, 15644666, 221520, 12162751, 94810, 102766, 41880, 121653, 36720, 83798, 39520, 254111, 8150, 30190, 47365, 27460, 337870, 72270, 1692583, 15190, 59496, 57280, 807546, 340, 2559, 112570, 6984334, 112550, 1914831, 91960, 229994, 17400, 25542, 92990, 82247, 112220, 368093, 87520, 581501, 96530, 404644, 253210, 9996182, 112520, 169569, 78390, 119471, 19160, 10007, 7240, 2715, 120, 3, 90, 2, 10020, 12913, 100, 73, 242260, 1214154, 245280, 1286668, 55290, 113674, 193020, 550512]] | H44: ['STATEFIPS', 'STATE', 'zipcode', 'AGI_STUB', 'N1', 'MARS1', 'MARS2', 'MARS4', 'PREP', 'N2', 'NUMDEP', 'A00100', 'N00200', 'A00200', 'N00300', 'A00300', 'N00600', 'A00600', 'N00650', 'A00650', 'N00900', 'A00900', 'SCHF', 'N01000', 'A01000', 'N01400', 'A01400', 'N01700', 'A01700', 'N02300', 'A02300', 'N02500', 'A02500', 'N03300', 'A03300', 'N00101', 'A00101', 'N04470', 'A04470', 'N18425', 'A18425', 'N18450', 'A18450', 'N18500', 'A18500', 'N18300', 'A18300', 'N19300', 'A19300', 'N19700', 'A19700', 'N04800', 'A04800', 'N07100', 'A07100', 'N07220', 'A07220', 'N07180', 'A07180', 'N07260', 'A07260', 'N59660', 'A59660', 'N59720', 'A59720', 'N11070', 'A11070', 'N09600', 'A09600', 'N06500', 'A06500', 'N10300', 'A10300', 'N11901', 'A11901', 'N11902', 'A11902'] | I44: DROP TABLE IF EXISTS Source41_0; CREATE TABLE Source41_0 ( STATEFIPS INT, STATE VARCHAR(2), zipcode INT, AGI_STUB INT, N1 INT, MARS1 INT, MARS2 INT, MARS4 INT, PREP INT, N2 INT, NUMDEP INT, A00100 INT, N00200 INT, A00200 INT, N00300 INT, A00300 INT, N00600 INT, A00600 INT, N00650 INT, A00650 INT, N00900 INT, A00900 INT, SCHF INT, N01000 INT, A01000 INT, N01400 INT, A01400 INT, N01700 INT, A01700 INT, N02300 INT, A02300 INT, N02500 INT, A02500 INT, N03300 INT, A03300 INT, N00101 INT, A00101 INT, N04470 INT, A04470 INT, N18425 INT, A18425 INT, N18450 INT, A18450 INT, N18500 INT, A18500 INT, N18300 INT, A18300 INT, N19300 INT, A19300 INT, N19700 INT, A19700 INT, N04800 INT, A04800 INT, N07100 INT, A07100 INT, N07220 INT, A07220 INT, N07180 INT, A07180 INT, N07260 INT, A07260 INT, N59660 INT, A59660 INT, N59720 INT, A59720 INT, N11070 INT, A11070 INT, N09600 INT, A09600 INT, N06500 INT, A06500 INT, N10300 INT, A10300 INT, N11901 INT, A11901 INT, N11902 INT, A11902 INT ); --entire file copy Source41_0 from 'D:\lab\ChatGPTwithSQLscript\github-pipelines\length1_41\test_0.csv' CSV HEADER NULL AS 'nan'; -- Step 3: Create the target table DROP TABLE IF EXISTS Target1_41; CREATE TABLE Target1_41 ( zipcode INT, AGI_STUB INT, N1 INT, A00100 INT ); -- Step 4: Insert rows from source table into target table INSERT INTO Target1_41 (zipcode, AGI_STUB, N1, A00100) SELECT zipcode, AGI_STUB, SUM(N1), SUM(A00100) FROM Source41_0 GROUP BY zipcode, AGI_STUB; -- Step 5: Export the result to a CSV file COPY (SELECT * FROM Target1_41) TO 'D:\lab\ChatGPTwithSQLscript\github-pipelines\length1_41\Target1_41_result.csv' DELIMITER ',' CSV HEADER; | J44: SQL Query executes but total number of rows are different. Target has 13862 rows but gpt produced 83156 | L44: 0 | M44: 0 | Q44: The conversion seems sum of source values but , target results are not matching the results. | R44: Need to figure out the duplicate values as number of rows are way too much different. | T44: 0 | Z44: failed | AA44: failed
A45: L1_42 | B45: Target1_42 | C45: ['user_id', 'item_id', 'rating', 'timestamp', 'movie title'] | D45: [[196, 242, 3, 881250949, 'Kolya (1996)'], [63, 242, 3, 875747190, 'Kolya (1996)'], [226, 242, 5, 883888671, 'Kolya (1996)']] | E45: Use Join on source tables | F45: Source42_0 | G45: [[196, 242, 3, 881250949], [186, 302, 3, 891717742], [22, 377, 1, 878887116]] | H45: ['user_id', 'item_id', 'rating', 'timestamp'] | J45: The csv file had extra column with space that was making extra , and making extra column | K45: DROP TABLE IF EXISTS Source42_0; CREATE TABLE Source42_0 ( user_id INTEGER, item_id INTEGER, rating INTEGER, timestamp INTEGER ); -- Insert rows into Source42_0 INSERT INTO Source42_0 (user_id, item_id, rating, timestamp) VALUES (196, 242, 3, 881250949), (186, 302, 3, 891717742), (22, 377, 1, 878887116); -- Create the second source table Source42_1 DROP TABLE IF EXISTS Source42_1; CREATE TABLE Source42_1 ( item_id INTEGER, movie_title VARCHAR(255), release_date VARCHAR(20), video_release_date VARCHAR(20), imdb_url VARCHAR(255), unknown INTEGER, action INTEGER, adventure INTEGER, animation INTEGER, childrens INTEGER, comedy INTEGER, crime INTEGER, documentary INTEGER, drama INTEGER, fantasy INTEGER, film_noir INTEGER, horror INTEGER, musical INTEGER, mystery INTEGER, romance INTEGER, sci_fi INTEGER, thriller INTEGER, war INTEGER, western INTEGER ); -- Insert rows into Source42_1 INSERT INTO Source42_1 (item_id, movie_title, release_date, video_release_date, imdb_url, unknown, action, adventure, animation, childrens, comedy, crime, documentary, drama, fantasy, film_noir, horror, musical, mystery, romance, sci_fi, thriller, war, western) VALUES (1, 'Toy Story (1995)', '01-Jan-1995', NULL, 'http://us.imdb.com/M/title-exact?Toy%20Story%20(1995)', 0, 0, 0, 1, 1, 1, 0, 0, 0, 0, 0, 0, 0, 0, 0, 0, 0, 0), (2, 'GoldenEye (1995)', '01-Jan-1995', NULL, 'http://us.imdb.com/M/title-exact?GoldenEye%20(1995)', 0, 1, 1, 0, 0, 0, 0, 0, 0, 0, 0, 0, 0, 0, 0, 0, 1, 0, 0), (3, 'Four Rooms (1995)', '01-Jan-1995', NULL, 'http://us.imdb.com/M/title-exact?Four%20Rooms%20(1995)', 0, 0, 0, 0, 0, 0, 0, 0, 0, 0, 0, 0, 0, 0, 0, 0, 1, 0, 0); -- Create the target table Target1_42 DROP TABLE IF EXISTS Target1_42; CREATE TABLE Target1_42 ( user_id INTEGER, item_id INTEGER, rating INTEGER, timestamp INTEGER, movie_title VARCHAR(255) ); -- Insert rows into Target1_42 by joining Source42_0 and Source42_1 INSERT INTO Target1_42 (user_id, item_id, rating, timestamp, movie_title) SELECT s0.user_id, s0.item_id, s0.rating, s0.timestamp, s1.movie_title FROM Source42_0 s0 JOIN Source42_1 s1 ON s0.item_id = s1.item_id; -- Export the result to a CSV file COPY (SELECT * FROM Target1_42) TO 'D:\lab\ChatGPTwithSQLscript\github-pipelines\length1_42\Target1_42_result.csv' DELIMITER ',' CSV HEADER; | L45: 0 | M45: 0 | O45: Failed | Q45: ERROR: INSERT has more target columns than expressions LINE 45: ..., musical, mystery, romance, sci_fi, thriller, war, western) ^ SQL state: 42601 | R45: ERROR: extra data after last expected column CONTEXT: COPY source42_0, line 2: "0,196,242,3,881250949" SQL state: 22P04 | T45: 1
F46: Source42_1 | G46: [[1, 'Toy Story (1995)', '01-Jan-1995', nan, 'http://us.imdb.com/M/title-exact?Toy%20Story%20(1995)', 0, 0, 0, 1, 1, 1, 0, 0, 0, 0, 0, 0, 0, 0, 0, 0, 0, 0, 0], [2, 'GoldenEye (1995)', '01-Jan-1995', nan, 'http://us.imdb.com/M/title-exact?GoldenEye%20(1995)', 0, 1, 1, 0, 0, 0, 0, 0, 0, 0, 0, 0, 0, 0, 0, 0, 1, 0, 0], [3, 'Four Rooms (1995)', '01-Jan-1995', nan, 'http://us.imdb.com/M/title-exact?Four%20Rooms%20(1995)', 0, 0, 0, 0, 0, 0, 0, 0, 0, 0, 0, 0, 0, 0, 0, 0, 1, 0, 0]] | H46: ['item_id', 'movie title', 'release date', 'video release date', 'IMDb URL', 'unknown', 'Action', 'Adventure', 'Animation', 'Childrens', 'Comedy', 'Crime', 'Documentary', 'Drama', 'Fantasy', 'Film-Noir', 'Horror', 'Musical', 'Mystery', 'Romance', 'Sci-Fi', 'Thriller', 'War', 'Western']
A47: L1_43 | B47: Target1_43 | C47: ['fac_type', 'facid', 'capacity', 'fac_name', 'fac_address', 'city_state_zip', 'owner', 'operator'] | D47: [['NF', 137, 137, 137, 137, 137, 137, 137], ['RCF', 184, 183, 184, 184, 184, 184, 184]] | E47: In target table, for each fac_type, the rest attributes are count of the attribtues in source table. | F47: Source43_0 | G47: [[385008, 'NF', 96.0, 'Presbyterian Community Care Center', '1085 N Oregon St', 'Ontario, OR 97914', 'Presbyterian Nursing Home, Inc.', 'Presbyterian Nursing Home, Inc.'], [385010, 'NF', 159.0, 'Laurelhurst Village Rehabilitation Center', '3060 SE Stark St', 'Portland, OR 97214', 'Laurelhurst Operations, LLC', 'Laurelhurst Operations, LLC'], [385015, 'NF', 128.0, 'Regency Gresham Nursing & Rehabilitation Center', '5905 SE Powell Valley Rd', 'Gresham, OR 97080', 'Regency Gresham Nursing & Rehabilitation Center, LLC', 'Regency Pacific Management, LLC']] | H47: ['facid', 'fac_type', 'capacity', 'fac_name', 'fac_address', 'city_state_zip', 'owner', 'operator'] | K47: DROP TABLE IF EXISTS Source43_0; -- Create the source table CREATE TABLE Source43_0 ( facid INTEGER, fac_type VARCHAR(2), capacity NUMERIC(5,1), fac_name VARCHAR(100), fac_address VARCHAR(100), city_state_zip VARCHAR(100), owner VARCHAR(100), operator VARCHAR(100) ); -- Insert sample rows into the source table INSERT INTO Source43_0 (facid, fac_type, capacity, fac_name, fac_address, city_state_zip, owner, operator) VALUES (385008, 'NF', 96.0, 'Presbyterian Community Care Center', '1085 N Oregon St', 'Ontario, OR 97914', 'Presbyterian Nursing Home, Inc.', 'Presbyterian Nursing Home, Inc.'), (385010, 'NF', 159.0, 'Laurelhurst Village Rehabilitation Center', '3060 SE Stark St', 'Portland, OR 97214', 'Laurelhurst Operations, LLC', 'Laurelhurst Operations, LLC'), (385015, 'NF', 128.0, 'Regency Gresham Nursing & Rehabilitation Center', '5905 SE Powell Valley Rd', 'Gresham, OR 97080', 'Regency Gresham Nursing & Rehabilitation Center, LLC', 'Regency Pacific Management, LLC'); -- Drop the target table if it exists DROP TABLE IF EXISTS Target1_43; -- Create the target table CREATE TABLE Target1_43 ( fac_type VARCHAR(2), facid INTEGER, capacity_count INTEGER, fac_name_count INTEGER, fac_address_count INTEGER, city_state_zip_count INTEGER, owner_count INTEGER, operator_count INTEGER ); -- Insert rows from the source table into the target table INSERT INTO Target1_43 (fac_type, facid, capacity_count, fac_name_count, fac_address_count, city_state_zip_count, owner_count, operator_count) SELECT fac_type, facid, COUNT(capacity) AS capacity_count, COUNT(fac_name) AS fac_name_count, COUNT(fac_address) AS fac_address_count, COUNT(city_state_zip) AS city_state_zip_count, COUNT(owner) AS owner_count, COUNT(operator) AS operator_count FROM Source43_0 GROUP BY fac_type, facid; -- Export the result to a CSV file COPY (SELECT * FROM Target1_43) TO 'D:\lab\ChatGPTwithSQLscript\github-pipelines\length1_43\Target1_43_result.csv' DELIMITER ',' CSV HEADER; | L47: 0 | M47: 0 | Q47: It should be a count, can not be a sum | T47: Fail | V47: ERROR: Error: ERROR: invalid input syntax for type integer: "38A001" CONTEXT: COPY source43_0, line 120, column facid: "38A001" | AA47: data pre processing error
A48: L1_46 | B48: Target1_46 | C48: ['Date', 'Water Use', 'Power Use'] | D48: [['Apr_2006', 4351.0999999999985, 25274], ['Apr_2007', 6148.879999999999, 34389], ['Apr_2008', 4618.79, 31594]] | E48: In target, for each date the water use and power use is sum from source table. | F48: Source46_0 | G48: [['Mar_2008', 'Mar-08', '90230\n(33.99506171100046, -118.39500957899969)', 16.7, 396], ['Jul_2011', 'Jul-11', '90272\n(34.04886156900045, -118.53572692799969)', 35.73, 1013], ['Apr_2010', 'Apr-10', '90272\n(34.04886156900045, -118.53572692799969)', 23.53, 916]] | H48: ['Text Date', 'Value Date', 'Zip Code', 'Water Use', 'Power Use'] | K48: DROP TABLE IF EXISTS Source46_0; -- Create the source table CREATE TABLE Source46_0 ( "Text Date" VARCHAR, "Value Date" VARCHAR, "Zip Code" VARCHAR, "Water Use" NUMERIC, "Power Use" NUMERIC ); -- Insert sample rows into the source table INSERT INTO Source46_0 ("Text Date", "Value Date", "Zip Code", "Water Use", "Power Use") VALUES ('Mar_2008', 'Mar-08', '90230\n(33.99506171100046, -118.39500957899969)', 16.7, 396), ('Jul_2011', 'Jul-11', '90272\n(34.04886156900045, -118.53572692799969)', 35.73, 1013), ('Apr_2010', 'Apr-10', '90272\n(34.04886156900045, -118.53572692799969)', 23.53, 916); -- Drop the target table if it exists DROP TABLE IF EXISTS Target1_46; -- Create the target table CREATE TABLE Target1_46 ( "Date" VARCHAR, "Water Use" NUMERIC, "Power Use" NUMERIC ); -- Insert rows from the source table into the target table INSERT INTO Target1_46 ("Date", "Water Use", "Power Use") SELECT "Text Date", SUM("Water Use"), SUM("Power Use") FROM Source46_0 GROUP BY "Text Date"; -- Export the result to a CSV file COPY (SELECT * FROM Target1_46) TO 'D:\lab\ChatGPTwithSQLscript\github-pipelines\length1_46\Target1_46_result.csv' DELIMITER ',' CSV HEADER; | L48: 0 | M48: 0 | T48: 0 | X48: wrong sql generation, as description was not used
A49: L1_5 | B49: Target1_5 | C49: ['ProvinciaID', 'ProvinciaNombre', 'RegionID', 'ComunaID', 'ComunaNombre'] | D49: [[1, "'Arica'", 1, 1, "'Arica'"], [1, "'Arica'", 1, 2, "'Camarones'"], [2, "'Parinacota'", 1, 3, "'General Lagos'"]] | E49: Use Join on source tables | F49: Source5_0 | G49: [[1, "'Arica'", 1], [2, "'Camarones'", 1], [3, "'General Lagos'", 2]] | H49: ['ComunaID', 'ComunaNombre', 'ProvinciaID'] | L49: 0 | M49: 1 | N49: [1.0, 1.0, 1.0, 1.0, 1.0] | Q49: success | T49: 1
F50: Source5_1 | G50: [[1, "'Arica'", 1], [2, "'Parinacota'", 1], [3, "'Iquique'", 2]] | H50: ['ProvinciaID', 'ProvinciaNombre', 'RegionID']
A51: L1_52 | B51: Target1_52 | C51: ['condition', '0'] | D51: [[0, 253], [1, 246]] | E51: In target, '0' is total count of click from source table. | F51: Source52_0 | G51: [[1, 0], [0, 0], [0, 0]] | H51: ['condition', 'click'] | K51: DROP TABLE IF EXISTS Source52_0; CREATE TABLE Source52_0 ( condition INT, click INT ); -- Insert sample rows into source table INSERT INTO Source52_0 (condition, click) VALUES (1, 0), (0, 0), (0, 0); -- Create target table DROP TABLE IF EXISTS Target1_52; CREATE TABLE Target1_52 ( condition INT, "0" INT ); -- Insert rows from source table into target table INSERT INTO Target1_52 (condition, "0") SELECT condition, COUNT(click) AS "0" FROM Source52_0 GROUP BY condition; -- Export result to CSV file COPY (SELECT * FROM Target1_52) TO 'D:\lab\ChatGPTwithSQLscript\github-pipelines\length1_52\Target1_52_result.csv' DELIMITER ',' CSV HEADER; | L51: 0 | M51: 0.5 | N51: 1.0, 0.0 | Q51: correct sql generation but failing due to mismatch in number of rows to compare in target. | T51: 0 | Z51: failed | AA51: failed | AB51: need to check why these are failing and some are success
A52: L1_53 | B52: Target1_53 | C52: ['continent', 'beer_servings', 'spirit_servings', 'wine_servings', 'total_litres_of_pure_alcohol'] | D52: [['AF', 67.11538461538461, 15.576923076923075, 18.69230769230769, 2.7884615384615383], ['AS', 31.9, 56.5, 10.75, 2.0], ['EU', 195.70833333333331, 141.79166666666666, 145.95833333333334, 8.962500000000002]] | E52: In target, for each continent, the average is calculated from source attributes. | F52: Source53_0 | G52: [['Afghanistan', 0, 0, 0, 0.0, 'AS'], ['Albania', 89, 132, 54, 4.9, 'EU'], ['Algeria', 25, 0, 14, 0.7, 'AF']] | H52: ['country', 'beer_servings', 'spirit_servings', 'wine_servings', 'total_litres_of_pure_alcohol', 'continent'] | K52: DROP TABLE IF EXISTS Source53_0; -- Create the source table CREATE TABLE Source53_0 ( country VARCHAR, beer_servings INTEGER, spirit_servings INTEGER, wine_servings INTEGER, total_litres_of_pure_alcohol FLOAT, continent VARCHAR ); -- Insert data from the CSV file into the source table COPY Source53_0 FROM 'D:\lab\ChatGPTwithSQLscript\github-pipelines\length1_53\test_0.csv' WITH (FORMAT CSV, HEADER, NULL ''); -- Drop the target table if it exists DROP TABLE IF EXISTS Target1_53; -- Create the target table CREATE TABLE Target1_53 ( continent VARCHAR, beer_servings INTEGER, spirit_servings INTEGER, wine_servings INTEGER, total_litres_of_pure_alcohol FLOAT ); -- Insert data from the source table into the target table INSERT INTO Target1_53 (continent, beer_servings, spirit_servings, wine_servings, total_litres_of_pure_alcohol) SELECT continent, AVG(beer_servings), AVG(spirit_servings), AVG(wine_servings), AVG(total_litres_of_pure_alcohol) FROM Source53_0 GROUP BY continent; -- Copy the result of the SQL query into a CSV file COPY (SELECT * FROM Target1_53) TO 'D:\lab\ChatGPTwithSQLscript\github-pipelines\length1_53\Target1_53_result.csv' WITH (FORMAT CSV, HEADER); | M52: 0 | Q52: correct sql generation but failing due to mismatch in number of rows to compare in target. | R52: two rows are missing from sql results | T52: 0 | X52: wrong sql as no description | Z52: failed | AA52: failed | AB52: why in this case target samples did not help
A53: L1_57 | B53: Target1_57 | C53: ['movieId', 'rating'] | D53: [[1.0, 3.8192307692307694], [2.0, 3.411290322580645], [3.0, 3.4615384615384617]] | E53: In target, rating is average from source table for each movieid | F53: Source57_0 | G53: [[1.0, 31.0, 2.5, 1260759144.0], [1.0, 1029.0, 3.0, 1260759179.0], [1.0, 1061.0, 3.0, 1260759182.0]] | H53: ['userId', 'movieId', 'rating', 'timestamp'] | L53: 0 | Q53: correct sql generation but failing due to mismatch in number of rows to compare in target. | T53: 0
A54: L1_59 | B54: Target1_59 | C54: ['PRODUCTLINE', 'SALES'] | D54: [['Classic Cars', 1489382.800000001], ['Motorcycles', 364712.20000000007], ['Planes', 116886.11]] | E54: In target, the sales is sum of sales for each productline type from source table. | F54: Source59_0 | G54: [[10107, 30.0, 95.7, 2.0, 2871.0, '2/24/2003 0:00', 'Shipped', 1.0, 2.0, 2003.0, 'Motorcycles', 95.0, 'S10_1678', 'Land of Toys Inc.', '2125557818', '897 Long Airport Avenue', nan, 'NYC', 'NY', 10022, 'USA', nan, 'Yu', 'Kwai', 'Small'], [10121, 34.0, 81.35, 5.0, 2765.9, '5/7/2003 0:00', 'Shipped', 2.0, 5.0, 2003.0, 'Motorcycles', 95.0, 'S10_1678', 'Reims Collectables', '26.47.1555', "59 rue de l'Abbaye", nan, 'Reims', nan, 51100, 'France', 'EMEA', 'Henriot', 'Paul', 'Small'], [10134, 41.0, 94.74, 2.0, 3884.34, '7/1/2003 0:00', 'Shipped', 3.0, 7.0, 2003.0, 'Motorcycles', 95.0, 'S10_1678', 'Lyon Souveniers', '+33 1 46 62 7555', '27 rue du Colonel Pierre Avia', nan, 'Paris', nan, 75508, 'France', 'EMEA', 'Da Cunha', 'Daniel', 'Medium']] | H54: ['ORDERNUMBER', 'QUANTITYORDERED', 'PRICEEACH', 'ORDERLINENUMBER', 'SALES', 'ORDERDATE', 'STATUS', 'QTR_ID', 'MONTH_ID', 'YEAR_ID', 'PRODUCTLINE', 'MSRP', 'PRODUCTCODE', 'CUSTOMERNAME', 'PHONE', 'ADDRESSLINE1', 'ADDRESSLINE2', 'CITY', 'STATE', 'POSTALCODE', 'COUNTRY', 'TERRITORY', 'CONTACTLASTNAME', 'CONTACTFIRSTNAME', 'DEALSIZE'] | I54: DROP TABLE IF EXISTS Source59_0; -- Create the source table CREATE TABLE Source59_0 ( ORDERNUMBER INTEGER, QUANTITYORDERED FLOAT, PRICEEACH FLOAT, ORDERLINENUMBER FLOAT, SALES FLOAT, ORDERDATE TIMESTAMP, STATUS VARCHAR(255), QTR_ID FLOAT, MONTH_ID FLOAT, YEAR_ID FLOAT, PRODUCTLINE VARCHAR(255), MSRP FLOAT, PRODUCTCODE VARCHAR(255), CUSTOMERNAME VARCHAR(255), PHONE VARCHAR(255), ADDRESSLINE1 VARCHAR(255), ADDRESSLINE2 VARCHAR(255), CITY VARCHAR(255), STATE VARCHAR(255), POSTALCODE INTEGER, COUNTRY VARCHAR(255), TERRITORY VARCHAR(255), CONTACTLASTNAME VARCHAR(255), CONTACTFIRSTNAME VARCHAR(255), DEALSIZE VARCHAR(255) ); -- Insert data from CSV into the source table COPY Source59_0 FROM 'D:\lab\ChatGPTwithSQLscript\github-pipelines\length1_59\test_0.csv' DELIMITER ',' CSV HEADER NULL ''; -- Drop the target table if it exists DROP TABLE IF EXISTS Target1_59; -- Create the target table CREATE TABLE Target1_59 ( PRODUCTLINE VARCHAR(255), SALES FLOAT ); -- Insert data into the target table INSERT INTO Target1_59 (PRODUCTLINE, SALES) SELECT PRODUCTLINE, SUM(SALES) FROM Source59_0 GROUP BY PRODUCTLINE; -- Copy the result into a CSV file COPY (SELECT * FROM Target1_59) TO 'D:\lab\ChatGPTwithSQLscript\github-pipelines\length1_59\Target1_59_result.csv' DELIMITER ',' CSV HEADER; | J54: SQL Result: Error: ERROR: invalid input syntax for type integer: "10180,29,86.13,9,2497.77,11/11/2003 0:00,Shipped,4,11,2003,Motorcycles,95,S10_1678,Daedalus Designs Imports,20.16.1555,"184, chausse de Tournai",,Lille,,59000,France,EMEA,Rance,Martine,Small" CONTEXT: COPY source59_0, line 8, column ordernumber: "10180,29,86.13,9,2497.77,11/11/2003 0:00,Shipped,4,11,2003,Motorcycles,95,S10_1678,Daedalus Designs ..." | K54: DROP TABLE IF EXISTS Source59_0; CREATE TABLE Source59_0 ( ORDERNUMBER INT, QUANTITYORDERED FLOAT, PRICEEACH FLOAT, ORDERLINENUMBER FLOAT, SALES FLOAT, ORDERDATE TIMESTAMP, STATUS VARCHAR(255), QTR_ID FLOAT, MONTH_ID FLOAT, YEAR_ID FLOAT, PRODUCTLINE VARCHAR(255), MSRP FLOAT, PRODUCTCODE VARCHAR(255), CUSTOMERNAME VARCHAR(255), PHONE VARCHAR(255), ADDRESSLINE1 VARCHAR(255), ADDRESSLINE2 VARCHAR(255), CITY VARCHAR(255), STATE VARCHAR(255), POSTALCODE INT, COUNTRY VARCHAR(255), TERRITORY VARCHAR(255), CONTACTLASTNAME VARCHAR(255), CONTACTFIRSTNAME VARCHAR(255), DEALSIZE VARCHAR(255) ); -- Create the second source table Source_0 DROP TABLE IF EXISTS Source_0; CREATE TABLE Source_0 ( ORDERNUMBER INT, QUANTITYORDERED FLOAT, PRICEEACH FLOAT, ORDERLINENUMBER FLOAT, SALES FLOAT, ORDERDATE TIMESTAMP, STATUS VARCHAR(255), QTR_ID FLOAT, MONTH_ID FLOAT, YEAR_ID FLOAT, PRODUCTLINE VARCHAR(255), MSRP FLOAT, PRODUCTCODE VARCHAR(255), CUSTOMERNAME VARCHAR(255), PHONE VARCHAR(255), ADDRESSLINE1 VARCHAR(255), ADDRESSLINE2 VARCHAR(255), CITY VARCHAR(255), STATE VARCHAR(255), POSTALCODE INT, COUNTRY VARCHAR(255), TERRITORY VARCHAR(255), CONTACTLASTNAME VARCHAR(255), CONTACTFIRSTNAME VARCHAR(255), DEALSIZE VARCHAR(255) ); -- Insert rows into the first source table Source59_0 INSERT INTO Source59_0 (ORDERNUMBER, QUANTITYORDERED, PRICEEACH, ORDERLINENUMBER, SALES, ORDERDATE, STATUS, QTR_ID, MONTH_ID, YEAR_ID, PRODUCTLINE, MSRP, PRODUCTCODE, CUSTOMERNAME, PHONE, ADDRESSLINE1, ADDRESSLINE2, CITY, STATE, POSTALCODE, COUNTRY, TERRITORY, CONTACTLASTNAME, CONTACTFIRSTNAME, DEALSIZE) VALUES (10107, 30.0, 95.7, 2.0, 2871.0, '2003-02-24 00:00:00', 'Shipped', 1.0, 2.0, 2003.0, 'Motorcycles', 95.0, 'S10_1678', 'Land of Toys Inc.', '2125557818', '897 Long Airport Avenue', NULL, 'NYC', 'NY', 10022, 'USA', NULL, 'Yu', 'Kwai', 'Small'), (10121, 34.0, 81.35, 5.0, 2765.9, '2003-05-07 00:00:00', 'Shipped', 2.0, 5.0, 2003.0, 'Motorcycles', 95.0, 'S10_1678', 'Reims Collectables', '26.47.1555', '59 rue de l''Abbaye', NULL, 'Reims', NULL, 51100, 'France', 'EMEA', 'Henriot', 'Paul', 'Small'), (10134, 41.0, 94.74, 2.0, 3884.34, '2003-07-01 00:00:00', 'Shipped', 3.0, 7.0, 2003.0, 'Motorcycles', 95.0, 'S10_1678', 'Lyon Souveniers', '+33 1 46 62 7555', '27 rue du Colonel Pierre Avia', NULL, 'Paris', NULL, 75508, 'France', 'EMEA', 'Da Cunha', 'Daniel', 'Medium'); -- Insert rows into the second source table Source_0 INSERT INTO Source_0 (ORDERNUMBER, QUANTITYORDERED, PRICEEACH, ORDERLINENUMBER, SALES, ORDERDATE, STATUS, QTR_ID, MONTH_ID, YEAR_ID, PRODUCTLINE, MSRP, PRODUCTCODE, CUSTOMERNAME, PHONE, ADDRESSLINE1, ADDRESSLINE2, CITY, STATE, POSTALCODE, COUNTRY, TERRITORY, CONTACTLASTNAME, CONTACTFIRSTNAME, DEALSIZE) VALUES (10107, 30.0, 95.7, 2.0, 2871.0, '2003-02-24 00:00:00', 'Shipped', 1.0, 2.0, 2003.0, 'Motorcycles', 95.0, 'S10_1678', 'Land of Toys Inc.', '2125557818', '897 Long Airport Avenue', NULL, 'NYC', 'NY', 10022, 'USA', NULL, 'Yu', 'Kwai', 'Small'), (10121, 34.0, 81.35, 5.0, 2765.9, '2003-05-07 00:00:00', 'Shipped', 2.0, 5.0, 2003.0, 'Motorcycles', 95.0, 'S10_1678', 'Reims Collectables', '26.47.1555', '59 rue de l''Abbaye', NULL, 'Reims', NULL, 51100, 'France', 'EMEA', 'Henriot', 'Paul', 'Small'), (10134, 41.0, 94.74, 2.0, 3884.34, '2003-07-01 00:00:00', 'Shipped', 3.0, 7.0, 2003.0, 'Motorcycles', 95.0, 'S10_1678', 'Lyon Souveniers', '+33 1 46 62 7555', '27 rue du Colonel Pierre Avia', NULL, 'Paris', NULL, 75508, 'France', 'EMEA', 'Da Cunha', 'Daniel', 'Medium'); -- Create the target table Target1_59 DROP TABLE IF EXISTS Target1_59; CREATE TABLE Target1_59 ( PRODUCTLINE VARCHAR(255), SALES FLOAT ); -- Insert rows into the target table Target1_59 by joining the source tables INSERT INTO Target1_59 (PRODUCTLINE, SALES) SELECT s.PRODUCTLINE, s.SALES FROM Source59_0 s JOIN Source_0 s0 ON s.ORDERNUMBER = s0.ORDERNUMBER; -- Export the result to a CSV file COPY (SELECT * FROM Target1_59) TO 'D:\lab\ChatGPTwithSQLscript\github-pipelines\length1_59\Target1_59_result.csv' DELIMITER ',' CSV HEADER; | Q54: correct sql generation but failing due to mismatch in number of rows to compare in target. | T54: Fail | V54: ERROR: Error: ERROR: invalid input syntax for type integer: "" CONTEXT: COPY source59_0, line 6, column postalcode: "" | Z54: 0.5 success [1,0.7] score. | AA54: ERROR: Error: ERROR: invalid input syntax for type integer: "2003.0" CONTEXT: COPY source59_0, line 2, column year_id: "2003.0"
A55: L1_6 | B55: Target1_6 | C55: ['provider_id', 'provider_name', 'provider_zip_code', 'average_covered_charges', 'average_total_payments', 'average_medicare_payments'] | D55: [[10001, 'SOUTHEAST ALABAMA MEDICAL CENTER', 36301, 45757.55797619046, 10177.445952380953, 8907.124523809522], [10005, 'MARSHALL MEDICAL CENTER SOUTH', 35957, 17601.732068965513, 7403.27448275862, 5947.807586206897], [10006, 'ELIZA COFFEE MEMORIAL HOSPITAL', 35631, 56096.88644067797, 11159.26627118644, 9789.64288135593]] | F55: Source6_0 | G55: [[17734.69, 3154.38, 4303.92, '195 - SIMPLE PNEUMONIA & PLEURISY W/O CC/MCC', 'TN - Johnson City', 'JOHNSON CITY', 440184, 'FRANKLIN WOODS COMMUNITY HOSPITAL', 'TN', '300 MED TECH PARKWAY', 37604, 13], [28375.14, 8231.48, 9003.1, '180 - RESPIRATORY NEOPLASMS W MCC', 'FL - Orlando', 'THE VILLAGES', 100290, 'VILLAGES REGIONAL HOSPITAL, THE', 'FL', '1451 EL CAMINO REAL', 32159, 21], [68931.09, 9809.0, 13479.96, '707 - MAJOR MALE PELVIC PROCEDURES W CC/MCC', 'TX - Houston', 'HOUSTON', 450358, 'METHODIST HOSPITAL,THE', 'TX', '6565 FANNIN', 77030, 23]] | H55: ['average_covered_charges', 'average_medicare_payments', 'average_total_payments', 'drg_definition', 'hospital_referral_region_hrr_description', 'provider_city', 'provider_id', 'provider_name', 'provider_state', 'provider_street_address', 'provider_zip_code', 'total_discharges'] | I55: CREATE TABLE Source6_0 ( average_covered_charges NUMERIC, average_medicare_payments NUMERIC, average_total_payments NUMERIC, drg_definition VARCHAR(100), hospital_referral_region_hrr_description VARCHAR(100), provider_city VARCHAR(100), provider_id INTEGER, provider_name VARCHAR(100), provider_state VARCHAR(2), provider_street_address VARCHAR(100), provider_zip_code INTEGER, total_discharges INTEGER ); -- Insert sample rows into the source table INSERT INTO Source6_0 (average_covered_charges, average_medicare_payments, average_total_payments, drg_definition, hospital_referral_region_hrr_description, provider_city, provider_id, provider_name, provider_state, provider_street_address, provider_zip_code, total_discharges) VALUES (17734.69, 3154.38, 4303.92, '195 - SIMPLE PNEUMONIA & PLEURISY W/O CC/MCC', 'TN - Johnson City', 'JOHNSON CITY', 440184, 'FRANKLIN WOODS COMMUNITY HOSPITAL', 'TN', '300 MED TECH PARKWAY', 37604, 13), (28375.14, 8231.48, 9003.1, '180 - RESPIRATORY NEOPLASMS W MCC', 'FL - Orlando', 'THE VILLAGES', 100290, 'VILLAGES REGIONAL HOSPITAL, THE', 'FL', '1451 EL CAMINO REAL', 32159, 21), (68931.09, 9809.0, 13479.96, '707 - MAJOR MALE PELVIC PROCEDURES W CC/MCC', 'TX - Houston', 'HOUSTON', 450358, 'METHODIST HOSPITAL,THE', 'TX', '6565 FANNIN', 77030, 23); -- Drop the target table if it exists DROP TABLE IF EXISTS Target1_6; -- Create the target table CREATE TABLE Target1_6 ( provider_id INTEGER, provider_name VARCHAR(100), provider_zip_code INTEGER, average_covered_charges NUMERIC, average_total_payments NUMERIC, average_medicare_payments NUMERIC ); -- Insert rows from the source table into the target table INSERT INTO Target1_6 (provider_id, provider_name, provider_zip_code, average_covered_charges, average_total_payments, average_medicare_payments) SELECT provider_id, provider_name, provider_zip_code, AVG(average_covered_charges), AVG(average_total_payments), AVG(average_medicare_payments) FROM Source6_0 GROUP BY provider_id, provider_name, provider_zip_code; -- Export the result to a CSV file COPY (SELECT * FROM Target1_6) TO 'D:\lab\ChatGPTwithSQLscript\github-pipelines\length1_6\Target1_6_result.csv' DELIMITER ',' CSV HEADER; | J55: Generated SQL result does not match at all, num of rows are different. | Q55: Its challenging to figure out mapping from source to target values. | T55: 0 | Y55: 1 | Z55: failed | AA55: failed
A56: L1_60 | B56: Target1_60 | C56: ['type', 'driver_count'] | D56: [['Urban', 2149]] | E56: In target table, the driver_count is total count of driver from source table for each type. | F56: Source60_0 | G56: [['Richardfort', 38, 'Urban'], ['Williamsstad', 59, 'Urban'], ['Port Angela', 67, 'Urban']] | H56: ['city', 'driver_count', 'type'] | K56: DROP TABLE IF EXISTS Source60_0; -- Create the source table CREATE TABLE Source60_0 ( city VARCHAR, driver_count INTEGER, type VARCHAR ); -- Insert sample rows into the source table INSERT INTO Source60_0 (city, driver_count, type) VALUES ('Richardfort', 38, 'Urban'), ('Williamsstad', 59, 'Urban'), ('Port Angela', 67, 'Urban'); -- Drop the target table if it exists DROP TABLE IF EXISTS Target1_60; -- Create the target table CREATE TABLE Target1_60 ( type VARCHAR, driver_count INTEGER ); -- Insert rows from the source table into the target table INSERT INTO Target1_60 (type, driver_count) SELECT type, SUM(driver_count) FROM Source60_0 GROUP BY type; -- Export the result to a CSV file COPY (SELECT * FROM Target1_60) TO 'D:\lab\ChatGPTwithSQLscript\github-pipelines\length1_60\Target1_60_result.csv' DELIMITER ',' CSV HEADER; | M56: 0.5 | N56: [1.0, 0.0] | Q56: The result is not a exact match, may be because only using test file not training. | Z56: success | AA56: failed
A57: L1_64 | B57: Target1_64 | C57: ['name', 'Gender', 'Eye color', 'Race', 'Hair color', 'Height', 'Publisher', 'Skin color', 'Alignment', 'Weight', 'hero_names', 'Agility', 'Accelerated Healing', 'Lantern Power Ring', 'Dimensional Awareness', 'Cold Resistance', 'Durability', 'Stealth', 'Energy Absorption', 'Flight', 'Danger Sense', 'Underwater breathing', 'Marksmanship', 'Weapons Master', 'Power Augmentation', 'Animal Attributes', 'Longevity', 'Intelligence', 'Super Strength', 'Cryokinesis', 'Telepathy', 'Energy Armor', 'Energy Blasts', 'Duplication', 'Size Changing', 'Density Control', 'Stamina', 'Astral Travel', 'Audio Control', 'Dexterity', 'Omnitrix', 'Super Speed', 'Possession', 'Animal Oriented Powers', 'Weapon-based Powers', 'Electrokinesis', 'Darkforce Manipulation', 'Death Touch', 'Teleportation', 'Enhanced Senses', 'Telekinesis', 'Energy Beams', 'Magic', 'Hyperkinesis', 'Jump', 'Clairvoyance', 'Dimensional Travel', 'Power Sense', 'Shapeshifting', 'Peak Human Condition', 'Immortality', 'Camouflage', 'Element Control', 'Phasing', 'Astral Projection', 'Electrical Transport', 'Fire Control', 'Projection', 'Summoning', 'Enhanced Memory', 'Reflexes', 'Invulnerability', 'Energy Constructs', 'Force Fields', 'Self-Sustenance', 'Anti-Gravity', 'Empathy', 'Power Nullifier', 'Radiation Control', 'Psionic Powers', 'Elasticity', 'Substance Secretion', 'Elemental Transmogrification', 'Technopath/Cyberpath', 'Photographic Reflexes', 'Seismic Power', 'Animation', 'Precognition', 'Mind Control', 'Fire Resistance', 'Power Absorption', 'Enhanced Hearing', 'Nova Force', 'Insanity', 'Hypnokinesis', 'Animal Control', 'Natural Armor', 'Intangibility', 'Enhanced Sight', 'Molecular Manipulation', 'Heat Generation', 'Adaptation', 'Gliding', 'Power Suit', 'Mind Blast', 'Probability Manipulation', 'Gravity Control', 'Regeneration', 'Light Control', 'Echolocation', 'Levitation', 'Toxin and Disease Control', 'Banish', 'Energy Manipulation', 'Heat Resistance', 'Natural Weapons', 'Time Travel', 'Enhanced Smell', 'Illusions', 'Thirstokinesis', 'Hair Manipulation', 'Illumination', 'Omnipotent', 'Cloaking', 'Changing Armor', 'Power Cosmic', 'Biokinesis', 'Water Control', 'Radiation Immunity', 'Vision - Telescopic', 'Toxin and Disease Resistance', 'Spatial Awareness', 'Energy Resistance', 'Telepathy Resistance', 'Molecular Combustion', 'Omnilingualism', 'Portal Creation', 'Magnetism', 'Mind Control Resistance', 'Plant Control', 'Sonar', 'Sonic Scream', 'Time Manipulation', 'Enhanced Touch', 'Magic Resistance', 'Invisibility', 'Sub-Mariner', 'Radiation Absorption', 'Intuitive aptitude', 'Vision - Microscopic', 'Melting', 'Wind Control', 'Super Breath', 'Wallcrawling', 'Vision - Night', 'Vision - Infrared', 'Grim Reaping', 'Matter Absorption', 'The Force', 'Resurrection', 'Terrakinesis', 'Vision - Heat', 'Vitakinesis', 'Radar Sense', 'Qwardian Power Ring', 'Weather Control', 'Vision - X-Ray', 'Vision - Thermal', 'Web Creation', 'Reality Warping', 'Odin Force', 'Symbiote Costume', 'Speed Force', 'Phoenix Force', 'Molecular Dissipation', 'Vision - Cryo', 'Omnipresent', 'Omniscient'] | D57: [['A-Bomb', 'Male', 'yellow', 'Human', 'No Hair', 203, 'Marvel Comics', '-', 'good', 441.0, 'A-Bomb', False, True, False, False, False, True, False, False, False, False, False, False, False, False, False, True, False, True, False, False, False, False, False, False, False, True, False, False, False, False, False, False, False, False, False, False, False, False, False, False, False, False, False, False, False, False, False, False, False, False, True, False, False, False, False, False, False, False, False, False, False, False, False, True, False, False, False, False, False, False, False, False, False, False, False, False, False, False, False, False, False, False, False, False, False, False, False, False, False, False, False, False, False, False, False, False, False, False, False, False, False, False, False, False, False, False, False, False, False, False, False, False, False, False, False, False, False, False, False, False, False, False, False, False, False, False, False, False, False, False, False, False, False, False, False, False, False, False, False, False, False, False, False, False, False, False, False, False, False, False, False, False, False, False, False, False, False, False, False, False, False, False, False, False, False, False, False], ['Abe Sapien', 'Male', 'blue', 'Icthyo Sapien', 'No Hair', 191, 'Dark Horse Comics', 'blue', 'good', 65.0, 'Abe Sapien', True, True, False, False, True, True, False, False, False, False, True, True, True, False, False, True, True, True, False, True, False, False, False, False, False, True, False, False, False, False, False, False, False, False, False, False, False, False, False, False, False, False, False, False, False, False, False, False, False, True, False, False, False, False, False, False, False, False, False, True, False, False, False, False, False, False, False, False, False, False, False, False, False, False, False, False, False, False, False, False, False, False, False, False, False, False, False, True, False, False, False, False, False, False, False, False, False, False, False, False, False, False, False, False, False, False, False, False, False, False, False, False, False, False, False, False, False, False, False, False, False, False, False, False, False, False, False, False, False, False, False, False, False, False, False, True, False, False, False, False, False, False, False, False, False, False, False, False, False, False, False, False, False, False, False, False, False, False, False, False, False, False, False, False, False, False, False], ['Abin Sur', 'Male', 'blue', 'Ungaran', 'No Hair', 185, 'DC Comics', 'red', 'good', 90.0, 'Abin Sur', False, False, True, False, False, False, False, False, False, False, False, False, False, False, False, False, False, False, False, False, False, False, False, False, False, False, False, False, False, False, False, False, False, False, False, False, False, False, False, False, False, False, False, False, False, False, False, False, False, False, False, False, False, False, False, False, False, False, False, False, False, False, False, False, False, False, False, False, False, False, False, False, False, False, False, False, False, False, False, False, False, False, False, False, False, False, False, False, False, False, False, False, False, False, False, False, False, False, False, False, False, False, False, False, False, False, False, False, False, False, False, False, False, False, False, False, False, False, False, False, False, False, False, False, False, False, False, False, False, False, False, False, False, False, False, False, False, False, False, False, False, False, False, False, False, False, False, False, False, False, False, False, False, False, False, False, False, False, False, False, False, False, False, False, False, False, False]] | E57: Use Join on source tables | F57: Source64_0 | G57: [['A-Bomb', 'Male', 'yellow', 'Human', 'No Hair', 203, 'Marvel Comics', '-', 'good', 441.0], ['Abe Sapien', 'Male', 'blue', 'Icthyo Sapien', 'No Hair', 191, 'Dark Horse Comics', 'blue', 'good', 65.0], ['Abin Sur', 'Male', 'blue', 'Ungaran', 'No Hair', 185, 'DC Comics', 'red', 'good', 90.0]] | H57: ['name', 'Gender', 'Eye color', 'Race', 'Hair color', 'Height', 'Publisher', 'Skin color', 'Alignment', 'Weight'] | I57: DROP TABLE IF EXISTS Source64_0; CREATE TABLE Source64_0 ( name VARCHAR(255), Gender VARCHAR(255), "Eye color" VARCHAR(255), Race VARCHAR(255), "Hair color" VARCHAR(255), Height INTEGER, Publisher VARCHAR(255), "Skin color" VARCHAR(255), Alignment VARCHAR(255), Weight FLOAT ); DROP TABLE IF EXISTS Source64_1; CREATE TABLE Source64_1 ( hero_names VARCHAR(255), Agility BOOLEAN, "Accelerated Healing" BOOLEAN, "Lantern Power Ring" BOOLEAN, "Dimensional Awareness" BOOLEAN, "Cold Resistance" BOOLEAN, Durability BOOLEAN, Stealth BOOLEAN, "Energy Absorption" BOOLEAN, Flight BOOLEAN, "Danger Sense" BOOLEAN, "Underwater breathing" BOOLEAN, Marksmanship BOOLEAN, "Weapons Master" BOOLEAN, "Power Augmentation" BOOLEAN, "Animal Attributes" BOOLEAN, Longevity BOOLEAN, Intelligence BOOLEAN, "Super Strength" BOOLEAN, Cryokinesis BOOLEAN, Telepathy BOOLEAN, "Energy Armor" BOOLEAN, "Energy Blasts" BOOLEAN, Duplication BOOLEAN, "Size Changing" BOOLEAN, "Density Control" BOOLEAN, Stamina BOOLEAN, "Astral Travel" BOOLEAN, "Audio Control" BOOLEAN, Dexterity BOOLEAN, Omnitrix BOOLEAN, "Super Speed" BOOLEAN, Possession BOOLEAN, "Animal Oriented Powers" BOOLEAN, "Weapon-based Powers" BOOLEAN, Electrokinesis BOOLEAN, "Darkforce Manipulation" BOOLEAN, "Death Touch" BOOLEAN, Teleportation BOOLEAN, "Enhanced Senses" BOOLEAN, Telekinesis BOOLEAN, "Energy Beams" BOOLEAN, Magic BOOLEAN, Hyperkinesis BOOLEAN, Jump BOOLEAN, Clairvoyance BOOLEAN, "Dimensional Travel" BOOLEAN, "Power Sense" BOOLEAN, Shapeshifting BOOLEAN, "Peak Human Condition" BOOLEAN, Immortality BOOLEAN, Camouflage BOOLEAN, "Element Control" BOOLEAN, Phasing BOOLEAN, "Astral Projection" BOOLEAN, "Electrical Transport" BOOLEAN, "Fire Control" BOOLEAN, Projection BOOLEAN, Summoning BOOLEAN, "Enhanced Memory" BOOLEAN, Reflexes BOOLEAN, Invulnerability BOOLEAN, "Energy Constructs" BOOLEAN, "Force Fields" BOOLEAN, "Self-Sustenance" BOOLEAN, "Anti-Gravity" BOOLEAN, Empathy BOOLEAN, "Power Nullifier" BOOLEAN, "Radiation Control" BOOLEAN, "Psionic Powers" BOOLEAN, Elasticity BOOLEAN, "Substance Secretion" BOOLEAN, "Elemental Transmogrification" BOOLEAN, "Technopath/Cyberpath" BOOLEAN, "Photographic Reflexes" BOOLEAN, "Seismic Power" BOOLEAN, Animation BOOLEAN, Precognition BOOLEAN, "Mind Control" BOOLEAN, "Fire Resistance" BOOLEAN, "Power Absorption" BOOLEAN, "Enhanced Hearing" BOOLEAN, "Nova Force" BOOLEAN, Insanity BOOLEAN, Hypnokinesis BOOLEAN, "Animal Control" BOOLEAN, "Natural Armor" BOOLEAN, Intangibility BOOLEAN, "Enhanced Sight" BOOLEAN, "Molecular Manipulation" BOOLEAN, "Heat Generation" BOOLEAN, Adaptation BOOLEAN, Gliding BOOLEAN, "Power Suit" BOOLEAN, "Mind Blast" BOOLEAN, "Probability Manipulation" BOOLEAN, "Gravity Control" BOOLEAN, Regeneration BOOLEAN, "Light Control" BOOLEAN, Echolocation BOOLEAN, Levitation BOOLEAN, "Toxin and Disease Control" BOOLEAN, Banish BOOLEAN, "Energy Manipulation" BOOLEAN, "Heat Resistance" BOOLEAN, "Natural Weapons" BOOLEAN, "Time Travel" BOOLEAN, "Enhanced Smell" BOOLEAN, Illusions BOOLEAN, Thirstokinesis BOOLEAN, "Hair Manipulation" BOOLEAN, Illumination BOOLEAN, Omnipotent BOOLEAN, Cloaking BOOLEAN, "Changing Armor" BOOLEAN, "Power Cosmic" BOOLEAN, Biokinesis BOOLEAN, "Water Control" BOOLEAN, "Radiation Immunity" BOOLEAN, "Vision - Telescopic" BOOLEAN, "Toxin and Disease Resistance" BOOLEAN, "Spatial Awareness" BOOLEAN, "Energy Resistance" BOOLEAN, "Telepathy Resistance" BOOLEAN, "Molecular Combustion" BOOLEAN, Omnilingualism BOOLEAN, "Portal Creation" BOOLEAN, Magnetism BOOLEAN, "Mind Control Resistance" BOOLEAN, "Plant Control" BOOLEAN, Sonar BOOLEAN, "Sonic Scream" BOOLEAN, "Time Manipulation" BOOLEAN, "Enhanced Touch" BOOLEAN, "Magic Resistance" BOOLEAN, Invisibility BOOLEAN, "Sub-Mariner" BOOLEAN, "Radiation Absorption" BOOLEAN, "Intuitive aptitude" BOOLEAN, "Vision - Microscopic" BOOLEAN, Melting BOOLEAN, "Wind Control" BOOLEAN, "Super Breath" BOOLEAN, Wallcrawling BOOLEAN, "Vision - Night" BOOLEAN, "Vision - Infrared" BOOLEAN, "Grim Reaping" BOOLEAN, "Matter Absorption" BOOLEAN, "The Force" BOOLEAN, Resurrection BOOLEAN, Terrakinesis BOOLEAN, "Vision - Heat" BOOLEAN, Vitakinesis BOOLEAN, "Radar Sense" BOOLEAN, "Qwardian Power Ring" BOOLEAN, "Weather Control" BOOLEAN, "Vision - X-Ray" BOOLEAN, "Vision - Thermal" BOOLEAN, "Web Creation" BOOLEAN, "Reality Warping" BOOLEAN, "Odin Force" BOOLEAN, "Symbiote Costume" BOOLEAN, "Speed Force" BOOLEAN, "Phoenix Force" BOOLEAN, "Molecular Dissipation" BOOLEAN, "Vision - Cryo" BOOLEAN, Omnipresent BOOLEAN, Omniscient BOOLEAN ); -- Step 2: Insert data into the source tables COPY Source64_0 FROM 'D:\lab\ChatGPTwithSQLscript\github-pipelines\length1_64\test_0.csv' DELIMITER ',' CSV HEADER NULL ''; COPY Source64_1 FROM 'D:\lab\ChatGPTwithSQLscript\github-pipelines\length1_64\test_1.csv' DELIMITER ',' CSV HEADER NULL ''; -- Step 3: Create the target table DROP TABLE IF EXISTS Target1_64; CREATE TABLE Target1_64 AS SELECT s0.name, s0.Gender, s0."Eye color", s0.Race, s0."Hair color", s0.Height, s0.Publisher, s0."Skin color", s0.Alignment, s0.Weight, s1.hero_names, s1.Agility, s1."Accelerated Healing", s1."Lantern Power Ring", s1."Dimensional Awareness", s1."Cold Resistance", s1.Durability, s1.Stealth, s1."Energy Absorption", s1.Flight, s1."Danger Sense", s1."Underwater breathing", s1.Marksmanship, s1."Weapons Master", s1."Power Augmentation", s1."Animal Attributes", s1.Longevity, s1.Intelligence, s1."Super Strength", s1.Cryokinesis, s1.Telepathy, s1."Energy Armor", s1."Energy Blasts", s1.Duplication, s1."Size Changing", s1."Density Control", s1.Stamina, s1."Astral Travel", s1."Audio Control", s1.Dexterity, s1.Omnitrix, s1."Super Speed", s1.Possession, s1."Animal Oriented Powers", s1."Weapon-based Powers", s1.Electrokinesis, s1."Darkforce Manipulation", s1."Death Touch", s1.Teleportation, s1."Enhanced Senses", s1.Telekinesis, s1."Energy Beams", s1.Magic, s1.Hyperkinesis, s1.Jump, s1.Clairvoyance, s1."Dimensional Travel", s1."Power Sense", s1.Shapeshifting, s1."Peak Human Condition", s1.Immortality, s1.Camouflage, s1."Element Control", s1.Phasing, s1."Astral Projection", s1."Electrical Transport", s1."Fire Control", s1.Projection, s1.Summoning, s1."Enhanced Memory", s1.Reflexes, s1.Invulnerability, s1."Energy Constructs", s1."Force Fields", s1."Self-Sustenance", s1."Anti-Gravity", s1.Empathy, s1."Power Nullifier", s1."Radiation Control", s1."Psionic Powers", s1.Elasticity, s1."Substance Secretion", s1."Elemental Transmogrification", s1."Technopath/Cyberpath", s1."Photographic Reflexes", s1."Seismic Power", s1.Animation, s1.Precognition, s1."Mind Control", s1."Fire Resistance", s1."Power Absorption", s1."Enhanced Hearing", s1."Nova Force", s1.Insanity, s1.Hypnokinesis, s1."Animal Control", s1."Natural Armor", s1.Intangibility, s1."Enhanced Sight", s1."Molecular Manipulation", s1."Heat Generation", s1.Adaptation, s1.Gliding, s1."Power Suit", s1."Mind Blast", s1."Probability Manipulation", s1."Gravity Control", s1.Regeneration, s1."Light Control", s1.Echolocation, s1.Levitation, s1."Toxin and Disease Control", s1.Banish, s1."Energy Manipulation", s1."Heat Resistance", s1."Natural Weapons", s1."Time Travel", s1."Enhanced Smell", s1.Illusions, s1.Thirstokinesis, s1."Hair Manipulation", s1.Illumination, s1.Omnipotent, s1.Cloaking, s1."Changing Armor", s1."Power Cosmic", s1.Biokinesis, s1."Water Control", s1."Radiation Immunity", s1."Vision - Telescopic", s1."Toxin and Disease Resistance", s1."Spatial Awareness", s1."Energy Resistance", s1."Telepathy Resistance", s1."Molecular Combustion", s1.Omnilingualism, s1."Portal Creation", s1.Magnetism, s1."Mind Control Resistance", s1."Plant Control", s1.Sonar, s1."Sonic Scream", s1."Time Manipulation", s1."Enhanced Touch", s1."Magic Resistance", s1.Invisibility, s1."Sub-Mariner", s1."Radiation Absorption", s1."Intuitive aptitude", s1."Vision - Microscopic", s1.Melting, s1."Wind Control", s1."Super Breath", s1.Wallcrawling, s1."Vision - Night", s1."Vision - Infrared", s1."Grim Reaping", s1."Matter Absorption", s1."The Force", s1.Resurrection, s1.Terrakinesis, s1."Vision - Heat", s1.Vitakinesis, s1."Radar Sense", s1."Qwardian Power Ring", s1."Weather Control", s1."Vision - X-Ray", s1."Vision - Thermal", s1."Web Creation", s1."Reality Warping", s1."Odin Force", s1."Symbiote Costume", s1."Speed Force", s1."Phoenix Force", s1."Molecular Dissipation", s1."Vision - Cryo", s1.Omnipresent, s1.Omniscient FROM Source64_0 s0 JOIN Source64_1 s1 ON s0.name = s1.hero_names; -- Step 4: Export the result to a CSV file COPY Target1_64 TO 'D:\lab\ChatGPTwithSQLscript\github-pipelines\length1_64\Target1_64_result.csv' DELIMITER ',' CSV HEADER; | J57: SQL Result: Table name not identified from last INSERT INTO query. | Q57: This type of error can be resolved if rerun. | V57: Error in the previous response: Error: ERROR: extra data after last expected column CONTEXT: COPY source64_1, line 2: "3-D Man,True,False,False,False,False,False,False,False,False,False,False,False,False,False,False,Fal..."
F58: Source64_1 | G58: [['3-D Man', True, False, False, False, False, False, False, False, False, False, False, False, False, False, False, False, False, True, False, False, False, False, False, False, False, True, False, False, False, False, True, False, False, False, False, False, False, False, False, False, False, False, False, False, False, False, False, False, False, False, False, False, False, False, False, False, False, False, False, False, False, False, False, False, False, False, False, False, False, False, False, False, False, False, False, False, False, False, False, False, False, False, False, False, False, False, False, False, False, False, False, False, False, False, False, False, False, False, False, False, False, False, False, False, False, False, False, False, False, False, False, False, False, False, False, False, False, False, False, False, False, False, False, False, False, False, False, False, False, False, False, False, False, False, False, False, False, False, False, False, False, False, False, False, False, False, False, False, False, False, False, False, False, False, False, False, False, False, False, False, False, False, False, False, False, False, False], ['A-Bomb', False, True, False, False, False, True, False, False, False, False, False, False, False, False, False, True, False, True, False, False, False, False, False, False, False, True, False, False, False, False, False, False, False, False, False, False, False, False, False, False, False, False, False, False, False, False, False, False, False, False, True, False, False, False, False, False, False, False, False, False, False, False, False, True, False, False, False, False, False, False, False, False, False, False, False, False, False, False, False, False, False, False, False, False, False, False, False, False, False, False, False, False, False, False, False, False, False, False, False, False, False, False, False, False, False, False, False, False, False, False, False, False, False, False, False, False, False, False, False, False, False, False, False, False, False, False, False, False, False, False, False, False, False, False, False, False, False, False, False, False, False, False, False, False, False, False, False, False, False, False, False, False, False, False, False, False, False, False, False, False, False, False, False, False, False, False, False], ['Abe Sapien', True, True, False, False, True, True, False, False, False, False, True, True, True, False, False, True, True, True, False, True, False, False, False, False, False, True, False, False, False, False, False, False, False, False, False, False, False, False, False, False, False, False, False, False, False, False, False, False, False, True, False, False, False, False, False, False, False, False, False, True, False, False, False, False, False, False, False, False, False, False, False, False, False, False, False, False, False, False, False, False, False, False, False, False, False, False, False, True, False, False, False, False, False, False, False, False, False, False, False, False, False, False, False, False, False, False, False, False, False, False, False, False, False, False, False, False, False, False, False, False, False, False, False, False, False, False, False, False, False, False, False, False, False, False, False, True, False, False, False, False, False, False, False, False, False, False, False, False, False, False, False, False, False, False, False, False, False, False, False, False, False, False, False, False, False, False, False]] | H58: ['hero_names', 'Agility', 'Accelerated Healing', 'Lantern Power Ring', 'Dimensional Awareness', 'Cold Resistance', 'Durability', 'Stealth', 'Energy Absorption', 'Flight', 'Danger Sense', 'Underwater breathing', 'Marksmanship', 'Weapons Master', 'Power Augmentation', 'Animal Attributes', 'Longevity', 'Intelligence', 'Super Strength', 'Cryokinesis', 'Telepathy', 'Energy Armor', 'Energy Blasts', 'Duplication', 'Size Changing', 'Density Control', 'Stamina', 'Astral Travel', 'Audio Control', 'Dexterity', 'Omnitrix', 'Super Speed', 'Possession', 'Animal Oriented Powers', 'Weapon-based Powers', 'Electrokinesis', 'Darkforce Manipulation', 'Death Touch', 'Teleportation', 'Enhanced Senses', 'Telekinesis', 'Energy Beams', 'Magic', 'Hyperkinesis', 'Jump', 'Clairvoyance', 'Dimensional Travel', 'Power Sense', 'Shapeshifting', 'Peak Human Condition', 'Immortality', 'Camouflage', 'Element Control', 'Phasing', 'Astral Projection', 'Electrical Transport', 'Fire Control', 'Projection', 'Summoning', 'Enhanced Memory', 'Reflexes', 'Invulnerability', 'Energy Constructs', 'Force Fields', 'Self-Sustenance', 'Anti-Gravity', 'Empathy', 'Power Nullifier', 'Radiation Control', 'Psionic Powers', 'Elasticity', 'Substance Secretion', 'Elemental Transmogrification', 'Technopath/Cyberpath', 'Photographic Reflexes', 'Seismic Power', 'Animation', 'Precognition', 'Mind Control', 'Fire Resistance', 'Power Absorption', 'Enhanced Hearing', 'Nova Force', 'Insanity', 'Hypnokinesis', 'Animal Control', 'Natural Armor', 'Intangibility', 'Enhanced Sight', 'Molecular Manipulation', 'Heat Generation', 'Adaptation', 'Gliding', 'Power Suit', 'Mind Blast', 'Probability Manipulation', 'Gravity Control', 'Regeneration', 'Light Control', 'Echolocation', 'Levitation', 'Toxin and Disease Control', 'Banish', 'Energy Manipulation', 'Heat Resistance', 'Natural Weapons', 'Time Travel', 'Enhanced Smell', 'Illusions', 'Thirstokinesis', 'Hair Manipulation', 'Illumination', 'Omnipotent', 'Cloaking', 'Changing Armor', 'Power Cosmic', 'Biokinesis', 'Water Control', 'Radiation Immunity', 'Vision - Telescopic', 'Toxin and Disease Resistance', 'Spatial Awareness', 'Energy Resistance', 'Telepathy Resistance', 'Molecular Combustion', 'Omnilingualism', 'Portal Creation', 'Magnetism', 'Mind Control Resistance', 'Plant Control', 'Sonar', 'Sonic Scream', 'Time Manipulation', 'Enhanced Touch', 'Magic Resistance', 'Invisibility', 'Sub-Mariner', 'Radiation Absorption', 'Intuitive aptitude', 'Vision - Microscopic', 'Melting', 'Wind Control', 'Super Breath', 'Wallcrawling', 'Vision - Night', 'Vision - Infrared', 'Grim Reaping', 'Matter Absorption', 'The Force', 'Resurrection', 'Terrakinesis', 'Vision - Heat', 'Vitakinesis', 'Radar Sense', 'Qwardian Power Ring', 'Weather Control', 'Vision - X-Ray', 'Vision - Thermal', 'Web Creation', 'Reality Warping', 'Odin Force', 'Symbiote Costume', 'Speed Force', 'Phoenix Force', 'Molecular Dissipation', 'Vision - Cryo', 'Omnipresent', 'Omniscient']
A59: L1_65 | B59: Target1_65 | C59: ['year', '0'] | D59: [[1940, 1], [1960, 1], [1962, 1]] | E59: In target, for each year the '0' is count for the year in order. | F59: Source65_0 | G59: [[237000000, '[{"id": 28, "name": "Action"}, {"id": 12, "name": "Adventure"}, {"id": 14, "name": "Fantasy"}, {"id": 878, "name": "Science Fiction"}]', 'http://www.avatarmovie.com/', 19995, '[{"id": 1463, "name": "culture clash"}, {"id": 2964, "name": "future"}, {"id": 3386, "name": "space war"}, {"id": 3388, "name": "space colony"}, {"id": 3679, "name": "society"}, {"id": 3801, "name": "space travel"}, {"id": 9685, "name": "futuristic"}, {"id": 9840, "name": "romance"}, {"id": 9882, "name": "space"}, {"id": 9951, "name": "alien"}, {"id": 10148, "name": "tribe"}, {"id": 10158, "name": "alien planet"}, {"id": 10987, "name": "cgi"}, {"id": 11399, "name": "marine"}, {"id": 13065, "name": "soldier"}, {"id": 14643, "name": "battle"}, {"id": 14720, "name": "love affair"}, {"id": 165431, "name": "anti war"}, {"id": 193554, "name": "power relations"}, {"id": 206690, "name": "mind and soul"}, {"id": 209714, "name": "3d"}]', 'en', 'Avatar', 'In the 22nd century, a paraplegic Marine is dispatched to the moon Pandora on a unique mission, but becomes torn between following orders and protecting an alien civilization.', 150.437577, '[{"name": "Ingenious Film Partners", "id": 289}, {"name": "Twentieth Century Fox Film Corporation", "id": 306}, {"name": "Dune Entertainment", "id": 444}, {"name": "Lightstorm Entertainment", "id": 574}]', '[{"iso_3166_1": "US", "name": "United States of America"}, {"iso_3166_1": "GB", "name": "United Kingdom"}]', '2009-12-10', 2787965087, 162, '[{"iso_639_1": "en", "name": "English"}, {"iso_639_1": "es", "name": "Espa\\u00f1ol"}]', 'Released', 'Enter the World of Pandora.', 'Avatar', 7.2, 11800, 2009], [300000000, '[{"id": 12, "name": "Adventure"}, {"id": 14, "name": "Fantasy"}, {"id": 28, "name": "Action"}]', 'http://disney.go.com/disneypictures/pirates/', 285, '[{"id": 270, "name": "ocean"}, {"id": 726, "name": "drug abuse"}, {"id": 911, "name": "exotic island"}, {"id": 1319, "name": "east india trading company"}, {"id": 2038, "name": "love of one\'s life"}, {"id": 2052, "name": "traitor"}, {"id": 2580, "name": "shipwreck"}, {"id": 2660, "name": "strong woman"}, {"id": 3799, "name": "ship"}, {"id": 5740, "name": "alliance"}, {"id": 5941, "name": "calypso"}, {"id": 6155, "name": "afterlife"}, {"id": 6211, "name": "fighter"}, {"id": 12988, "name": "pirate"}, {"id": 157186, "name": "swashbuckler"}, {"id": 179430, "name": "aftercreditsstinger"}]', 'en', "Pirates of the Caribbean: At World's End", 'Captain Barbossa, long believed to be dead, has come back to life and is headed to the edge of the Earth with Will Turner and Elizabeth Swann. But nothing is quite as it seems.', 139.082615, '[{"name": "Walt Disney Pictures", "id": 2}, {"name": "Jerry Bruckheimer Films", "id": 130}, {"name": "Second Mate Productions", "id": 19936}]', '[{"iso_3166_1": "US", "name": "United States of America"}]', '2007-05-19', 961000000, 169, '[{"iso_639_1": "en", "name": "English"}]', 'Released', 'At the end of the world, the adventure begins.', "Pirates of the Caribbean: At World's End", 6.9, 4500, 2007], [245000000, '[{"id": 28, "name": "Action"}, {"id": 12, "name": "Adventure"}, {"id": 80, "name": "Crime"}]', 'http://www.sonypictures.com/movies/spectre/', 206647, '[{"id": 470, "name": "spy"}, {"id": 818, "name": "based on novel"}, {"id": 4289, "name": "secret agent"}, {"id": 9663, "name": "sequel"}, {"id": 14555, "name": "mi6"}, {"id": 156095, "name": "british secret service"}, {"id": 158431, "name": "united kingdom"}]', 'en', 'Spectre', 'A cryptic message from Bond’s past sends him on a trail to uncover a sinister organization. While M battles political forces to keep the secret service alive, Bond peels back the layers of deceit to reveal the terrible truth behind SPECTRE.', 107.376788, '[{"name": "Columbia Pictures", "id": 5}, {"name": "Danjaq", "id": 10761}, {"name": "B24", "id": 69434}]', '[{"iso_3166_1": "GB", "name": "United Kingdom"}, {"iso_3166_1": "US", "name": "United States of America"}]', '2015-10-26', 880674609, 148, '[{"iso_639_1": "fr", "name": "Fran\\u00e7ais"}, {"iso_639_1": "en", "name": "English"}, {"iso_639_1": "es", "name": "Espa\\u00f1ol"}, {"iso_639_1": "it", "name": "Italiano"}, {"iso_639_1": "de", "name": "Deutsch"}]', 'Released', 'A Plan No One Escapes', 'Spectre', 6.3, 4466, 2015]] | H59: ['budget', 'genres', 'homepage', 'movie_id', 'keywords', 'original_language', 'original_title', 'overview', 'popularity', 'production_companies', 'production_countries', 'release_date', 'revenue', 'runtime', 'spoken_languages', 'status', 'tagline', 'title', 'vote_average', 'vote_count', 'year'] | K59: DROP TABLE IF EXISTS Source65_0; -- Create the source table CREATE TABLE Source65_0 ( budget NUMERIC, genres JSONB, homepage TEXT, movie_id INTEGER, keywords JSONB, original_language TEXT, original_title TEXT, overview TEXT, popularity NUMERIC, production_companies JSONB, production_countries JSONB, release_date DATE, revenue NUMERIC, runtime INTEGER, spoken_languages JSONB, status TEXT, tagline TEXT, title TEXT, vote_average NUMERIC, vote_count INTEGER, year INTEGER ); -- Insert data from the CSV file into the source table COPY Source65_0 FROM 'D:\lab\ChatGPTwithSQLscript\github-pipelines\length1_65\test_0.csv' DELIMITER ',' CSV HEADER NULL ''; -- Drop the target table if it exists DROP TABLE IF EXISTS Target1_65; -- Create the target table CREATE TABLE Target1_65 ( year INTEGER, "0" INTEGER ); -- Insert data from the source table into the target table INSERT INTO Target1_65 (year, "0") SELECT year, COUNT(*) AS "0" FROM Source65_0 GROUP BY year; -- Export the result to a CSV file COPY (SELECT * FROM Target1_65) TO 'D:\lab\ChatGPTwithSQLscript\github-pipelines\length1_65\Target1_65_result.csv' DELIMITER ',' CSV HEADER; | M59: 0 | N59: [0.018867924528301886, 0.07547169811320754] | Q59: The hints made sim score better, the order of row should match exactly. | T59: 0 | Z59: success
A60: L1_69 | B60: Target1_69 | C60: ['city', 'driver_count', 'type', 'date', 'fare', 'ride_id'] | D60: [['Kelseyland', 63, 'Urban', '2016-08-19 04:27:52', 5.51, 6246006544795], ['Kelseyland', 63, 'Urban', '2016-04-17 06:59:50', 5.54, 7466473222333], ['Kelseyland', 63, 'Urban', '2016-05-04 15:06:07', 30.54, 2140501382736]] | E60: Use Join on source tables | F60: Source69_0 | G60: [['Kelseyland', 63, 'Urban'], ['Nguyenbury', 8, 'Urban'], ['East Douglas', 12, 'Urban']] | H60: ['city', 'driver_count', 'type'] | K60: DROP TABLE IF EXISTS Source_0; CREATE TABLE Source_0 ( city VARCHAR, driver_count INTEGER, type VARCHAR ); DROP TABLE IF EXISTS Source_1; CREATE TABLE Source_1 ( city VARCHAR, date TIMESTAMP, fare FLOAT, ride_id BIGINT ); -- Step 2: Insert data into the source tables from CSV files COPY Source_0(city, driver_count, type) FROM 'D:\lab\ChatGPTwithSQLscript\github-pipelines\length1_69\test_0.csv' DELIMITER ',' CSV HEADER NULL ''; COPY Source_1(city, date, fare, ride_id) FROM 'D:\lab\ChatGPTwithSQLscript\github-pipelines\length1_69\test_1.csv' DELIMITER ',' CSV HEADER NULL ''; -- Step 3: Create the target table DROP TABLE IF EXISTS Target1_69; CREATE TABLE Target1_69 ( city VARCHAR, driver_count INTEGER, type VARCHAR, date TIMESTAMP, fare FLOAT, ride_id BIGINT ); -- Step 4: Insert data into the target table by joining the source tables INSERT INTO Target1_69 (city, driver_count, type, date, fare, ride_id) SELECT s0.city, s0.driver_count, s0.type, s1.date, s1.fare, s1.ride_id FROM Source_0 s0 JOIN Source_1 s1 ON s0.city = s1.city; -- Step 5: Export the result to a CSV file COPY (SELECT * FROM Target1_69) TO 'D:\lab\ChatGPTwithSQLscript\github-pipelines\length1_69\Target1_69_result.csv' DELIMITER ',' CSV HEADER; | M60: 0.5 | N60: [1.0, 0.02358887952822241, 1.0, 1.0, 0.0008424599831508003, 0.0008424599831508003] | T60: 1
F61: Source69_1 | G61: [['Sarabury', '2016-01-16 13:49:27', 38.35, 5403689035038], ['South Roy', '2016-01-02 18:42:34', 17.49, 4036272335942], ['Wiseborough', '2016-01-21 17:35:29', 44.18, 3645042422587]] | H61: ['city', 'date', 'fare', 'ride_id']
A62: L1_70 | B62: Target1_70 | C62: ['order_id', 'order_status', 'order_approved_at', 'product_id', 'seller_id', 'price', 'freight_value'] | D62: [['53cdb2fc8bc7dce0b6741e2150273451', 'delivered', '2018-07-26 03:24:27', '595fac2a385ac33a80bd5114aec74eb8', '289cdb325fb7e7f891c38608bf9e0962', 118.7, 22.76], ['47770eb9100c2d0c44946d9cf07ec65d', 'delivered', '2018-08-08 08:55:23', 'aa4383b373c6aca5d8797843e5594415', '4869f7a5dfa277a7dca6462dcf3b52b2', 159.9, 19.22], ['136cce7faa42fdb2cefd53fdc79a6098', 'invoiced', '2017-04-13 13:25:17', 'a1804276d9941ac0733cfd409f5206eb', 'dc8798cbf453b7e0f98745e396cc5616', 49.9, 16.05]] | E62: Use Join on source tables | F62: Source70_0 | G62: [['e481f51cbdc54678b7cc49136f2d6af7', '9ef432eb6251297304e76186b10a928d', 'delivered', '2017-10-02 10:56:33', '2017-10-02 11:07:15', '2017-10-04 19:55:00', '2017-10-10 21:25:13', '2017-10-18 00:00:00'], ['53cdb2fc8bc7dce0b6741e2150273451', 'b0830fb4747a6c6d20dea0b8c802d7ef', 'delivered', '2018-07-24 20:41:37', '2018-07-26 03:24:27', '2018-07-26 14:31:00', '2018-08-07 15:27:45', '2018-08-13 00:00:00'], ['47770eb9100c2d0c44946d9cf07ec65d', '41ce2a54c0b03bf3443c3d931a367089', 'delivered', '2018-08-08 08:38:49', '2018-08-08 08:55:23', '2018-08-08 13:50:00', '2018-08-17 18:06:29', '2018-09-04 00:00:00']] | H62: ['order_id', 'customer_id', 'order_status', 'order_purchase_timestamp', 'order_approved_at', 'order_delivered_carrier_date', 'order_delivered_customer_date', 'order_estimated_delivery_date'] | K62: DROP TABLE IF EXISTS Source70_0; CREATE TABLE Source70_0 ( order_id VARCHAR, customer_id VARCHAR, order_status VARCHAR, order_purchase_timestamp TIMESTAMP, order_approved_at TIMESTAMP, order_delivered_carrier_date TIMESTAMP, order_delivered_customer_date TIMESTAMP, order_estimated_delivery_date TIMESTAMP ); DROP TABLE IF EXISTS Source70_1; CREATE TABLE Source70_1 ( order_id VARCHAR, order_item_id INTEGER, product_id VARCHAR, seller_id VARCHAR, price NUMERIC, freight_value NUMERIC ); -- Step 2: Insert data into the source tables from CSV files COPY Source70_0 (order_id, customer_id, order_status, order_purchase_timestamp, order_approved_at, order_delivered_carrier_date, order_delivered_customer_date, order_estimated_delivery_date) FROM 'D:\lab\ChatGPTwithSQLscript\github-pipelines\length1_70\test_0.csv' DELIMITER ',' CSV HEADER NULL ''; COPY Source70_1 (order_id, order_item_id, product_id, seller_id, price, freight_value) FROM 'D:\lab\ChatGPTwithSQLscript\github-pipelines\length1_70\test_1.csv' DELIMITER ',' CSV HEADER NULL ''; -- Step 3: Create the target table DROP TABLE IF EXISTS Target1_70; CREATE TABLE Target1_70 ( order_id VARCHAR, order_status VARCHAR, order_approved_at TIMESTAMP, product_id VARCHAR, seller_id VARCHAR, price NUMERIC, freight_value NUMERIC ); -- Step 4: Insert data into the target table from the source tables INSERT INTO Target1_70 (order_id, order_status, order_approved_at, product_id, seller_id, price, freight_value) SELECT s0.order_id, s0.order_status, s0.order_approved_at, s1.product_id, s1.seller_id, s1.price, s1.freight_value FROM Source70_0 s0 JOIN Source70_1 s1 ON s0.order_id = s1.order_id; -- Step 5: Export the result to a CSV file COPY (SELECT * FROM Target1_70) TO 'D:\lab\ChatGPTwithSQLscript\github-pipelines\length1_70\Target1_70_result.csv' DELIMITER ',' CSV HEADER; | Q62: Ordering row would make acc 1. We do not know which ordering target file is using. No target data description was given. | T62: 1
F63: Source70_1 | G63: [['00010242fe8c5a6d1ba2dd792cb16214', 1, '4244733e06e7ecb4970a6e2683c13e61', '48436dade18ac8b2bce089ec2a041202', 58.9, 13.29], ['00018f77f2f0320c557190d7a144bdd3', 1, 'e5f2d52b802189ee658865ca93d83a8f', 'dd7ddc04e1b6c2c614352b383efe2d36', 239.9, 19.93], ['000229ec398224ef6ca0657da4fc703e', 1, 'c777355d18b72b67abbeef9df44fd0fd', '5b51032eddd242adc84c38acab88f23d', 199.0, 17.87]] | H63: ['order_id', 'order_item_id', 'product_id', 'seller_id', 'price', 'freight_value'] | M63: 0.57 | N63: 1.0, 1.0, 0.9999574793774981, 1.0, 1.0, 0.00388814913448735, 0.0037283621837549932 | Q63: Running with 'E'
A64: L1_71 | B64: Target1_71 | C64: ['Region', 'Poblacion', 'Superficie'] | D64: [['Antofagasta', 551627, 126048.8], ['Arica y Parinacota', 308271, 17446.2], ['Atacama', 292054, 74806.3]] | E64: In target, Poblacion and superficie are sum from source table for each Region in order. | F64: Source71_0 | G64: [[1, 'Arica y Parinacota', 'Arica', 'Arica', 4799.4, 210936, 38.4, 0.736], [1, 'Arica y Parinacota', 'Arica', 'Camarones', 3927.0, 679, 0.3, 0.7509999999999999], [1, 'Arica y Parinacota', 'Parinacota', 'General Lagos', 2244.4, 739, 0.5, 0.67]] | H64: ['RegionID', 'Region', 'Provincia', 'Comuna', 'Superficie', 'Poblacion', 'Densidad', 'IDH_2005'] | K64: DROP TABLE IF EXISTS Source71_0; -- Create the source table CREATE TABLE Source71_0 ( RegionID INT, Region VARCHAR(255), Provincia VARCHAR(255), Comuna VARCHAR(255), Superficie FLOAT, Poblacion INT, Densidad FLOAT, IDH_2005 FLOAT ); -- Insert data from the CSV file into the source table COPY Source71_0 FROM 'D:\lab\ChatGPTwithSQLscript\github-pipelines\length1_71\test_0.csv' DELIMITER ',' CSV HEADER NULL ''; -- Drop the target table if it exists DROP TABLE IF EXISTS Target1_71; -- Create the target table CREATE TABLE Target1_71 ( Region VARCHAR(255), Poblacion INT, Superficie FLOAT ); -- Insert data from the source table into the target table INSERT INTO Target1_71 (Region, Poblacion, Superficie) SELECT Region, SUM(Poblacion), SUM(Superficie) FROM Source71_0 GROUP BY Region; -- Copy the result from the target table to a CSV file COPY (SELECT * FROM Target1_71) TO 'D:\lab\ChatGPTwithSQLscript\github-pipelines\length1_71\Target1_71_result.csv' DELIMITER ',' CSV HEADER; | M64: 0.33 | N64: 1.0, 0.0, 0.0 | T64: 1 | Z64: success | AA64: success
A65: L1_72 | B65: Target1_72 | C65: ['condition', '0'] | D65: [[0, 253], [1, 246]] | E65: In target, for each condition, '0' is total count. | F65: Source72_0 | G65: [[1, 0], [0, 0], [0, 0]] | H65: ['condition', 'click'] | K65: DROP TABLE IF EXISTS Source72_0; -- Create the source table CREATE TABLE Source72_0 ( condition INTEGER, click INTEGER ); -- Insert data from the CSV file into the source table COPY Source72_0 (condition, click) FROM 'D:\lab\ChatGPTwithSQLscript\github-pipelines\length1_72\test_0.csv' WITH (FORMAT csv, HEADER true, NULL ''); -- Drop the target table if it exists DROP TABLE IF EXISTS Target1_72; -- Create the target table CREATE TABLE Target1_72 ( condition INTEGER, "0" INTEGER ); -- Insert data from the source table into the target table INSERT INTO Target1_72 (condition, "0") SELECT condition, COUNT(*) AS "0" FROM Source72_0 GROUP BY condition; -- Copy the result of the SQL query into a CSV file COPY ( SELECT * FROM Target1_72 ) TO 'D:\lab\ChatGPTwithSQLscript\github-pipelines\length1_72\Target1_72_result.csv' WITH (FORMAT csv, HEADER true); | M65: 1 | Q65: success | T65: 0 | Z65: failed | AA65: failed | AB65: should have done aggregation
A66: L1_73 | B66: Target1_73 | C66: ['Country', 'Region', 'Happiness_Rank_15', 'Happiness_Score_15', 'Standard_Error_15', 'Economy_15', 'Family_15', 'Life_Expectancy_15', 'Freedom_15', 'Trust_15', 'Generosity_15', 'Dystopia_15', 'Happiness_Rank_17', 'Happiness_Score_17', 'Whisker_High_17', 'Whisker_Low_17', 'Economy_17', 'Family_17', 'Life_Expectancy_17', 'Freedom_17', 'Generosity_17', 'Trust_17', 'Dystopia_17'] | D66: [['Switzerland', 'Western Europe', 1, 7.5870000000000015, 0.03411, 1.39651, 1.34951, 0.94143, 0.66557, 0.41978, 0.29678000000000004, 2.51738, 4, 7.493999958, 7.56177242, 7.426227496, 1.564979553, 1.516911745, 0.858131289, 0.620070577, 0.290549278, 0.367007285, 2.276716232], ['Iceland', 'Western Europe', 2, 7.561, 0.04884, 1.30232, 1.40223, 0.94784, 0.6287699999999999, 0.14145, 0.4363, 2.70201, 3, 7.504000187000001, 7.622030473, 7.385969901, 1.48063302, 1.610574007, 0.8335521220000001, 0.627162635, 0.475540221, 0.153526559, 2.322715282], ['Denmark', 'Western Europe', 3, 7.527, 0.033280000000000004, 1.32548, 1.36058, 0.87464, 0.6493800000000001, 0.48357, 0.34139, 2.4920400000000003, 2, 7.521999836, 7.581728065, 7.462271607000001, 1.4823830130000002, 1.5511215930000002, 0.792565525, 0.6260067220000001, 0.355280489, 0.400770068, 2.313707352]] | E66: Use Join on source table | F66: Source73_0 | G66: [['Norway', 1, 7.537000179, 7.5944448210000015, 7.479555538, 1.616463184, 1.53352356, 0.796666503, 0.635422587, 0.362012237, 0.315963835, 2.277026653], ['Denmark', 2, 7.521999836, 7.581728065, 7.462271607000001, 1.4823830130000002, 1.5511215930000002, 0.792565525, 0.6260067220000001, 0.355280489, 0.400770068, 2.313707352], ['Iceland', 3, 7.504000187000001, 7.622030473, 7.385969901, 1.48063302, 1.610574007, 0.8335521220000001, 0.627162635, 0.475540221, 0.153526559, 2.322715282]] | H66: ['Country', 'Happiness_Rank_17', 'Happiness_Score_17', 'Whisker_High_17', 'Whisker_Low_17', 'Economy_17', 'Family_17', 'Life_Expectancy_17', 'Freedom_17', 'Generosity_17', 'Trust_17', 'Dystopia_17'] | K66: DROP TABLE IF EXISTS Source73_0; CREATE TABLE Source73_0 ( Country VARCHAR, Happiness_Rank_17 INTEGER, Happiness_Score_17 FLOAT, Whisker_High_17 FLOAT, Whisker_Low_17 FLOAT, Economy_17 FLOAT, Family_17 FLOAT, Life_Expectancy_17 FLOAT, Freedom_17 FLOAT, Generosity_17 FLOAT, Trust_17 FLOAT, Dystopia_17 FLOAT ); -- Insert data into the first table Source73_0 COPY Source73_0 FROM 'D:\lab\ChatGPTwithSQLscript\github-pipelines\length1_73\test_0.csv' DELIMITER ',' CSV HEADER NULL ''; -- Create the second table Source73_1 DROP TABLE IF EXISTS Source73_1; CREATE TABLE Source73_1 ( Country VARCHAR, Region VARCHAR, Happiness_Rank INTEGER, Happiness_Score FLOAT, Standard_Error FLOAT, Economy FLOAT, Family FLOAT, Life_Expectancy FLOAT, Freedom FLOAT, Trust FLOAT, Generosity FLOAT, Dystopia_Residual FLOAT ); -- Insert data into the second table Source73_1 COPY Source73_1 FROM 'D:\lab\ChatGPTwithSQLscript\github-pipelines\length1_73\test_1.csv' DELIMITER ',' CSV HEADER NULL ''; -- Create the target table Target1_73 DROP TABLE IF EXISTS Target1_73; CREATE TABLE Target1_73 ( Country VARCHAR, Region VARCHAR, Happiness_Rank_15 INTEGER, Happiness_Score_15 FLOAT, Standard_Error_15 FLOAT, Economy_15 FLOAT, Family_15 FLOAT, Life_Expectancy_15 FLOAT, Freedom_15 FLOAT, Trust_15 FLOAT, Generosity_15 FLOAT, Dystopia_15 FLOAT, Happiness_Rank_17 INTEGER, Happiness_Score_17 FLOAT, Whisker_High_17 FLOAT, Whisker_Low_17 FLOAT, Economy_17 FLOAT, Family_17 FLOAT, Life_Expectancy_17 FLOAT, Freedom_17 FLOAT, Generosity_17 FLOAT, Trust_17 FLOAT, Dystopia_17 FLOAT ); -- Insert data into the target table Target1_73 by joining the two source tables INSERT INTO Target1_73 ( Country, Region, Happiness_Rank_17, Happiness_Score_17, Economy_17, Family_17, Life_Expectancy_17, Freedom_17, Generosity_17, Trust_17, Dystopia_17 ) SELECT s0.Country, s1.Region, s0.Happiness_Rank_17, s0.Happiness_Score_17, s0.Economy_17, s0.Family_17, s0.Life_Expectancy_17, s0.Freedom_17, s0.Generosity_17, s0.Trust_17, s0.Dystopia_17 FROM Source73_0 s0 JOIN Source73_1 s1 ON s0.Country = s1.Country; -- Export the result to a CSV file COPY Target1_73 TO 'D:\lab\ChatGPTwithSQLscript\github-pipelines\length1_73\Target1_73_result.csv' DELIMITER ',' CSV HEADER; | M66: 0.086 | N66: [1.0, 1.0, 0.0, 0.0, 0.0, 0.0, 0.0, 0.0, 0.0, 0.013333333333333334, 0.0, 0.0, 0.08, 0.08, 0.0, 0.0, 0.08, 0.08, 0.08, 0.08, 0.08, 0.08, 0.08] | Q66: Some columns are empty hence the low similarity score. | T66: 1
F67: Source73_1 | G67: [['Switzerland', 'Western Europe', 1, 7.5870000000000015, 0.03411, 1.39651, 1.34951, 0.94143, 0.66557, 0.41978, 0.29678000000000004, 2.51738], ['Iceland', 'Western Europe', 2, 7.561, 0.04884, 1.30232, 1.40223, 0.94784, 0.6287699999999999, 0.14145, 0.4363, 2.70201], ['Denmark', 'Western Europe', 3, 7.527, 0.033280000000000004, 1.32548, 1.36058, 0.87464, 0.6493800000000001, 0.48357, 0.34139, 2.4920400000000003]] | H67: ['Country', 'Region', 'Happiness Rank', 'Happiness Score', 'Standard Error', 'Economy (GDP per Capita)', 'Family', 'Health (Life Expectancy)', 'Freedom', 'Trust (Government Corruption)', 'Generosity', 'Dystopia Residual']
A68: L1_75 | B68: Target1_75 | C68: ['neighbourhood', 'id', 'name', 'host_id', 'host_name', 'neighbourhood_group', 'latitude', 'longitude', 'room_type', 'price', 'minimum_nights', 'number_of_reviews', 'last_review', 'reviews_per_month', 'calculated_host_listings_count', 'availability_365'] | D68: [['Can Baró', 21, 21, 21, 21, 21, 21, 21, 21, 21, 21, 21, 19, 19, 21, 21], ['Canyelles', 3, 3, 3, 3, 3, 3, 3, 3, 3, 3, 3, 2, 2, 3, 3], ['Ciutat Meridiana', 5, 5, 5, 5, 5, 5, 5, 5, 5, 5, 5, 5, 5, 5, 5]] | F68: Source75_0 | G68: [[18666, 'Flat with Sunny Terrace', 71615, 'Mireia And Maria', 'Sant Martí', "el Camp de l'Arpa del Clot", 41.408886211580345, 2.1855453256058017, 'Entire home/apt', 130, 3, 1, '2015-10-10', 0.03, 34, 20], [18674, 'Huge flat for 8 people close to Sagrada Familia', 71615, 'Mireia And Maria', 'Eixample', 'la Sagrada Família', 41.404196784819064, 2.1730577177402504, 'Entire home/apt', 55, 1, 5, '2018-06-18', 0.07, 34, 40], [21605, 'Nice and sunny duble room', 82522, 'Meritxell', 'Sant Martí', 'el Poblenou', 41.4056041572247, 2.19820512273065, 'Private room', 33, 2, 103, '2018-11-30', 3.26, 3, 290]] | H68: ['id', 'name', 'host_id', 'host_name', 'neighbourhood_group', 'neighbourhood', 'latitude', 'longitude', 'room_type', 'price', 'minimum_nights', 'number_of_reviews', 'last_review', 'reviews_per_month', 'calculated_host_listings_count', 'availability_365'] | T68: 0
A69: L1_77 | B69: Target1_77 | C69: ['fac_type', 'capacity'] | D69: [['NF', 11201], ['RCF', 7136]] | F69: Source77_0 | G69: [[385008, 'NF', 96.0, 'Presbyterian Community Care Center', '1085 N Oregon St', 'Ontario, OR 97914', 'Presbyterian Nursing Home, Inc.', 'Presbyterian Nursing Home, Inc.'], [385010, 'NF', 159.0, 'Laurelhurst Village Rehabilitation Center', '3060 SE Stark St', 'Portland, OR 97214', 'Laurelhurst Operations, LLC', 'Laurelhurst Operations, LLC'], [385015, 'NF', 128.0, 'Regency Gresham Nursing & Rehabilitation Center', '5905 SE Powell Valley Rd', 'Gresham, OR 97080', 'Regency Gresham Nursing & Rehabilitation Center, LLC', 'Regency Pacific Management, LLC']] | H69: ['facid', 'fac_type', 'capacity', 'fac_name', 'fac_address', 'city_state_zip', 'owner', 'operator'] | T69: Fail | V69: ERROR: Error: ERROR: invalid input syntax for type integer: "38A001" CONTEXT: COPY source77_0, line 120, column facid: "38A001" | AA69: data pre processing error
A70: L1_78 | B70: Target1_78 | C70: ['Product', 'Price'] | D70: [['P0000005913', 1590.0], ['P0000006591', 999.0], ['P0000011163', 790.0]] | F70: Source78_0 | G70: [['2015-07-01 00:00:01', 'order', 'U312622727', 'P0006944501', 1, 1069.0], ['2015-07-01 00:00:03', 'order', 'U239012343', 'P0006018073', 1, 1680.0], ['2015-07-01 00:00:19', 'order', 'U10007697373', 'P0002267974', 1, 285.0]] | H70: ['Dates', 'Action', 'User', 'Product', 'Quantity', 'Price'] | T70: Fail | V70: ERROR: Error: ERROR: syntax error at or near "User" LINE 6: User VARCHAR, ^ | AA70: data pre processing error
A71: L1_8 | B71: Target1_8 | C71: ['index_track', 'track_id', 'dummy'] | D71: [[1, 2359314, 1], [11, 2621486, 1], [12, 2621488, 1]] | E71: Use join on source tables | F71: Source8_0 | G71: [[1316175, 1], [3885714, 1], [3091270, 1]] | H71: ['track_id', 'dummy'] | M71: 0 | T71: 1
F72: Source8_1 | G72: [[0, 1048594], [1, 2359314], [2, 1835030]] | H72: ['index_track', 'track_id']
A73: L1_44 | B73: Target1_44 | C73: ['Country / territory of asylum/residence', 'Year'] | D73: [['Albania', 211552], ['Australia', 6563431], ['Austria', 6958781]] | F73: Source44_0 | G73: [['Canada', 'Djibouti', 2010, 'May', 17], ['Belgium', 'The former Yugoslav Rep. of Macedonia', 2007, 'May', 4], ['Ireland', 'Libya', 2013, 'January', 2]] | H73: ['Country / territory of asylum/residence', 'Origin', 'Year', 'Month', 'Value'] | T73: fail | V73: ERROR: Error: ERROR: invalid input syntax for type integer: "*" CONTEXT: COPY source_0, line 26, column Value: "*" | AA73: data pre processing error
A74: L1_62 | B74: Target1_62 | C74: ['Month', 'Water Use', 'Power Use'] | D74: [['Apr_2006', 4351.0999999999985, 25274], ['Apr_2007', 6148.879999999999, 34389], ['Apr_2008', 4618.79, 31594]] | F74: Source62_0 | G74: [['Mar_2008', 'Mar-08', '90230\n(33.99506171100046, -118.39500957899969)', 16.7, 396], ['Jul_2011', 'Jul-11', '90272\n(34.04886156900045, -118.53572692799969)', 35.73, 1013], ['Apr_2010', 'Apr-10', '90272\n(34.04886156900045, -118.53572692799969)', 23.53, 916]] | H74: ['Text Date', 'Value Date', 'Zip Code', 'Water Use', 'Power Use'] | T74: 0 | Z74: failed | AA74: failed
A75: L1_80 | B75: Target1_80 | C75: ['movieId', 'rating'] | D75: [[1.0, 3.8192307692307694], [2.0, 3.411290322580645], [3.0, 3.4615384615384617]] | F75: Source80_0 | G75: [[1.0, 31.0, 2.5, 1260759144.0], [1.0, 1029.0, 3.0, 1260759179.0], [1.0, 1061.0, 3.0, 1260759182.0]] | H75: ['userId', 'movieId', 'rating', 'timestamp'] | T75: 0 | Z75: failed | AA75: failed
A76: L1_99 | B76: Target1_99 | C76: ['user_id', 'timestamp', 'source', 'device', 'operative_system', 'test', 'price', 'converted'] | D76: [[639459, '2015-05-02 13:45:32', 'ads_facebook', 'mobile', 'iOS', 0, 39, 0], [285124, '2015-03-26 18:28:13', 'seo-google', 'mobile', 'other', 1, 59, 0], [275927, '2015-03-13 07:06:45', 'seo-google', 'web', 'windows', 0, 39, 0]] | F76: Source99_0 | G76: [[639459, '2015-05-02 13:45:32', 'ads_facebook', 'mobile', 'iOS', 0, 39, 0], [285124, '2015-03-26 18:28:13', 'seo-google', 'mobile', 'other', 1, 59, 0], [275927, '2015-03-13 07:06:45', 'seo-google', 'web', 'windows', 0, 39, 0]] | H76: ['user_id', 'timestamp', 'source', 'device', 'operative_system', 'test', 'price', 'converted'] | T76: 0 | Z76: data procesessing error | AA76: failed | AB76: check p1 response, why not preprocesin g error
A77: L2_26 | B77: Target2_26 | C77: ['user_id', 'time', 'bet', 'win', 'email', 'geo'] | D77: [['user_1000', 5, 1, 0, 5, 5], ['user_900', 8, 2, 1, 8, 8], ['user_901', 5, 0, 0, 5, 5]] | F77: Source26_0 | G77: [['user_943', 'Accumanst@gmail.com', 'Ижевск'], ['user_908', 'Advismowr@mail.ru', 'Ижевск'], ['user_962', 'Anachso@ukr.net', 'Краснодар']] | H77: ['user_id', 'email', 'geo']
F78: Source26_1 | G78: [['user_919', '[2019-01-01 14:06:51', nan, nan], ['user_973', '[2019-01-01 14:51:16', nan, nan], ['user_903', '[2019-01-01 16:31:16', nan, nan]] | H78: ['user_id', 'time', 'bet', 'win']
A79: L2_44 | B79: Target2_44 | C79: ['city', 'fare', 'ride_id'] | D79: [['Amandaburgh', 23.072, 15], ['Barajasview', 28.754375, 16], ['Carriemouth', 27.250476190476192, 21]] | F79: Source44_0 | G79: [['Lake Jonathanshire', '2018-01-14 10:14:22', 13.83, 5739410935873], ['South Michelleport', '2018-03-04 18:24:09', 30.24, 2343912425577], ['Port Samanthamouth', '2018-02-24 04:29:00', 33.44, 2005065760003]] | H79: ['city', 'date', 'fare', 'ride_id'] | T79: 0
F80: Source44_1 | G80: [['Richardfort', 38, 'Urban'], ['Williamsstad', 59, 'Urban'], ['Port Angela', 67, 'Urban']] | H80: ['city', 'driver_count', 'type']
A81: L2_62 | B81: Target2_62 | C81: ['city', 'driver_count'] | D81: [['Amandaburgh', 12], ['Barajasview', 26], ['Carriemouth', 52]] | F81: Source62_0 | G81: [['Lake Jonathanshire', '2018-01-14 10:14:22', 13.83, 5739410935873], ['South Michelleport', '2018-03-04 18:24:09', 30.24, 2343912425577], ['Port Samanthamouth', '2018-02-24 04:29:00', 33.44, 2005065760003]] | H81: ['city', 'date', 'fare', 'ride_id'] | T81: 0
F82: Source62_1 | G82: [['Richardfort', 38, 'Urban'], ['Williamsstad', 59, 'Urban'], ['Port Angela', 67, 'Urban']] | H82: ['city', 'driver_count', 'type']
A83: L2_80 | B83: Target2_80 | C83: ['0', '1', '2', '3'] | D83: [[0.8814461055685514, 0.5528350673993359, 0.424363111682073, -1.5633158532575984], [-2.154050040012661, 0.4643952008043402, 0.3803460852376078, 1.944852361758166], [2.4446149781602804, -0.3806431069606226, 0.06266350330003836, 2.058244993436092]] | F83: Source80_0 | G83: [[0.8814461055685514, 0.5528350673993359, 0.424363111682073, -1.5633158532575984], [-2.154050040012661, 0.4643952008043402, 0.3803460852376078, 1.944852361758166], [2.4446149781602804, -0.3806431069606226, 0.06266350330003836, 2.058244993436092]] | H83: ['0', '1', '2', '3'] | T83: 0
A84: L2_99 | B84: Target2_99 | C84: ['city', 'driver_count'] | D84: [['Amandaburgh', 12], ['Barajasview', 26], ['Carriemouth', 52]] | F84: Source99_0 | G84: [['Richardfort', 38, 'Urban'], ['Williamsstad', 59, 'Urban'], ['Port Angela', 67, 'Urban']] | H84: ['city', 'driver_count', 'type'] | T84: 0
F85: Source99_1 | G85: [['Lake Jonathanshire', '2018-01-14 10:14:22', 13.83, 5739410935873], ['South Michelleport', '2018-03-04 18:24:09', 30.24, 2343912425577], ['Port Samanthamouth', '2018-02-24 04:29:00', 33.44, 2005065760003]] | H85: ['city', 'date', 'fare', 'ride_id']
A86: L3_25 | B86: Target3_25 | C86: ['title', 'user_id', 'movie_id', 'rating', 'timestamp', 'age', 'occupation'] | D86: [['$1,000,000 Duck (1971)', 1964.833333333333, 2031, 3.6666666666666665, 973809729.5, 30.16666666666667, 8.166666666666666], ["'Night Mother (1986)", 3879.5, 3112, 3.0, 966715936.75, 35.0, 1.5], ["'Til There Was You (1997)", 528.0, 779, 3.0, 980041013.0, 18.0, 17.0]] | F86: Source25_0 | G86: [[1, 'F', 1, 10, 48067], [2, 'M', 56, 16, 70072], [3, 'M', 25, 15, 55117]] | H86: ['user_id', 'gender', 'age', 'occupation', 'zip'] | T86: 0
F87: Source25_1 | G87: [[2619, 3798, 4, 973658301], [2825, 3424, 5, 972612877], [275, 1258, 5, 976592546]] | H87: ['user_id', 'movie_id', 'rating', 'timestamp']
F88: Source25_2 | G88: [[1, 'Toy Story (1995)', "Animation|Children's|Comedy"], [2, 'Jumanji (1995)', "Adventure|Children's|Fantasy"], [3, 'Grumpier Old Men (1995)', 'Comedy|Romance']] | H88: ['movie_id', 'title', 'genres']
A89: L3_43 | B89: Target3_43 | C89: ['type', 'Total Students', 'Total School Budget', 'Average Math Score', 'Average Reading Score', 'School Size'] | D89: [['Charter', 1842.5, 1093757.5, 83.26176215406309, 83.87693735977467, 1842.5], ['District', 3869.25, 2485498.5, 76.93311232228885, 81.03334502384055, 3869.25]] | F89: Source43_0 | G89: [[0, 'Huang High School', 'District', 2917, 1910635], [1, 'Figueroa High School', 'District', 2949, 1884411], [2, 'Shelton High School', 'Charter', 1761, 1056600]] | H89: ['School ID', 'school_name', 'type', 'size', 'budget'] | T89: 0
F90: Source43_1 | G90: [[0, 'Paul Bradley', 'M', '9th', 'Huang High School', 66, 79], [1, 'Victor Smith', 'M', '12th', 'Huang High School', 94, 61], [2, 'Kevin Rodriguez', 'M', '12th', 'Huang High School', 90, 60]] | H90: ['Student ID', 'student_name', 'gender', 'grade', 'school_name', 'reading_score', 'math_score']
A91: L3_61 | B91: Target3_61 | C91: ['Timepoint', 'Capomulin', 'Ceftamin', 'Infubinol', 'Ketapril', 'Naftisol', 'Placebo', 'Propriva', 'Ramicane', 'Stelasyn', 'Zoniferol'] | D91: [[0.0, 45.0, 45.0, 45.0, 45.0, 45.0, 45.0, 45.0, 45.0, 45.0, 45.0], [5.0, 44.26608641544399, 46.5030509580381, 47.06200103308799, 47.38917452114347, 46.7960980984913, 47.12558918843749, 47.24896703293201, 43.944859399664004, 47.527451674148, 46.851818267095844], [10.0, 43.08429058188399, 48.285125215944994, 49.40390857087143, 49.582268974622714, 48.694209604047636, 49.4233294786875, 49.10154084291304, 42.53195729572083, 49.46384376145653, 48.68988143470909]] | F91: Source61_0 | G91: [['f234', 'Stelasyn'], ['x402', 'Stelasyn'], ['a492', 'Stelasyn']] | H91: ['Mouse ID', 'Drug'] | T91: 0.09 | U91: [1.0, 0.2, 0.4, 0.2, 0.4, 0.4, 0.2, 0.2, 0.4, 0.4, 0.4]
F92: Source61_1 | G92: [['b128', 0, 45.0, 0], ['f932', 0, 45.0, 0], ['g107', 0, 45.0, 0]] | H92: ['Mouse ID', 'Timepoint', 'Tumor Volume (mm3)', 'Metastatic Sites']
A93: L3_8 | B93: Target3_8 | C93: ['Wrestler', '2013 Wins', '2013 Losses', '2013 Draws', '2014 Wins', '2014 Losses', '2014 Draws', '2015 Wins', '2015 Losses', '2015 Draws', '2016 Wins', '2016 Losses', '2016 Draws'] | D93: [['Dean Ambrose', 70, 134, 4, 129, 36, 2, 150, 63, 5, 133, 67, 4], ['Seth Rollins', 50, 150, 4, 87, 105, 4, 51, 124, 1, 39, 75, 4], ['Randy Orton', 129, 63, 8, 33, 87, 5, 81, 10, 1, 39, 21, 0]] | F93: Source8_0 | G93: [['Daniel Bryan', 177, 37, 6], ['Dean Ambrose', 70, 134, 4], ['Antonio Cesaro', 80, 126, 1]] | H93: ['Wrestler', 'Wins', 'Losses', 'Draws']
F94: Source8_1 | G94: [['Dean Ambrose', 133, 67, 4], ['Kevin Owens', 61, 130, 2], ['Tyler Breeze', 17, 163, 2]] | H94: ['Wrestler', 'Wins', 'Losses', 'Draws']
F95: Source8_2 | G95: [['Dean Ambrose', 150, 63, 5], ['Roman Reigns', 187, 19, 7], ['Cesaro', 117, 69, 1]] | H95: ['Wrestler', 'Wins', 'Losses', 'Draws']
F96: Source8_3 | G96: [['Dolph Ziggler', 134, 60, 2], ['Seth Rollins', 87, 105, 4], ['Jimmy Uso', 143, 43, 4]] | H96: ['Wrestler', 'Wins', 'Losses', 'Draws']
A97: L3_98 | B97: Target3_98 | C97: ['MOTATE_V', 'count'] | D97: [['ACCIDENTES, ENVENENAMIENTO Y VIOLENCIAS', 2990865], ['APOYO A SERVICIOS DE MEDICINA GENERAL', 92665], ['GINECO-OBSTETRICA', 9068678]] | F97: Source98_0 | G97: [['ASSSA000025', -1, 1, 2009, 2919, nan, 'ACCIDENTES, ENVENENAMIENTO Y VIOLENCIAS'], ['ASSSA000025', 1, 2, 2009, 2236, 'URGENCIA CALIFICADA', 'MEDICA'], ['ASSSA000025', 1, 3, 2009, 38, 'URGENCIA CALIFICADA', 'QUIRURGICA']] | H97: ['CLUES', 'TIPOURGENCIA', 'MOTATE', 'YEAR', 'count', 'TIPOURGENCIA_V', 'MOTATE_V'] | T97: fail | V97: ERROR: Error: ERROR: invalid input syntax for type integer: "HGZ" CONTEXT: COPY source98_1, line 10, column CLAVE DE TIPOLOGIA: "HGZ"
